Workbook

Sheet Read Me
A1: ISRM internal pricing model
A2: Version date | B2: 2026-10-01
A3: Status | B3: DRAFT — Phase 1 baseline audit only; not client-facing
A4: Purpose | B4: Formula-driven starting point for the revised, non-linear proposal model.
A5: Color key | B5: Gold cells are source inputs; blue cells are formulas; gray cells are notes or unresolved items.
A6: Pricing boundary | B6: This section audits the historical estimate and compares a historical-hour assumption with published hourly bands. It is not a quote.
A7: Source rule | B7: Every numeric input has a unit, period, status, and source locator in Inputs/Sources. No FX conversion is included.
A8: Known scope gaps | B8: Feature-level effort, live database environment/schema, user load, support plan, vendor choices, IP terms, and visitor-IP retention remain unresolved.
A9: Privacy boundary | B9: Do not collect visitor IP addresses until notice, legal basis, retention, access controls, and secure storage are agreed. Operator-only visibility does not remove those obligations.
A10: Next gate | B10: Review this baseline slice before estimating feature-level work and SaaS scenarios.

Sheet Inputs
A1: Input | B1: Value | C1: Unit | D1: Period | E1: Status | F1: Origin / locator | G1: Notes
A2: Historical planned effort | B2: 620 | C2: person-hours | D2: one-time; old MVP scope | E2: ⚠ ASSUMPTION | F2: ISRM_Internal_Product_Architecture_Roadmap_and_Pricing.md §§1, 10.1–10.2 | G2: Historical baseline only; scope has changed.
A3: Clutch Ukraine band lower endpoint | B3: 25 | C3: USD / provider-hour | D3: 2026 published band | E3: Source-reported | F3: Clutch Software Development Pricing Guide, updated 2026-09-21 | G3: Published band endpoint, not a national floor.
A4: Clutch Ukraine band upper endpoint | B4: 49 | C4: USD / provider-hour | D4: 2026 published band | E4: Source-reported | F4: Clutch Software Development Pricing Guide, updated 2026-09-21 | G4: Band endpoint, not a national maximum or a bespoke quote.
A5: Clutch US band lower endpoint | B5: 50 | C5: USD / provider-hour | D5: 2026 published band | E5: Source-reported | F5: Clutch Software Development Pricing Guide, updated 2026-09-21 | G5: Published band endpoint, not a national floor.
A6: Clutch US band upper endpoint | B6: 99 | C6: USD / provider-hour | D6: 2026 published band | E6: Source-reported | F6: Clutch Software Development Pricing Guide, updated 2026-09-21 | G6: Band endpoint, not a national maximum or a bespoke quote.
A7: Upwork global band lower endpoint | B7: 10 | C7: USD / freelancer-hour | D7: page accessed 2026-10-01 | E7: Source-reported | F7: Upwork Software Developer Cost page | G7: Global freelancer context only; not region-comparable to Clutch.
A8: Upwork global band upper endpoint | B8: 100 | C8: USD / freelancer-hour | D8: page accessed 2026-10-01 | E8: Source-reported | F8: Upwork Software Developer Cost page | G8: Global freelancer context only; not region-comparable to Clutch.
A9: Upwork global median | B9: 20 | C9: USD / freelancer-hour | D9: page accessed 2026-10-01 | E9: Source-reported | F9: Upwork Software Developer Cost page | G9: Global page median; not a company billing rate.
A10: Historical reserve | B10: 0.1 | C10: fraction of base estimate | D10: one-time; old MVP scope | E10: ⚠ ASSUMPTION | F10: ISRM_Internal_Product_Architecture_Roadmap_and_Pricing.md §10.1 | G10: Internal planning input, not a validated contingency policy.
A11: Historical rounding increment | B11: 100 | C11: EUR | D11: one-time; old MVP scope | E11: Documented convention | F11: ISRM_Internal_Product_Architecture_Roadmap_and_Pricing.md §10.1 | G11: Old estimate rounded to the nearest €100; not yet approved for the new model.
A12: Minimum advance | B12: 0.3 | C12: fraction of confirmed project estimate | D12: per contract | E12: User-approved minimum | F12: User instruction in current conversation | G12: Only the minimum advance is set; later milestone percentages remain configurable.
A13: Supabase Pro subscription | B13: 25 | C13: USD / organization-month | D13: current public price; accessed 2026-10-01 | E13: Source-reported; candidate | F13: Supabase Pricing | G13: Not treated as selected production hosting or total SaaS cost.
... A19: Cloudflare CPU overage | B19: 0.02 | C19: USD / additional million CPU milliseconds | D19: current public price; accessed 2026-10-01 | E19: Source-reported; candidate | F19: Cloudflare Workers Pricing | G19: Requires actual CPU usage.

Sheet Sources
A1: Source ID | B1: Source / locator | C1: Exact fact used | D1: Unit / period | E1: Accessed / published | F1: How it is used | G1: Limit / status | H1: URL
A2: INT-WBS | B2: Internal architecture and pricing roadmap §§1, 10.1–10.2 | C2: Role plan totals 620 hours and €49,170 base; 10% reserve; rounded discussion estimate €54,100. | D2: person-hours; EUR/hour; EUR one-time | E2: Document dated 2026-09-26 | F2: Historical arithmetic audit only. | G2: Internal planning assumptions; not approved for the expanded scope or as a quote.
A3: CLUTCH-UA | B3: Clutch Software Development Pricing Guide | C3: Ukraine provider rate band $25–$49 per hour. | D3: USD / provider-hour | E3: Updated 2026-09-21 | F3: Reference scenario uses the upper endpoint only. | G3: The endpoint is not a country maximum; data is not a matched quote. | H3: https://clutch.co/developers/pricing
A4: CLUTCH-US | B4: Clutch Software Development Pricing Guide | C4: United States provider rate band $50–$99 per hour. | D4: USD / provider-hour | E4: Updated 2026-09-21 | F4: Reference scenario uses the upper endpoint only. | G4: The endpoint is not a country maximum; data is not a matched quote. | H4: https://clutch.co/developers/pricing
A5: UPWORK | B5: Upwork Software Developer Cost page | C5: Global freelancer range $10–$100/hour; median $20/hour. | D5: USD / freelancer-hour | E5: Accessed 2026-10-01 | F5: Broad context only; do not blend with company rates. | G5: Not a geographic or provider-type match to Clutch. | H5: https://www.upwork.com/hire/software-developers/cost
A6: SUPABASE | B6: Supabase Pricing and Compute/Disk docs | C6: Pro subscription $25/month; $10 compute credits; Micro compute starts at $10/month per project. | D6: USD / organization-month and project-month | E6: Accessed 2026-10-01 | F6: Candidate recurring infrastructure inputs for a future scenario. | G6: Supabase direction exists, but data source-of-truth, environment, schema, and project topology are unresolved. | H6: https://supabase.com/pricing
A7: CLOUDFLARE | B7: Cloudflare Workers Pricing | C7: Paid plan $5/month; 10 million requests and 30 million CPU-ms included; additional request/CPU pricing is usage-based. | D7: USD / account-month and usage units | E7: Accessed 2026-10-01 | F7: Candidate hosting input only. | G7: Not a complete bill; account allocation and actual usage are unknown. | H7: https://developers.cloudflare.com/workers/platform/pricing
A8: GEMINI | B8: Google Gemini API Pricing | C8: Paid API pricing varies by model, input/output tokens, and optional tools such as grounding. | D8: USD / model-specific usage units | E8: Accessed 2026-10-01 | F8: No numeric model cost used in this slice. | G8: No AI model or usage profile has been selected. | H8: https://ai.google.dev/gemini-api/docs/pricing

Sheet Legacy Baseline
A1: Historical estimate audit — not current scope pricing
A2: Role | B2: Planned hours | C2: Planning rate (EUR/hour) | D2: Line amount (EUR) | E2: Input status | F2: Origin
A3: Product/Business Analyst | B3: 68 | C3: 80 | D3: =B3*C3 | E3: ⚠ ASSUMPTION | F3: Internal roadmap §10.1
A4: UX/UI Designer | B4: 56 | C4: 70 | D4: =B4*C4 | E4: ⚠ ASSUMPTION | F4: Internal roadmap §10.1
A5: Solution Architect / Tech Lead | B5: 52 | C5: 100 | D5: =B5*C5 | E5: ⚠ ASSUMPTION | F5: Internal roadmap §10.1
A6: Full-stack Engineer | B6: 226 | C6: 80 | D6: =B6*C6 | E6: ⚠ ASSUMPTION | F6: Internal roadmap §10.1
A7: Graph / Data Visualization Engineer | B7: 72 | C7: 85 | D7: =B7*C7 | E7: ⚠ ASSUMPTION | F7: Internal roadmap §10.1
A8: QA Engineer | B8: 76 | C8: 60 | D8: =B8*C8 | E8: ⚠ ASSUMPTION | F8: Internal roadmap §10.1
A9: DevOps / Application Security | B9: 38 | C9: 95 | D9: =B9*C9 | E9: ⚠ ASSUMPTION | F9: Internal roadmap §10.1
A10: Project/Delivery Manager | B10: 32 | C10: 70 | D10: =B10*C10 | E10: ⚠ ASSUMPTION | F10: Internal roadmap §10.1
A11: Base total | B11: =SUM(B3:B10) | D11: =SUM(D3:D10) | E11: Formula | F11: Calculated from role rows
A12: Reserve rate | B12: =Inputs!B10 | D12: =D11*B12 | E12: Formula + source input | F12: Internal roadmap §10.1
A13: Exact total before display rounding | D13: =D11+D12 | E13: Formula | F13: Base + reserve
A14: Historical rounded discussion amount | D14: =ROUND(D13/Inputs!B11,0)*Inputs!B11 | E14: Formula | F14: Nearest €100 per old document
A15: Minimum advance at 30% of rounded amount | B15: =Inputs!B12 | D15: =D14*B15 | E15: Formula + user-approved minimum | F15: 30% is a minimum; payment milestones are not agreed
A16: Balance after minimum advance | D16: =D14-D15 | E16: Formula | F16: Unallocated remainder; do not infer milestone split

Sheet Rate Benchmark
A1: Historical-hour scenario against published Clutch band endpoints
A2: Measure | B2: Value | C2: Unit | D2: Formula / source | E2: Status and caveat
A3: Historical planned effort | B3: =Inputs!B2 | C3: person-hours | D3: Inputs!B2 | E3: ⚠ ASSUMPTION; old scope only
A4: Ukraine published upper endpoint | B4: =Inputs!B4 | C4: USD / provider-hour | D4: Clutch, 2026 published band | E4: Reference endpoint, not a national maximum
A5: Ukraine reference total | B5: =B3*B4 | C5: USD one-time | D5: Historical hours × published band endpoint | E5: Illustrative only; not a quote
A6: US published upper endpoint | B6: =Inputs!B6 | C6: USD / provider-hour | D6: Clutch, 2026 published band | E6: Reference endpoint, not a national maximum
A7: US reference total | B7: =B3*B6 | C7: USD one-time | D7: Historical hours × published band endpoint | E7: Illustrative only; not a quote
A8: Comparability limit | B8: The two totals use the same historical effort assumption but not matched proposals, team composition, risk, scope, taxes, support, IP terms, or service levels. | E8: No FX conversion; old internal total remains EUR.

Sheet Scope and Gaps
A1: Requirement / work package | B1: Current evidence | C1: Target behavior / requirement | D1: Estimate status | E1: Open input / gate
A2: One-page workspace and graph modes | B2: The root route currently renders network, coordinator, and proposal sections vertically. Config state defines network/platform/dependencies values, but no mode-switch use was found. | C2: One page with explicit switching among network graph, feature graph, and DEPENDENCIES/MIX view; graph layers can be toggled. | D2: TBD — no role-hour breakdown | E2: Confirm final visible label and any required keyboard/touch behavior during UI review.
A3: FUNCTION → FEATURE interaction | B3: The proposal catalog has service dependency IDs; there is no separate FUNCTION entity or function-to-feature map. | C3: Selecting a function opens a non-full-screen feature frame; approving the feature accepts it and all linked functions. | D3: TBD — new interaction/workflow | E3: Define the demo function set and the blank client-request template fields.
A4: Feature cancellation and loss confirmation | B4: Current feature helper toggles one feature ID and does not cascade related function choices. | C4: Cancellation shows lost functionality and asks for confirmation; only confirmed cancellation removes the feature and linked functions. | D4: TBD — new interaction/workflow | E4: Specify whether the warning has cancel/confirm actions and how selections are restored.
A5: Client-request function templates | B5: No blank function-template model was found in proposal config. | C5: Keep editable blank templates separate from demonstration functions; do not seed invented client requirements. | D5: TBD — content and UI | E5: Template fields need confirmation after the demo catalog is mapped.
A6: Live table-backed graph | B6: Network server function reads local experts.json; generated Supabase Database type has no application tables; access contract says final source of truth/import are unapproved. | C6: Graph reflects authorized table changes on refresh or a defined live-update mechanism. | D6: TBD — architecture and implementation | E6: Choose existing project/environment, source-of-truth, schema, refresh semantics, RLS, and migration permission. No data was imported.
A7: Operator-only visit IP records | B7: No IP collection/logging code was found in src. | C7: Keep visitor network addresses out of the visitor UI and restrict access to authorized operator(s). | D7: TBD — data handling and operations | E7: Before implementation decide legal notice/basis, retention, access audit, secure storage, and deletion process. No collection is being added in this slice.
A8: Trust / Influence / Projects signals | B8: Trust is a heuristic; the current replay changes demo verification state. No source-backed Influence or Projects score fields were found. | C8: Label prototype status; do not show fabricated numeric scores or use them for access/selection. | D8: TBD — methodology and data source | E8: Define objective evidence, metrics, corrections/appeals, and provenance before numerical displays.
A9: Fixed core plus variable features | B9: Current proposal sums static service prices; no non-disableable cost base or function-level effort estimates. | C9: Price unavoidable architecture/team separately; feature work follows dependency-aware effort estimates. | D9: TBD — requires reviewed work breakdown | E9: Confirm historical 620 hours are only a comparison baseline, not the new estimate.
A10: Managed SaaS and external usage | B10: No production hosting/data source or expected load is fixed. | C10: Separate recurring platform/support/maintenance/optional PM from AI/OSINT and other metered pass-through costs. | D10: TBD — scenario inputs | E10: Users/tenants/requests/storage/retention, support hours, provider selection, margin/tax, and currency.
A11: Partnership and source-code transfer | B11: Existing document treats recipient/share and transfer rights as open commercial/legal choices. | C11: Keep revenue share/recipient variable; make IP transfer highest-priced alternative, rights explicitly defined. | D11: TBD — not numerically priced | E11: No share %, recipient, exclusivity, reuse rights, or buyout factor set.
