Workbook

Sheet Registry & Sources
A1: ISRM pilot cohort 2 — financial feasibility & registry v1
A2: Last updated | B2: 2026-10-07
A3: Currency | B3: GBP
A4: Status legend
A5: verified
A6: assumption · conservative indicative
A7: assumption · unverified
A8: historical/inactive
A9: Tier legend
A10: T1 anchor
A11: T2 derived
A12: T3 package total
A13: T4 scenario
A14: T5 module line
A16: Verified Tier 1 anchors
A17: Code | B17: Value | C17: Unit | D17: Period | E17: Source / note | F17: Source URL | G17: Tier | H17: Status
A18: ISRM-EXT-BLS-DEV-MEAN | B18: 66.4 | C18: USD/h mean | D18: May 2023 | E18: BLS OEWS SOC 15-1252 software developer mean wage | F18: https://www.bls.gov/oes/2023/may/oes151252.htm | G18: T1 | H18: verified
A19: ISRM-EXT-BLS-DEV-P90 | B19: 100.3 | C19: USD/h 90th pct | D19: May 2023 | E19: BLS OEWS SOC 15-1252 90th percentile | F19: https://www.bls.gov/oes/2023/may/oes151252.htm | G19: T1 | H19: verified
A20: ISRM-EXT-CLUTCH-UA | B20: 37 | C20: USD/h band midpoint | D20: 2024-Q3 | E20: Clutch UA band $25-$49 midpoint; unverified retrieval | F20: https://clutch.co/developers/pricing | G20: T1 | H20: assumption · unverified
A21: ISRM-EXT-DOU-ARCH | B21: 48.5 | C21: GBP/h gross | D21: Nov-Dec 2024 | E21: DOU.ua Winter 2025 System Architect median net → gross | F21: https://dou.ua/lenta/articles/salary-report-devs-winter-2025/ | G21: T3/4 | H21: verified
A22: ISRM-EXT-LON-TECH | B22: 100 | C22: GBP/h median upper | D22: 2024 | E22: IT Jobs Watch UK senior contractor median | F22: https://www.itjobswatch.co.uk/ | G22: T1 | H22: assumption · conservative indicative
A23: ISRM-PILOT-LI-FOLLOWERS | B23: 8742 | C23: LinkedIn Page followers | D23: snapshot 2026-08-28 | E23: ISRM Ukraine CRM Dashboard Table 1 — LinkedIn public snapshot | F23: ISRM_Pilot_CRM | G23: T1 | H23: verified
A24: ISRM-PILOT-LI-EMP | B24: 44 | C24: LinkedIn associated employee profiles | D24: snapshot 2026-08-28 | E24: Same CRM Dashboard file | F24: ISRM_Pilot_CRM | G24: T1 | H24: verified
A25: ISRM-PILOT-LI-CO-SIZE | B25: 10001+ | C25: 10001+ | D25: snapshot 2026-08-28 | E25: Page-level setting, NOT a member count | F25: ISRM_Pilot_CRM | G25: T1 | H25: verified
A26: ISRM-PILOT-LI-NO-FOLLOWERS-EXPORT | B26: not available | C26: not available | D26: snapshot 2026-08-28 | E26: No exportable follower list | F26: ISRM_Pilot_CRM | G26: T1 | H26: verified
A27: ISRM-PILOT-LI-GROUP-OBS | B27: 11750 | C27: LinkedIn group members (screenshot) | D27: capture date not recorded | E27: User-supplied screenshot; not used as denominator | F27: user-screenshot | G27: T5 | H27: assumption · unverified
A29: Pilot cohort 2 funnel — conservative indicative rates
A30: Code | B30: Conservative rate | C30: Funnel step | D30: Lower band | E30: Upper band | F30: Public benchmark anchors | G30: Why this rate | H30: Source URLs
A31: ISRM-PILOT-CONV-R1-APP | B31: 0.02 | C31: Reach → application | D31: 0.008 | E31: 0.05 | F31: Rival IQ median 0.41% by follower (2024); Bigeye prof-services 2.15%; Rossell assoc free-trial 3-5% | G31: Below 2.0% — niche single-country chapter / passive follower reach (Rival IQ 0.41%, Bigeye 2.15%) | H31: rivaliq.com + bigeyeagency.com (see registry §7e.2) | I31: T5 | J31: assumption · conservative indicative · cross-referenced ≥ 2 sources
A32: ISRM-PILOT-CONV-R2-ACC | B32: 0.3 | C32: Application → accepted | D32: 0.15 | E32: 0.3 | F32: Glue Up opportunity-to-committed 15-30%; Rossell free-trial 20-30% | G32: Upper Glue Up band; assumes manual review / LinkedIn-verified identity gate | H32: kirro.io + linkedin.com/pulse/...rossell-kqmof | I32: T5 | J32: assumption · conservative indicative · cross-referenced ≥ 2 sources
A33: ISRM-PILOT-CONV-R3-PAID | B33: 0.25 | C33: Accepted → paid | D33: 0.2 | E33: 0.3 | F33: Rossell voluntary assoc trial-to-paid 20-30% (LinkedIn Pulse) | G33: Mid of Rossell band; permission-to-invoice raises to 50% | H33: linkedin.com/pulse/...rossell-kqmof + aro.org/.../2024-Membership-Marketing-Benchmarking | I33: T5 | J33: assumption · conservative indicative · offer-specific
A34: ISRM-PILOT-SAAS-ENGAGE | B34: 0.005 | C34: Engaged-in-services share | D34: 0.002 | E34: 0.015 | F34: Metricuno blended visitor→paid 0.2-1.5% (2024); First Page Sage visitor→freemium 13.3% (top performers only) | G34: Mid of Metricuno blended visitor→paid band; below First Page Sage top-performer freemium anchor | H34: metricuno.com + firstpagesage.com | I34: T5 | J34: assumption · conservative indicative · cross-referenced ≥ 2 sources
A36: Open inputs (client/partner provide)
A37: Code | B37: Value | C37: Unit | D37: Slot | E37: Note | F37: Tier | G37: Status
A38: ISRM-PILOT-SUB-FEE | B38: 0 | C38: GBP/paid member/year | D38: Annual subscription fee | E38: open · client input · awaiting client supply | F38: T5 | G38: open
A39: ISRM-PILOT-SAAS-PRICE | B39: 240 | C39: GBP/user/year | D39: SaaS price per engaged user | E39: £240/year = £20/month anchor; partner override allowed | F39: T5 | G39: assumption · conservative indicative · cross-referenced

Sheet Rate Card & Modules
A1: partner rate card
A2: Code | B2: Value (GBP/h) | C2: Note
A3: ISRM-RATE-PARTNER-LOW | B3: 25 | C3: Low end of Clutch UA $25-49 band converted at K_eur_usd
A4: ISRM-RATE-PARTNER-BASE | B4: 37 | C4: Midpoint of $25-49; cross-checked vs BLS
A5: ISRM-RATE-PARTNER-HIGH | B5: 49 | C5: High end of $25-49; below BLS 90th percentile $100
A7: module lines T5
A8: Code | B8: Module | C8: Package | D8: Role | E8: Hours | F8: Pay base @ £37/h
A9: ISRM-MOD-MVP-SEARCH | B9: Search | C9: 02 | D9: ops | E9: 16 | F9: =E9*37 -> 592
A10: ISRM-MOD-MVP-GRAPH | B10: Graph | C10: 02 | D10: product | E10: 32 | F10: =E10*37 -> 1184
A11: ISRM-MOD-PILOT-GRAPH | B11: Graph pilot | C11: 03 | D11: product | E11: 20 | F11: =E11*37 -> 740
A12: ISRM-MOD-PILOT-DEP | B12: Dependencies | C12: 03 | D12: product | E12: 16 | F12: =E12*37 -> 592
A13: Σ modules | E13: =SUM(E9:E12) -> 84 | F13: =SUM(F9:F12) -> 3108

Sheet Hours & Pay
A1: hours per package x role
A2: Pkg | B2: client-comms (h) | C2: ops (h) | D2: product (h) | E2: Σ hours
A3: 01 Consulting & strategy | B3: 16 | C3: 8 | D3: 24 | E3: =SUM(B3:D3) -> 48
A4: 02 Application MVP | B4: 24 | C4: 40 | D4: 80 | E4: =SUM(B4:D4) -> 144
A5: 03 Pilot functions | B5: 60 | C5: 80 | D5: 100 | E5: =SUM(B5:D5) -> 240
A6: 04 Remaining | B6: 0 | C6: 0 | D6: 0 | E6: =SUM(B6:D6) -> 0
A7: Σ per partner (01-03) | B7: =SUM(B3:B5) -> 100 | C7: =SUM(C3:C5) -> 128 | D7: =SUM(D3:D5) -> 204 | E7: =SUM(E3:E5) -> 432
A10: per-partner pay scenarios (registry §2+§3)
A11: Partner role | B11: Hours | C11: Pay low @ £25/h | D11: Pay base @ £37/h | E11: Pay high @ £49/h
A12: Client communications + business development | B12: 100 | C12: =B12*25 -> 2500 | D12: =B12*37 -> 3700 | E12: =B12*49 -> 4900
A13: Operations, OSINT, events, external communications | B13: 128 | C13: =B13*25 -> 3200 | D13: =B13*37 -> 4736 | E13: =B13*49 -> 6272
A14: Product, strategy, vendor coordination | B14: 204 | C14: =B14*25 -> 5100 | D14: =B14*37 -> 7548 | E14: =B14*49 -> 9996
A15: Σ combined | B15: =SUM(B12:B14) -> 432 | C15: =SUM(C12:C14) -> 10800 | D15: =SUM(D12:D14) -> 15984 | E15: =SUM(E12:E14) -> 21168

Sheet Per-Package x Tier
A1: per-package x tier x scenario
A2: Package | B2: Low T-1 (×1.0 £25/h) | C2: Base T-1 (×1.0 £37/h) | D2: High T-1 (×1.0 £49/h) | E2: Base T-2 (×1.5 £37/h) | F2: Base T-3 (×2.0 £37/h)
A3: 01 Consulting | B3: ='Hours & Pay'!E3*25 | C3: ='Hours & Pay'!E3*37 | D3: ='Hours & Pay'!E3*49 | E3: ='Hours & Pay'!E3*37*1.5 | F3: ='Hours & Pay'!E3*37*2.0
A4: 02 MVP | B4: ='Hours & Pay'!E4*25 | C4: ='Hours & Pay'!E4*37 | D4: ='Hours & Pay'!E4*49 | E4: ='Hours & Pay'!E4*37*1.5 | F4: N/A
A5: 03 Pilot | B5: ='Hours & Pay'!E5*25 | C5: ='Hours & Pay'!E5*37 | D5: ='Hours & Pay'!E5*49 | E5: ='Hours & Pay'!E5*37*1.5 | F5: ='Hours & Pay'!E5*37*2.0
A6: Σ 01-03 (T-1 base) | B6: =SUM(B3:B5) -> 10800 | C6: =SUM(C3:C5) -> 15984 | D6: =SUM(D3:D5) -> 21168 | E6: N/A | F6: N/A
A7: Σ 01-03 (T-2) | B7: N/A | C7: N/A | D7: N/A | E7: =SUM(E3:E5) -> 23976 | F7: N/A
A8: Σ 01-03 (T-3, where applicable) | B8: N/A | C8: N/A | D8: N/A | E8: N/A | F8: =F3+F5 -> 21312

Sheet Cohort 2 Funnel
A1: cohort 2 funnel - inputs and outputs
A2: Input / step | B2: Value | C2: Formula / derivation
A3: LinkedIn reach | B3: 8742 | C3: snapshot 2026-08-28 · ISRM-PILOT-LI-FOLLOWERS verified
A4: R1 · Reach → application | B4: 0.02 | C4: ISRM-PILOT-CONV-R1-APP · 2.0% conservative
A5: R2 · Application → accepted | B5: 0.3 | C5: ISRM-PILOT-CONV-R2-ACC · 30% conservative
A6: R3 · Accepted → paid | B6: 0.25 | C6: ISRM-PILOT-CONV-R3-PAID · 25% conservative
A7: Engaged-in-services share | B7: 0.005 | C7: ISRM-PILOT-SAAS-ENGAGE · 0.5% conservative
A8: Annual subscription fee (client input) | B8: 100 | C8: ISRM-PILOT-SUB-FEE · awaiting client input
A9: SaaS price per engaged user | B9: 240 | C9: ISRM-PILOT-SAAS-PRICE · £240/year anchor
A11: Funnel output — derived from inputs above
A12: applications | B12: =ROUND(B3*B4,0) -> 175 | C12: Reach × R1
A13: accepted | B13: =ROUND(B12*B5,0) -> 52 | C13: Applications × R2
A14: paid new members | B14: =ROUND(B13*B6,0) -> 13 | C14: Accepted × R3
A15: engaged-in-services users | B15: =ROUND(B3*B7,0) -> 44 | C15: Reach × saasEngage
A17: Two revenue views — same funnel output, two multipliers
A18: Client view · subscription revenue (year 1) | B18: =IF(B8>0,B14*B8,0) -> 1300 | C18: Paid members × subscription fee · 0 if fee not supplied
A19: Partner view · SaaS revenue (year 1, conservative) | B19: =B15*B9 -> 10560 | C19: Engaged users × SaaS price

Sheet SaaS Feasibility
A1: SaaS feasibility sensitivity (registry §7f)
A2: Effective reach | B2: Eng-share | C2: ARPU | D2: Annual SaaS revenue | E2: Implication tier | F2: Implication detail
A3: 8742 | B3: 0.005 | C3: 240 | D3: =A3*B3*C3 -> 10490.4 | E3: token | F3: Recovers nothing of partner block. Confirms §7e.6 honest.
A4: 8742 | B4: 0.02 | C4: 240 | D4: =A4*B4*C4 -> 41961.6 | E4: self-sustaining | F4: Pilot reaches above-default services engagement; covers hosting + Cloudflare + Supabase + part-time engineer
A5: 8742 | B5: 0.005 | C5: 1200 | D5: =A5*B5*C5 -> 52452 | E5: self-sustaining | F5: Pilot does not move; ARPU moves (corporate buyer pays for ten seats)
A6: 50000 | B6: 0.005 | C6: 240 | D6: =A6*B6*C6 -> 60000 | E6: self-sustaining | F6: Reach moves; engagement stays conservative. UK/US LinkedIn Page scale.
A7: 50000 | B7: 0.02 | C7: 240 | D7: =A7*B7*C7 -> 240000 | E7: real SaaS | F7: International chapter + above-default engagement. Realistic only after 12-24 months.
A8: 50000 | B8: 0.05 | C8: 600 | D8: =A8*B8*C8 -> 1500000 | E8: large SaaS | F8: Upper aspirational band; requires reach scaling + pricing tier mix shift
A11: Verdict (registry §7f.3)
A12: LinkedIn alone, year 1, does NOT support meaningful SaaS revenue. To reach £30k+/year, at least one of three parameters must move:
A13: Effective reach 8742 → 25000+ (3×)
A14: Engaged-in-services share 0.5% → 2%+ (4×)
A15: ARPU £240 → £600+/year (5×)
A16: Any one → self-sustaining; any two → real SaaS. None is year-1 deliverable for current pilot.

Sheet Payment & Excluded
A1: payment terms
A2: Code | B2: Value | C2: Description
A3: ISRM-PAY-DUE | B3: On acceptance | C3: Payment due on delivery/acceptance of each package
A4: ISRM-PAY-FIRST | B4: ≥ 30% | C4: First payment ≥ 30% of agreed total
A5: ISRM-PAY-MODULE | B5: Module-level | C5: Payment on delivery/acceptance of search/graph modules
A6: ISRM-PAY-NOINSTAL | B6: Per-delivery | C6: No invented installment split
A7: ISRM-PAY-INDICATIVE | B7: INDICATIVE | C7: All totals are INDICATIVE pending scope and budget-ceiling approval
A10: excluded & historical-inactive items
A11: Code | B11: Excluded item | C11: Why excluded
A12: ISRM-EXCL-HOSTING | B12: Hosting | C12: Not in MVP
A13: ISRM-EXCL-AIAPI | B13: AI / API usage | C13: Not in MVP
A14: ISRM-EXCL-LEGAL | B14: Legal & privacy work | C14: Not in MVP
A15: ISRM-EXCL-REUSE | B15: Reuse compensation | C15: Pending agreement
A16: ISRM-EXCL-TAX | B16: Tax & ongoing support | C16: Out of scope
A17: ISRM-EXCL-CONF | B17: LinkedIn confirmed experts | C17: Awaiting pilot measurement
A18: ISRM-EXCL-MULT | B18: M = 3.0 (Maister / AIA DPE) | C18: Historical/inactive
A19: ISRM-EXCL-2080H | B19: 2 080 h greenfield €66 090 | C19: Historical/inactive
A20: ISRM-EXCL-198K | B20: Commercial €198 270 | C20: Historical/inactive
A21: ISRM-EXCL-54100 | B21: Base MVP €54 100 | C21: Historical/inactive
A22: ISRM-EXCL-OSINT | B22: AI OSINT 480 h × €45/h × 3 = €64 800 | C22: Historical/inactive
A23: ISRM-EXCL-TRANCHE | B23: Tranches 30/40/30 | C23: Historical/inactive

Sheet Unit Economics
A1: unit economics
A2: Code | B2: Action | C2: Partner time (h) | D2: Fee @ base £37/h | E2: Tier gate
A3: ISRM-UE-CONTRIB | B3: 1 contribution | C3: 0.5 | D3: 18.5 | E3: all
A4: ISRM-UE-ARTICLE | B4: 1 article | C4: 8-16 | D4: 296-592 | E4: T-2/T-3
A5: ISRM-UE-PLACE | B5: 1 placement | C5: 0 | D5: 0 | E5: system
A6: ISRM-UE-SERVICE | B6: 1 client service | C6: 2-4 | D6: 74-148 | E6: all
A7: ISRM-UE-CONF | B7: 1 conference participation | C7: 8-16 | D7: 296-592 | E7: T-2/T-3
A8: ISRM-UE-OSINT | B8: 1 OSINT search | C8: 0.5 | D8: 18.5 | E8: T-3
A11: fee tiers T1 overlay
A12: Code | B12: Tier | C12: Multiplier | D12: Description | E12: Capacity created (KPI)
A13: ISRM-TIER-SELF | B13: T-1 | C13: ×1.0 | D13: Self-serve | E13: cycle count, publications, conferences
A14: ISRM-TIER-COPILOT | B14: T-2 | C14: ×1.5 | D14: Co-pilot | E14: + 1-on-1 sessions, agenda approved by board
A15: ISRM-TIER-OPERATE | B15: T-3 | C15: ×2.0 | D15: Operate | E15: + publications, conference plan, AI features gate
A17: go-no-go per tier
A18: Tier | B18: Go criterion | C18: No-go consequence
A19: T-1 | B19: Deliverables present, board sign-off | C19: Cycle incomplete, partner repeats at no extra fee
A20: T-2 | B20: T-1 + board approves agenda + cohort 2 measured + sessions held ≥ agreed | C20: Cycle pauses; partner waits for board
A21: T-3 | B21: T-2 + TII coverage measured + AI ethics approved | C21: Forward features deferred; partner keeps base cycle
A23: KPIs per function (registry §7c)
A24: Code | B24: Function | C24: KPI | D24: Capacity | E24: Gate
A25: ISRM-KPI-SEARCH | B25: Search | C25: query response time | D25: < 1s for n=100 | E25: always on
A26: ISRM-KPI-GRAPH | B26: Graph | C26: nodes rendered | D26: 178 → 1 000 | E26: always on
A27: ISRM-KPI-DEPENDENCY | B27: Dependency | C27: edges resolved | D27: per function spec | E27: always on
A28: ISRM-KPI-CYCLE | B28: Pilot cycle | C28: completed/quarter | D28: 1 → 4 | E28: T-1+
A29: ISRM-KPI-PUBLICATION | B29: Publication | C29: articles/cycle | D29: 2 baseline | E29: T-2/T-3
A30: ISRM-KPI-CONF | B30: Conference plan | C30: plan ready by cycle end | D30: yes/no | E30: T-2/T-3
A31: ISRM-KPI-OSINT | B31: AI OSINT | C31: queries/cycle | D31: 50 baseline | E31: T-3 only
A32: ISRM-KPI-CHATBOT | B32: AI chatbot | C32: interactions/user/session | D32: 3 baseline | E32: T-3 only
A33: ISRM-KPI-DASHBOARD | B33: Dashboards | C33: generated/cycle | D33: 5 baseline | E33: T-3 only
A34: ISRM-KPI-TII | B34: TII coverage | C34: measured at gate | D34: gate-conditioned | E34: T-3 · 2nd pass
