Workbook

Sheet Read Me
A1: ISRM internal pricing model
A2: Version date | B2: 2026-09-26
A3: Status | B3: DRAFT — source audit, scope boundary and pricing model; not client-facing
A4: Purpose | B4: Formula-driven starting point for the revised, non-linear proposal model.
A5: Color key | B5: Gold cells are source inputs; blue cells are formulas; gray cells are notes or unresolved items.
A6: Pricing boundary | B6: This section preserves the historical estimate as source context only. The 620-hour total is excluded from future pricing comparisons and new feature estimates; it is not a quote.
A7: Source rule | B7: Every numeric input has a unit, period, status, and source locator in Inputs/Sources. No FX conversion is included.
A8: Known scope gaps | B8: Feature-level effort, live database environment/schema, user load, support plan, vendor choices, IP terms, and visitor-IP retention remain unresolved.
A9: Privacy boundary | B9: Do not collect visitor IP addresses until notice, legal basis, retention, access controls, and secure storage are agreed. Operator-only visibility does not remove those obligations.
A10: Next gate | B10: Review greenfield fixed-core effort assumptions before estimating optional modules and pre-contract tooling.

Sheet Inputs
A1: Input | B1: Value | C1: Unit | D1: Period | E1: Status | F1: Origin / locator | G1: Notes
A2: Historical planned effort | B2: 620 | C2: person-hours | D2: one-time; old MVP scope | E2: ⚠ ASSUMPTION | F2: ISRM_Internal_Product_Architecture_Roadmap_and_Pricing.md §§1, 10.1–10.2 | G2: Historical baseline only; scope has changed.
A3: Clutch Ukraine band lower endpoint | B3: 25 | C3: USD / provider-hour | D3: 2026 published band | E3: Source-reported | F3: Clutch Software Development Pricing Guide, updated 2026-09-21 | G3: Published band endpoint, not a national floor.
A4: Clutch Ukraine band upper endpoint | B4: 49 | C4: USD / provider-hour | D4: 2026 published band | E4: Source-reported | F4: Clutch Software Development Pricing Guide, updated 2026-09-21 | G4: Band endpoint, not a national maximum or a bespoke quote.
A5: Clutch US band lower endpoint | B5: 50 | C5: USD / provider-hour | D5: 2026 published band | E5: Source-reported | F5: Clutch Software Development Pricing Guide, updated 2026-09-21 | G5: Published band endpoint, not a national floor.
A6: Clutch US band upper endpoint | B6: 99 | C6: USD / provider-hour | D6: 2026 published band | E6: Source-reported | F6: Clutch Software Development Pricing Guide, updated 2026-09-21 | G6: Band endpoint, not a national maximum or a bespoke quote.
A7: Upwork global band lower endpoint | B7: 10 | C7: USD / freelancer-hour | D7: page accessed 2026-10-01 | E7: Source-reported | F7: Upwork Software Developer Cost page | G7: Global freelancer context only; not region-comparable to Clutch.
A8: Upwork global band upper endpoint | B8: 100 | C8: USD / freelancer-hour | D8: page accessed 2026-10-01 | E8: Source-reported | F8: Upwork Software Developer Cost page | G8: Global freelancer context only; not region-comparable to Clutch.
A9: Upwork global median | B9: 20 | C9: USD / freelancer-hour | D9: page accessed 2026-10-01 | E9: Source-reported | F9: Upwork Software Developer Cost page | G9: Global page median; not a company billing rate.
A10: Historical reserve | B10: 0.1 | C10: fraction of base estimate | D10: one-time; old MVP scope | E10: ⚠ ASSUMPTION | F10: ISRM_Internal_Product_Architecture_Roadmap_and_Pricing.md §10.1 | G10: Internal planning input, not a validated contingency policy.
A11: Historical rounding increment | B11: 100 | C11: EUR | D11: one-time; old MVP scope | E11: Documented convention | F11: ISRM_Internal_Product_Architecture_Roadmap_and_Pricing.md §10.1 | G11: Old estimate rounded to the nearest €100; not yet approved for the new model.
A12: Minimum advance | B12: 0.3 | C12: fraction of confirmed project estimate | D12: per contract | E12: User-approved minimum | F12: User instruction in current conversation | G12: Only the minimum advance is set; later milestone percentages remain configurable.
A13: Supabase Pro subscription | B13: 25 | C13: USD / organization-month | D13: current public price; accessed 2026-10-01 | E13: Source-reported; candidate | F13: Supabase Pricing | G13: Not treated as selected production hosting or total SaaS cost.
... A19: Cloudflare CPU overage | B19: 0.02 | C19: USD / additional million CPU milliseconds | D19: current public price; accessed 2026-10-01 | E19: Source-reported; candidate | F19: Cloudflare Workers Pricing | G19: Requires actual CPU usage.

Sheet Sources
A1: Source ID | B1: Source / locator | C1: Exact fact used | D1: Unit / period | E1: Accessed / published | F1: How it is used | G1: Limit / status | H1: URL
A2: INT-WBS | B2: Internal architecture and pricing roadmap §§1, 10.1–10.2 | C2: Role plan totals 620 hours and €49,170 base; 10% reserve; rounded discussion estimate €54,100. | D2: person-hours; EUR/hour; EUR one-time | E2: Document dated 2026-09-26 | F2: Historical arithmetic audit only. | G2: Internal planning assumptions; not approved for the expanded scope or as a quote.
A3: CLUTCH-UA | B3: Clutch Software Development Pricing Guide | C3: Ukraine provider rate band $25–$49 per hour. | D3: USD / provider-hour | E3: Updated 2026-09-21 | F3: Reference scenario uses the upper endpoint only. | G3: The endpoint is not a country maximum; data is not a matched quote. | H3: https://clutch.co/developers/pricing
A4: CLUTCH-US | B4: Clutch Software Development Pricing Guide | C4: United States provider rate band $50–$99 per hour. | D4: USD / provider-hour | E4: Updated 2026-09-21 | F4: Reference scenario uses the upper endpoint only. | G4: The endpoint is not a country maximum; data is not a matched quote. | H4: https://clutch.co/developers/pricing
A5: UPWORK | B5: Upwork Software Developer Cost page | C5: Global freelancer range $10–$100/hour; median $20/hour. | D5: USD / freelancer-hour | E5: Accessed 2026-10-01 | F5: Broad context only; do not blend with company rates. | G5: Not a geographic or provider-type match to Clutch. | H5: https://www.upwork.com/hire/software-developers/cost
A6: SUPABASE | B6: Supabase Pricing and Compute/Disk docs | C6: Pro subscription $25/month; $10 compute credits; Micro compute starts at $10/month per project. | D6: USD / organization-month and project-month | E6: Accessed 2026-10-01 | F6: Candidate recurring infrastructure inputs for a future scenario. | G6: Supabase direction exists, but data source-of-truth, environment, schema, and project topology are unresolved. | H6: https://supabase.com/pricing
A7: CLOUDFLARE | B7: Cloudflare Workers Pricing | C7: Paid plan $5/month; 10 million requests and 30 million CPU-ms included; additional request/CPU pricing is usage-based. | D7: USD / account-month and usage units | E7: Accessed 2026-10-01 | F7: Candidate hosting input only. | G7: Not a complete bill; account allocation and actual usage are unknown. | H7: https://developers.cloudflare.com/workers/platform/pricing
A8: GEMINI | B8: Google Gemini API Pricing | C8: Paid API pricing varies by model, input/output tokens, and optional tools such as grounding. | D8: USD / model-specific usage units | E8: Accessed 2026-10-01 | F8: No numeric model cost used in this slice. | G8: No AI model or usage profile has been selected. | H8: https://ai.google.dev/gemini-api/docs/pricing
A9: CIRCLE-CAP | B9: Circle Community Managers platform page | C9: Lists member directory/profiles, discussions, events, analytics and gamification; workflows, profile fields, branded notifications and activity scores appear in a higher plan. | D9: Product capabilities; plan-dependent | E9: Accessed 2026-10-01 | F9: Capability comparison only; no pricing or outcome claims used. | G9: Vendor description; feature depth and availability vary by plan/community. | H9: https://circle.so/platform/community-managers
A10: CIRCLE-SEC | B10: Circle Data Processing Addendum, security section | C10: Describes AES-256 encryption at rest and TLS 1.2+ in transit, plus organizational controls. | D10: Security controls; current DPA | E10: Accessed 2026-10-01 | F10: Baseline security comparison; does not establish end-to-end encrypted member messaging. | G10: Vendor statement; no claim that this meets ISRM threat model. | H10: https://circle.so/dpa
A11: HIVE-CAP | B11: Hivebrite features page | C11: Lists direct messaging, events, forums, journeys, live feed, searchable member directory, groups, memberships, projects, news and people recommendations. | D11: Product capabilities | E11: Accessed 2026-10-01 | F11: Capability comparison only. | G11: Vendor feature page; not proof every capability is included in every plan. | H11: https://hivebrite.com/features
A12: HIVE-SEC | B12: Hivebrite demo/product security page | C12: Publishes ISO 27001 and PCI-DSS certification, AES-256 encryption, SSO, role-based access control and audit logs. | D12: Security controls; current page | E12: Accessed 2026-10-01 | F12: Security capability comparison. | G12: Vendor statement; scope/certification evidence and contract must be checked during procurement. | H12: https://hivebrite.com/demo
A13: VIVA-ADMIN | B13: Microsoft Learn: Manage admin roles in Viva Engage | C13: Community admins can manage members/admins and conversations, create/manage campaigns, send announcements, and control community settings; network admins can constrain community creation. | D13: Role capabilities | E13: Accessed 2026-10-01 | F13: Embedded community governance comparison. | G13: Microsoft product documentation; feature/licensing availability may vary. | H13: https://learn.microsoft.com/en-us/viva/engage/eac-key-admin-roles-permissions
A14: VIVA-ANALYTICS | B14: Microsoft Support: Track engagement in Viva Engage with analytics | C14: Community analytics include member/admin activity, engaged/reached people and dormant conversations; Microsoft states early admin engagement is associated with greater community success. | D14: Engagement metrics; product guidance | E14: Accessed 2026-10-01 | F14: Supports operator analytics and re-engagement requirements, not a guaranteed outcome. | G14: Vendor guidance/observation; association is not proof of causation or universal threshold. | H14: https://support.microsoft.com/en-us/viva/engage/track-engagement-in-viva-engage-with-analytics
... A17: CRT-GROWTH | B17: The Community Roundtable: Elevating Content & Programs for Community Growth | C17: Recommends onboarding, newsletters, member spotlights, virtual presentations and varied programming as ways to support participation and retention. | D17: Qualitative community-practice guidance | E17: Accessed 2026-10-01 | F17: Supports lifecycle and community-operations workflows; no numerical lift assumed. | G17: Practice guidance; not a causal estimate or proof that software alone creates engagement. | H17: https://communityroundtable.com/state-of-community-management/elevating-content-programs-for-community-growth

Sheet Legacy Baseline
A1: Historical Estimate — Source Record Only
A2: Role | B2: Planned hours | C2: Planning rate (EUR/hour) | D2: Line amount (EUR) | E2: Input status | F2: Origin
A3: Product/Business Analyst | B3: 68 | C3: 80 | D3: =B3*C3 | E3: ⚠ ASSUMPTION | F3: Internal roadmap §10.1
A4: UX/UI Designer | B4: 56 | C4: 70 | D4: =B4*C4 | E4: ⚠ ASSUMPTION | F4: Internal roadmap §10.1
A5: Solution Architect / Tech Lead | B5: 52 | C5: 100 | D5: =B5*C5 | E5: ⚠ ASSUMPTION | F5: Internal roadmap §10.1
A6: Full-stack Engineer | B6: 226 | C6: 80 | D6: =B6*C6 | E6: ⚠ ASSUMPTION | F6: Internal roadmap §10.1
A7: Graph / Data Visualization Engineer | B7: 72 | C7: 85 | D7: =B7*C7 | E7: ⚠ ASSUMPTION | F7: Internal roadmap §10.1
A8: QA Engineer | B8: 76 | C8: 60 | D8: =B8*C8 | E8: ⚠ ASSUMPTION | F8: Internal roadmap §10.1
A9: DevOps / Application Security | B9: 38 | C9: 95 | D9: =B9*C9 | E9: ⚠ ASSUMPTION | F9: Internal roadmap §10.1
A10: Project/Delivery Manager | B10: 32 | C10: 70 | D10: =B10*C10 | E10: ⚠ ASSUMPTION | F10: Internal roadmap §10.1
A11: Base total | B11: =SUM(B3:B10) | D11: =SUM(D3:D10) | E11: Formula | F11: Calculated from role rows
A12: Reserve rate | B12: =Inputs!B10 | D12: =D11*B12 | E12: Formula + source input | F12: Internal roadmap §10.1
A13: Exact total before display rounding | D13: =D11+D12 | E13: Formula | F13: Base + reserve
A14: Historical rounded discussion amount | D14: =ROUND(D13/Inputs!B11,0)*Inputs!B11 | E14: Formula | F14: Nearest €100 per old document
A15: Minimum advance at 30% of rounded amount | B15: =Inputs!B12 | D15: =D14*B15 | E15: Formula + user-approved minimum | F15: 30% is a minimum; payment milestones are not agreed
A16: Balance after minimum advance | D16: =D14-D15 | E16: Formula | F16: Unallocated remainder; do not infer milestone split

Sheet Scope and Gaps
A1: Requirement / work package | B1: Current evidence | C1: Target behavior / requirement | D1: Estimate status | E1: Open input / gate
A2: One-page workspace and graph modes | B2: The root route currently renders network, coordinator, and proposal sections vertically. Config state defines network/platform/dependencies values, but no mode-switch use was found. | C2: One page with explicit switching among network graph, feature graph, and DEPENDENCIES/MIX view; graph layers can be toggled. | D2: TBD — no role-hour breakdown | E2: Confirm final visible label and any required keyboard/touch behavior during UI review.
A3: FUNCTION → FEATURE interaction | B3: The proposal catalog has service dependency IDs; there is no separate FUNCTION entity or function-to-feature map. | C3: Selecting a function opens a non-full-screen feature frame; approving the feature accepts it and all linked functions. | D3: TBD — new interaction/workflow | E3: Define the demo function set and the blank client-request template fields.
A4: Feature cancellation and loss confirmation | B4: Current feature helper toggles one feature ID and does not cascade related function choices. | C4: Cancellation shows lost functionality and asks for confirmation; only confirmed cancellation removes the feature and linked functions. | D4: TBD — new interaction/workflow | E4: Specify whether the warning has cancel/confirm actions and how selections are restored.
A5: Client-request function templates | B5: No blank function-template model was found in proposal config. | C5: Keep editable blank templates separate from demonstration functions; do not seed invented client requirements. | D5: TBD — content and UI | E5: Template fields need confirmation after the demo catalog is mapped.
A6: Live table-backed graph | B6: Network server function reads local experts.json; generated Supabase Database type has no application tables; access contract says final source of truth/import are unapproved. | C6: Graph reflects authorized table changes on refresh or a defined live-update mechanism. | D6: TBD — architecture and implementation | E6: Choose existing project/environment, source-of-truth, schema, refresh semantics, RLS, and migration permission. No data was imported.
A7: Operator-only visit IP records | B7: No IP collection/logging code was found in src. | C7: Keep visitor network addresses out of the visitor UI and restrict access to authorized operator(s). | D7: TBD — data handling and operations | E7: Before implementation decide legal notice/basis, retention, access audit, secure storage, and deletion process. No collection is being added in this slice.
A8: Trust / Influence / Projects signals | B8: Trust is a heuristic; the current replay changes demo verification state. No source-backed Influence or Projects score fields were found. | C8: Label prototype status; do not show fabricated numeric scores or use them for access/selection. | D8: TBD — methodology and data source | E8: Define objective evidence, metrics, corrections/appeals, and provenance before numerical displays.
A9: Fixed core plus variable features | B9: Current proposal sums static service prices; no non-disableable cost base or function-level effort estimates. | C9: Price unavoidable architecture/team separately; feature work follows dependency-aware effort estimates. | D9: TBD — requires reviewed work breakdown | E9: Confirm historical 620 hours are only a comparison baseline, not the new estimate.
A10: Managed SaaS and external usage | B10: No production hosting/data source or expected load is fixed. | C10: Separate recurring platform/support/maintenance/optional PM from AI/OSINT and other metered pass-through costs. | D10: TBD — scenario inputs | E10: Users/tenants/requests/storage/retention, support hours, provider selection, margin/tax, and currency.
A11: Partnership and source-code transfer | B11: Existing document treats recipient/share and transfer rights as open commercial/legal choices. | C11: Keep revenue share/recipient variable; make IP transfer highest-priced alternative, rights explicitly defined. | D11: TBD — not numerically priced | E11: No share %, recipient, exclusivity, reuse rights, or buyout factor set.
A12: Presentation demo access credential | B12: resolveAccess() contains a hard-coded fallback coordinator credential in src/lib/experts.server.ts; no value is reproduced here. | C12: No source-code fallback; without configured secret, access stays at guest level. Treat the exposed fallback as compromised. | D12: Security gate; not yet modified | E12: Before external sharing, remove fallback and confirm how authorized coordinator access is supplied outside source control.

Sheet Scope Mapping
A1: Recommended core and optional boundary — review before new effort estimates
A2: Market comparison is based on published capability lists from Circle, Hivebrite, Viva Engage and Salesforce Experience Cloud. These are examples, not a universal standard. No historical hours or old package prices are used as new estimate inputs.
A3: Cost treatment | B3: Feature ID | C3: Feature / module | D3: Candidate functions | E3: Prerequisites / dependencies | F3: Evidence and basis | G3: Estimate readiness | H3: Boundary or unresolved decision
A4: Fixed core | B4: core-access | C4: Access, consent, security and audit | D4: Least-privilege role checks; guest/member disclosure; consent and retention controls; encrypted transport/storage requirements; audit sensitive reads/writes; incident and deletion controls. | E4: Identity and tenant model; threat model; operator roles. | F4: User-approved access direction; Access Contract; CIRCLE-SEC; HIVE-SEC; SALESFORCE-GUEST. | G4: Fixed core; security requirements not costed yet | H4: Baseline application/data security is core. End-to-end encrypted member messaging is not established by the cited sources and needs a separate threat-model decision.
A5: Fixed core | B5: core-data-operator | C5: Live data and operator workspace | D5: Authorized source-of-truth; operator CRUD/review; evidence and profile updates; change history; graph reflects approved data changes. | E5: Database/environment; schema; RLS; access and audit. | F5: User-approved live-table requirement; current network.functions.ts reads local experts.json; Supabase types currently have no application tables. | G5: Fixed core; blocked on architecture inputs | H5: Choose project/environment, source of truth, schema, refresh semantics, RLS and any migration/import permission. No CRM import is approved.
A6: Fixed core for ISRM experience | B6: core-network-workspace | C6: One-page network and feature workspace | D6: Explicit NETWORK / PLATFORM CONFIGURATOR / DEPENDENCIES modes; expert/feature graph; toggleable layers; filters, sectors, territories and network panels; touch/keyboard support; text graph equivalent. | E6: Live data; expert search; approved graph entities. | F6: User-approved interaction requirements; current proposal-config.ts defines modes/layers but root route is vertically stacked. | G6: ISRM differentiator; fixed-core candidate | H6: This is part of the selected ISRM experience, not a universal community-platform requirement. Validate panel count, labels and mobile behavior.
A7: Separate pre-contract tooling | B7: core-configurator-pdf | C7: Function-to-feature configurator and validated-scope PDF | D7: Function dossier; feature/function selection and cancellation warning; dependencies; stack confirmation; planning range; PDF and approval/request capture. | E7: Approved function-feature map; estimate engine; PDF/submission; access. | F7: User-approved configurator and working-scope PDF requirement; current proposal route is a local demo and contains static prices. | G7: Separate workstream; not community-platform core | H7: Treat as proposal/scope-generation tooling, not a non-removable capability of the commissioned community. PDF is not a contract. Payment/IP choices affect the commercial offer.
A8: Fixed core — domain requirement | B8: expert-search | C8: Expert search and dossiers | D8: Search by expertise, geography, sector and experience; show privacy-aware profile and evidence; control field visibility by role/consent. | E8: Access/consent; live data; verified expertise vocabulary. | F8: Current SERVICE_CATALOG entry `expert-search`; user-approved network graph/search direction; CIRCLE-CAP; HIVE-CAP. | G8: Fixed core; function design review needed | H8: Generic directories do not verify expertise. Keep evidence/provenance in the core; exact checks and fields remain to be agreed.
A9: Optional advanced module | B9: service-war-room | C9: Network map and War Room | D9: Advanced situational context; alert ownership; operational coordination; external World Monitor hand-off. | E9: Core directory/graph; live data; access rules; optional external source. | F9: Current SERVICE_CATALOG entry `service-war-room`; declared dependency on `expert-search`. | G9: Optional; estimate delta only | H9: Basic expert/network graph is in core. Advanced War Room workflows and external integration are removable scope.
A10: Optional advanced module; basic opportunities stay in core | B10: service-projects | C10: Advanced project management and expert-request workflows | D10: Multi-stage project/request workflows, task ownership, approvals, invitation orchestration and project records beyond basic group posts/opportunities. | E10: Core directory, groups, access and audit. | F10: Current SERVICE_CATALOG entry `service-projects`; declared dependency on `expert-search`; user distinguished complex project management as optional. | G10: Optional; estimate delta only | H10: Keep lightweight opportunity/activity sharing in core groups. Scope the complex PM workflow separately.
A11: Optional automation extension; basic growth is core | B11: service-recruitment | C11: Recruitment campaign automation | D11: Sector/territory campaign administration; channel integrations; bulk outreach; AI-assisted triage at scale. | E11: Core member-growth pipeline; consent; approved providers. | F11: Current `service-recruitment` catalog plus user-approved active recruitment and AI-assisted checks. | G11: Optional automation; core human-controlled growth included | H11: Core includes intake, source attribution, objective evidence review and onboarding. AI does not independently verify a person; messaging automation and vendors are separate.
A12: Optional advanced module | B12: service-research | C12: Expert discussions and research | D12: Question briefs; participant composition; evidence packs; synthesis with caveats and dissent. | E12: Core directory/groups; source and attribution rules. | F12: Current SERVICE_CATALOG entry `service-research`; declared dependency on `expert-search`. | G12: Optional; estimate delta only | H12: Facilitated research and decision-ready synthesis are not baseline community functions.
A13: Optional advanced module | B13: service-public-engagement | C13: Public campaigns and hearings | D13: Public engagement plans; stakeholder mapping; submissions; moderation and response matrices. | E13: Core groups; accessibility, safeguarding and moderation policy. | F13: Current SERVICE_CATALOG entry `service-public-engagement`; declared dependency on `service-projects`. | G13: Optional; estimate delta only | H13: A specialist public-engagement workflow, not basic community discussion.
A14: Optional advanced module | B14: service-leads | C14: Consulting lead generation | D14: External needs intake; qualification; candidate team assembly; commercial follow-up. | E14: Core expert directory; separately agreed commercial process. | F14: Current SERVICE_CATALOG entry `service-leads`; declared dependencies on `expert-search` and `service-projects`. | G14: Optional; estimate delta only | H14: Lead sources, qualification criteria and commercial ownership remain open.
... A28: Fixed core — operating capability | B28: core-engagement-operations | C28: Group administration and engagement loop | D28: Assign group owners/moderators; set purpose and access; seed useful content/programs; route questions/comments to an owner; close response loops; track reach/participation and dormant groups; support targeted re-engagement. | E28: Core groups, notifications, moderator roles and analytics. | F28: VIVA-ADMIN; VIVA-ANALYTICS; CRT-GROWTH. | G28: Fixed core tools; operational staffing/content is a separate recurring service assumption. | H28: Software can expose and support the loop but cannot guarantee activity. Owner, response expectations, content plan and cadence require an operating model.

Sheet Capability Benchmark
A1: What belongs in the non-removable ISRM core? — external benchmark and critical boundary
A2: Critical reading: comparable platforms show recurring capabilities, not a universal standard. ISRM also needs domain-specific expert evidence and active network operations; features alone cannot guarantee a living community.
A3: Layer | B3: Published evidence | C3: Repeated capability / finding | D3: Recommendation for ISRM core boundary | E3: Pricing treatment | F3: Evidence limitation
A4: Standalone community platforms | B4: CIRCLE-CAP; HIVE-CAP | C4: Across these examples: profiles/member directory, group spaces, feed/discussion, messaging, events, onboarding journeys/workflows and analytics. Some features are plan-dependent. | D4: Treat member identity, directory/search, groups, collaboration, basic messaging/events, admin, onboarding and engagement analytics as the generic platform baseline. | E4: Fixed core, subject to final functional limits. | F4: Two vendor capability lists are examples, not a universal industry standard. Do not infer exact depth, compliance or implementation effort from a feature list.
A5: Embedded enterprise/community platforms | B5: VIVA-ADMIN; VIVA-ANALYTICS; SALESFORCE-EXP; SALESFORCE-GUEST | C5: Community functions can sit inside Teams or a CRM portal, with delegated moderators/admins, campaigns, analytics, CRM-connected data exposure and guest-access controls. | D5: Access control, operator/admin workflows and auditable data visibility belong in core whether standalone or embedded. A particular enterprise connector is optional until selected. | E5: Core capabilities fixed; connectors/integrations separate. | F5: Vendor documentation describes specific ecosystems and configured products, not a drop-in ISRM implementation.
A6: Security and communications | B6: CIRCLE-SEC; HIVE-SEC; SALESFORCE-GUEST | C6: Published examples describe encryption at rest/in transit, role-based access, SSO/audit and least-privilege guest controls. | D6: Make access, data protection, privacy, audit, retention and secure transport non-removable. Define a threat model before asserting secure messaging or requiring E2E encryption. | E6: Baseline controls fixed; E2E or high-assurance requirements are explicit scope deltas. | F6: These sources do not establish end-to-end encryption of community messages; absence of evidence is not proof a vendor cannot offer it.
A7: Keeping groups active | B7: VIVA-ADMIN; VIVA-ANALYTICS; CRT-GROWTH | C7: Admin ownership, campaigns/announcements, onboarding, useful recurring content/programs, participation analytics and dormant-conversation signals support the operating loop. | D7: Include group ownership/moderation, onboarding, content/response workflows, basic events/notifications, engagement health and re-engagement tools in core. Price the human community-operations service separately. | E7: Core product capability plus separate recurring operations/staffing. | F7: Microsoft notes an association between admin engagement and success; it is not a causal guarantee. Community Roundtable recommendations are qualitative practice guidance.
A8: ISRM-specific expert-network difference | B8: User requirements; current proposal catalog; CIRCLE-CAP; HIVE-CAP | C8: A searchable community directory is not the same as evidence-backed verification of a person’s identity and expertise. | D8: Treat evidence provenance, reviewer workflow, corrections/appeals and controlled expert onboarding as core differentiators. AI may assist; an authorized human/process owns verification. | E8: Fixed core; evidence providers/checks may be usage-based. | F8: No verified evidence classes, sources, expiry rules or score methodology have yet been approved.
A9: Growth and network expansion | B9: User requirements; CIRCLE-CAP; HIVE-CAP; CRT-GROWTH | C9: Invitations, onboarding journeys, segmented communications, recommendations, content and activity programs are platform-supported growth mechanisms. | D9: Make a consent-aware sector/territory recruitment-to-onboarding pipeline core. Separate channel automation/provider costs and any large-scale AI screening. | E9: Core workflow fixed; automation and metered services as optional deltas. | F9: Software enables the process but does not create a sustainable member value proposition or guarantee recruitment/retention.
A10: Basic activity vs advanced service modules | B10: Current SERVICE_CATALOG; user boundary | C10: Simple groups, posts, opportunities, discussion, and event notices support the community baseline; multi-step delivery workflows and operational services are deeper modules. | D10: Keep lightweight participation and opportunity sharing in core. Make advanced project management, War Room, research, public engagement, commercial lead generation, marketplace, billing, production AI/OSINT and field logistics removable. | E10: Optional modules priced by dependency-aware incremental effort; shared platform/team costs remain fixed. | F10: The exact cutoff between lightweight and advanced workflows needs the product owner’s approval.
A11: Pre-contract proposal tooling | B11: User-approved configurator/PDF requirement; current proposal route | C11: Function-to-feature selection, price preview, working-scope PDF, approval and reviewer identity support sales/formalization; they are not ordinary member-community functions. | D11: Keep the configurator/PDF as a separate workstream or product-tooling line, not part of the non-removable ISRM community core. | E11: Separate one-time tooling cost; reviewer registration remains an open decision. | F11: Whether the proposal tool itself will be delivered to ISRM or only used internally is not yet confirmed.
A12: Privacy-gated visitor logging | B12: User-approved operator-only IP request; no implementation found | C12: Collecting visitor IP creates a personal-data/security/retention workflow distinct from member-community functionality. | D12: Do not include as generic core or implement until purpose, notice/legal basis, retention, operator access/audit, secure storage and deletion are approved. | E12: Blocked optional operational item. | F12: This analysis is not legal advice; jurisdiction and controller/processor roles are unresolved.

Sheet Negotiation Narrative
A1: Negotiation narrative — reuse commodity community capabilities
A2: The purpose is to reject duplicate custom development and reserve budget for domain-specific gaps; license and lifecycle costs remain subject to verification.
A4: Purpose | B4: Negotiation framing against duplicate custom development; not a claim that the complete solution has zero cost.
A5: Українська — чернетка | B5: Базові можливості спільноти — профілі й каталог учасників, групи, обговорення, повідомлення, події, адміністрування та базова аналітика — вже реалізовані у готових платформах. Перед фінансуванням окремої розробки спершу варто використати рішення, що доступні без додаткової ліцензійної плати або вже включені до підписок замовника. Бюджет розробки слід спрямувати на підтверджені прогалини ISRM: доказову перевірку експертності, контрольоване розширення мережі, узгоджені правила доступу й роботи з даними, потрібну графову взаємодію та спеціалізовані сервісні процеси.
A6: English — draft | B6: Baseline community capabilities—member profiles and directory, groups, discussions, messaging, events, administration, and basic analytics—already exist in ready-made platforms. Before funding custom development, first use options available at no additional licence charge or already included in the client’s subscriptions. Development budget should address verified ISRM gaps: evidence-backed expert validation, controlled network growth, agreed access and data rules, the required graph experience, and specialized service workflows.
A7: Negotiation ask | B7: Use existing or no-additional-license tools for commodity community functions; do not charge for rebuilding them. Scope and price only the ISRM-specific gaps and the work required to integrate, configure, secure, migrate, operate, or extend the selected tools.
A8: Evidence basis | B8: Capability examples: CIRCLE-CAP, HIVE-CAP, VIVA-ADMIN, VIVA-ANALYTICS, SALESFORCE-EXP. These establish that comparable capabilities exist; they do not prove that a specific option is free, included in the client’s current licence, or suitable for ISRM.
A9: Internal qualification — do not omit | B9: “Free” means no additional licence charge for a verified option, not zero total cost. Confirm current entitlements and terms; assess data ownership/location, privacy, access controls and security; include configuration, migration, integration, hosting, support and operations where applicable. Free/open-source software can still create material implementation and lifecycle costs.
A10: No-build-first rule | B10: For every baseline function, check existing ISRM/Microsoft/CRM/community licences and suitable free/open-source options before estimating custom code. Build only when a verified gap, security requirement, data-control constraint or essential ISRM differentiator cannot be met by reuse.
A11: Limit | B11: This is a negotiation position supported by published product capability lists, not a universal market price statement or a promise that all comparable solutions are free.

Sheet Core Estimate
A1: Greenfield Estimate — Fixed ISRM Core
A2: Planning slice only. One customer; bespoke delivery from a clean sheet. Existing code, vendor subscriptions and open-source tools receive no effort credit.
A3: ⚠ ASSUMPTION: hours are bottom-up planning inputs, not measured delivery data or a commitment. Low/base/high ranges reflect unresolved workflows, access rules, data ownership, integrations and acceptance detail.
A4: Technical baseline for this slice: React + TypeScript web UI; managed PostgreSQL; OIDC identity; object storage; email notifications; a 2D graph library (Cytoscape/Sigma selection not final). A1/A2 describe candidates, not an approved production architecture.
A5: Rate scenarios are gross provider-rate comparisons only: formulas use the Clutch published Ukraine/US upper endpoints in Inputs. They are not national maxima, supplier quotes, a final price or a cost-plus model; no FX, tax, reserve, profit, hosting, licences or AI usage is included.
A6: WBS ID | B6: Work package | C6: Included scope / completion outcome | D6: Dependencies | E6: Candidate technology / approach | F6: Low hours | G6: Base hours | H6: High hours | I6: Status, rationale and evidence locator | J6: Base-hours × Ukraine published upper endpoint (USD) | K6: Base-hours × US published upper endpoint (USD)
A7: CORE-01 | B7: Discovery, product and security architecture | C7: Define user journeys, role/access matrix, domain model, acceptance scenarios, privacy rules and architecture decision record. Output: reviewed implementation backlog and unresolved-decision register. | D7: — | E7: React/TypeScript; PostgreSQL; OIDC; managed object storage; email; graph library TBD | F7: 120 | G7: 160 | H7: 220 | I7: ⚠ ASSUMPTION; A1 §§1.1–1.2; A2 §§7.3–7.4; Access Contract. Wider high case reflects unapproved data/access and workflow rules. | J7: =G7*Inputs!$B$4 | K7: =G7*Inputs!$B$6
A8: CORE-02 | B8: UX, design system and accessible responsive UI | C8: Design one-page network workspace, explicit mode/layer states, stacked drawers/panels, responsive touch layout, keyboard operation and bilingual UI. | D8: CORE-01 | E8: React + TypeScript; HTML/CSS design system | F8: 100 | G8: 140 | H8: 190 | I8: ⚠ ASSUMPTION; user-approved workspace requirements; A2 §5.4. Final visual direction and complete screen inventory remain open. | J8: =G8*Inputs!$B$4 | K8: =G8*Inputs!$B$6
A9: CORE-03 | B9: Identity, authorization, consent and audit foundation | C9: Implement managed sign-in, MFA-ready account policy, role/scope checks, guest/member/operator/admin access, profile visibility/consent, contact separation and audit events. | D9: CORE-01 | E9: OIDC provider; PostgreSQL authorization/RLS; server-side policy enforcement | F9: 180 | G9: 240 | H9: 330 | I9: ⚠ ASSUMPTION; Access Contract; A2 §§6–7. Includes implementation and tests, not legal advice or a certification. | J9: =G9*Inputs!$B$4 | K9: =G9*Inputs!$B$6
A10: CORE-04 | B10: Live data model and operator workspace | C10: Build relational schema, migrations, data validation/import staging, provenance, deduplication review, edit/correction workflow, operator queues and live graph data APIs. Use synthetic/de-identified data until data rights are approved. | D10: CORE-01, CORE-03 | E10: Managed PostgreSQL; object storage; server API; operator UI | F10: 180 | G10: 260 | H10: 380 | I10: ⚠ ASSUMPTION; Access Contract; Content-to-Service Assessment. Real CRM migration, source cleanup and volume are not confirmed. | J10: =G10*Inputs!$B$4 | K10: =G10*Inputs!$B$6
A11: CORE-05 | B11: Expert profiles and evidence-backed verification | C11: Implement profiles, evidence records with source/date/reviewer, verification states, provenance, corrections, appeal/review workflow and disclosure rules. No composite Trust/Influence score. | D11: CORE-03, CORE-04 | E11: PostgreSQL evidence model; controlled file storage; human-review workflow | F11: 200 | G11: 290 | H11: 420 | I11: ⚠ ASSUMPTION; user-approved core boundary; Access Contract; Capability Benchmark. Verification rubric and evidence-source policy remain unapproved. | J11: =G11*Inputs!$B$4 | K11: =G11*Inputs!$B$6
A12: CORE-06 | B12: Expert search, filters and layered network graph | C12: Implement searchable profiles, sector/geography/topic filters, expert and feature layers, layer toggles, dependencies view, graph-to-dossier navigation and text-accessible equivalent. | D12: CORE-02, CORE-04, CORE-05 | E12: PostgreSQL full-text search; React; Cytoscape.js or Sigma.js (choice open) | F12: 180 | G12: 260 | H12: 380 | I12: ⚠ ASSUMPTION; A1 §1.2; A2 §7.3; user-approved graph requirements. No separate graph database assumed. | J12: =G12*Inputs!$B$4 | K12: =G12*Inputs!$B$6
A13: CORE-07 | B13: Community collaboration and basic events | C13: Implement groups, member feed/posts, comments, shared resources, basic opportunities, event notices, moderation, delegated group administration and transactional email notifications. No complex PM or E2EE. | D13: CORE-02, CORE-03, CORE-04 | E13: React; PostgreSQL; object storage; email provider | F13: 220 | G13: 320 | H13: 470 | I13: ⚠ ASSUMPTION; user-approved core boundary; CIRCLE-CAP; HIVE-CAP; VIVA-ADMIN. Message retention, upload policy and email provider remain open. | J13: =G13*Inputs!$B$4 | K13: =G13*Inputs!$B$6
A14: CORE-08 | B14: Expert intake, recruitment and onboarding | C14: Implement consent-aware intake, campaign records, source tracking, candidate triage queue, human-reviewed verification handoff, onboarding steps and membership status. No autonomous AI decisions or social-platform automation. | D14: CORE-03, CORE-04, CORE-05, CORE-07 | E14: Forms/API; PostgreSQL workflow; email provider; optional queue | F14: 160 | G14: 240 | H14: 360 | I14: ⚠ ASSUMPTION; user-approved growth lifecycle; A2 §§4, 6; CRT-GROWTH. Outreach channels, volume and AI role are unresolved. | J14: =G14*Inputs!$B$4 | K14: =G14*Inputs!$B$6
A15: CORE-09 | B15: Engagement operations and basic health analytics | C15: Implement group-owner tools, activity/participation measures, dormant-group signals, re-engagement tasks and basic role assignment workflow. No ranking or automatic privilege elevation. | D15: CORE-03, CORE-07, CORE-08 | E15: PostgreSQL event records; dashboard UI; notification rules | F15: 140 | G15: 210 | H15: 320 | I15: ⚠ ASSUMPTION; VIVA-ADMIN; VIVA-ANALYTICS; CRT-GROWTH; user-approved boundary. KPI definitions and operating cadence remain open. | J15: =G15*Inputs!$B$4 | K15: =G15*Inputs!$B$6
A16: CORE-10 | B16: Security hardening and privacy verification | C16: Threat-model core flows, verify authorization boundaries and data minimization, configure secrets, encryption and secure defaults, test access/audit paths, prepare incident and retention controls. | D16: CORE-03, CORE-04, CORE-05, CORE-07, CORE-08, CORE-09 | E16: OIDC; managed Postgres/object storage; logging; security test tooling | F16: 80 | G16: 120 | H16: 180 | I16: ⚠ ASSUMPTION; Access Contract; A2 §§6–7. No third-party penetration-test quote or certification scope included. | J16: =G16*Inputs!$B$4 | K16: =G16*Inputs!$B$6
A17: CORE-11 | B17: Quality assurance, accessibility and acceptance testing | C17: Test role/data isolation, imports, graph interactions, workflows, failure paths, mobile/touch/keyboard and bilingual presentation; prepare acceptance scripts and regression coverage. | D17: CORE-02 through CORE-10 | E17: Browser automation; unit/integration tests; accessibility checks | F17: 180 | G17: 270 | H17: 400 | I17: ⚠ ASSUMPTION; user-approved loop requirements; A2 §8. Includes testing effort, not an independent certification audit. | J17: =G17*Inputs!$B$4 | K17: =G17*Inputs!$B$6
A18: CORE-12 | B18: Deployment, observability, backup and operational handover | C18: Create non-production/production environments, CI/CD, monitoring/error logs, backups/restore checks, operational runbook and release handover. | D18: CORE-03, CORE-04, CORE-10, CORE-11 | E18: Managed app hosting; PostgreSQL; object storage; CI/CD; monitoring | F18: 100 | G18: 150 | H18: 230 | I18: ⚠ ASSUMPTION; A2 §§7.3, 8. Exact provider, region, availability target and support plan remain unchosen. | J18: =G18*Inputs!$B$4 | K18: =G18*Inputs!$B$6
A19: CORE-13 | B19: Delivery management and client acceptance | C19: Coordinate dependencies, decisions, demonstrations, review cycles, issue triage, scope control and handover documentation through acceptance. | D19: CORE-01 through CORE-12 | E19: Delivery workflow and project documentation | F19: 100 | G19: 150 | H19: 240 | I19: ⚠ ASSUMPTION; A2 §§8–8.2; user-approved ≤3 milestone constraint. Client review turnaround and governance cadence remain open. | J19: =G19*Inputs!$B$4 | K19: =G19*Inputs!$B$6
A20: TOTAL — fixed core | F20: =SUM(F7:F19) | G20: =SUM(G7:G19) | H20: =SUM(H7:H19) | J20: =G20*Inputs!$B$4 | K20: =G20*Inputs!$B$6
A22: Indicative rate sensitivity — same scope; not a proposal price
A23: Low effort × Ukraine upper endpoint | F23: =F20 | G23: person-hours | H23: =F20*Inputs!$B$4
A24: Base effort × Ukraine upper endpoint | F24: =G20 | G24: person-hours | H24: =G20*Inputs!$B$4
A25: Base effort × US upper endpoint | F25: =G20 | G25: person-hours | H25: =G20*Inputs!$B$6
A26: High effort × US upper endpoint | F26: =H20 | G26: person-hours | H26: =H20*Inputs!$B$6
A28: Inclusions | B28: Fixed core only: account/access controls, live data/operator tools, expert search and graph, evidence-backed verification/provenance, basic community collaboration/events, recruitment/intake/onboarding, engagement operations, QA and deployment.
A29: Exclusions for later estimates | B29: Advanced optional modules (War Room, complex project management, research, public engagement, leads, campaigns, extended events, AI/OSINT production, partner marketplace, billing and Nomad logistics); pre-contract configurator/PDF; visitor-IP collection; composite Trust/Influence scoring; external subscriptions and usage.
A30: Greenfield basis | B30: Estimate assumes a bespoke application for one customer, with no effort credit for the current repository, existing product code, existing data assets, or free/previously licensed products. Any reuse case belongs in a separate negotiation or scenario analysis.
A31: Gated decisions | B31: Exact source data and lawful migration; reviewer identity; access/contact policy; evidence rubric; event/communications provider; data residency/retention; production load/availability; support SLA; IP/source-code/co-development terms; AI provider and human-review policy.
A32: Calculation passport | B32: Effort inputs F:H are ⚠ ASSUMPTION person-hours per work package. Reasoning and documentary basis are in column I. J/K and scenario outputs are formulas referencing these inputs and the published rate endpoints in Inputs (CLUTCH-UA / CLUTCH-US). No FX conversion or markup.
