Workbook

Sheet Readme
A1: ISRM partner budget model — draft for decision
A3: Purpose | B3: A transparent scope and budget sensitivity model for partner review. It is not a signed offer, quotation, delivery commitment, or verified project registry.
A4: Scope basis | B4: The original 13-package greenfield fixed-core estimate is retained as a historical reference only. It is not the revised-scope estimate and includes no validated reuse credit for the client demo.
A5: Effort status | B5: The original Low/Base/High hours remain historical assumptions for the earlier scope only; they are not current product or pricing tiers. Revised production effort, partner consulting effort, demo-module compensation, external costs and operating costs remain TBD pending scope reconciliation, live measurement, partner decisions and comparable quotes. AI use and API costs are excluded from the committed MVP and require separate approval.
A6: Rate sensitivity | B6: Published Clutch provider-rate bands are multiplied by assumed person-hours only to show sensitivity. This is not a quote, not a national rate ceiling, and not the partner team’s actual rate. The project delivery location/team is not confirmed.
A7: Currency | B7: Client preference is GBP; confirm contract currency with partners/client before budgeting. No FX conversion is performed. The UK contractor comparator is shown in GBP, separately from US/Ukraine provider-company benchmarks in USD.
A8: Allocation | B8: The developer and core-team/admin/relationship/representation bands are independent target ranges. Do not add their upper endpoints to a separate profit share. Profit is only a possible residual after verified costs and remains undecided.
A9: Payment terms | B9: The user-approved proposal constraint is an advance of at least 30% and no more than 3 payments total. Later milestone shares remain blank until agreed.
A10: SaaS | B10: No customer/member data, legal basis, consent, or migration permission is assumed. Alex's ~11,700 LinkedIn group count is user-reported and unverified (screenshot/date not retained); it is not unique reach, an expert count, or a conversion denominator. It supersedes the earlier ~11,000 working approximation for planning only.
A11: Data boundary | B11: Blue inputs on Inputs, Work_Packages and Project_Budget; green formulas; yellow assumptions; orange unresolved gates. Blank means unknown, not zero. Inputs!B30 is the separate demo reuse fee, not added twice. Project_Budget is the project-wide revised-scope model; Budget_Model remains historical.
A12: Using the workbook | B12: Use Inputs for contract currency, partner role rates and periods, plus the agreed whole-project reference amount in B47; Project_Budget for bounded effort/cost inputs, scope decisions, KPI/acceptance and roll-up; Partner_Effort and Revised_Scope remain detailed schedules. Historical Low/Base/High figures are not current offer tiers.
A13: Source limits | B13: The draft Source_Register provides a model-local audit trail. It is not a canonical project registry. The original source files remain unchanged; revised-scope scenario assumptions are documented on Revised_Scope.
A14: Revised scope / scenarios | B14: Revised_Scope documents demo reuse, residual work, strategy/Trust & Influence and 300/400/500 dossier scenarios. Project_Budget rolls up all five tracks and Gate 4A; conditional work stays excluded until selected. Unknown inputs remain TBD.
... A19: Bilingual companion / Двомовний супровід | B19: ISRM_Partner_Decision_Input_Draft.md is the English/Ukrainian review narrative and scope companion. / ISRM_Partner_Decision_Input_Draft.md — двомовний супровідний документ для розгляду scope і партнерських рішень.

Sheet Inputs
A1: Inputs and partner decisions
A3: Input ID | B3: Value | C3: Unit / period | D3: Status | E3: Origin / locator | F3: Notes / calculation use | H3: Cell map for formulas
A4: RATE_UA_LOW | B4: 25 | C4: USD / provider-hour; published band | D4: Source-reported | E4: Clutch Software Development Pricing Guide, updated Sep 2026 | F4: Band endpoint, not a national floor or matched quote. | H4: Actual row addresses (formulas): rates B4:B7; share bands B8:B11; profit ceiling B12; advance B13; max payments B14; operations runway cap B15; currency B16; total budget B17; actual costs B18:B21; approved residual share B22; monthly operations cost B23; SaaS monthly cost B24; selected budget shares B25:B26; payment shares B27:B29; demo-module reuse fee B30. New project-wide rates: Inputs!B33:B39; controls/period inputs: Inputs!B40:B46; see Project_Budget.
A5: RATE_UA_HIGH | B5: 49 | C5: USD / provider-hour; published band | D5: Source-reported | E5: Clutch Software Development Pricing Guide, updated Sep 2026 | F5: Band endpoint, not a national ceiling or matched quote.
A6: RATE_US_LOW | B6: 50 | C6: USD / provider-hour; published band | D6: Source-reported | E6: Clutch Software Development Pricing Guide, updated Sep 2026 | F6: Band endpoint, not a national floor or matched quote.
A7: RATE_US_HIGH | B7: 99 | C7: USD / provider-hour; published band | D7: Source-reported | E7: Clutch Software Development Pricing Guide, updated Sep 2026 | F7: Band endpoint, not a national ceiling or matched quote.
A8: DEV_SHARE_MIN | B8: 0.33 | C8: share of agreed budget | D8: User-stated target; uncontracted | E8: Current conversation | F8: Target band only; actual split remains for partner decision.
A9: DEV_SHARE_MAX | B9: 0.5 | C9: share of agreed budget | D9: User-stated target; uncontracted | E9: Current conversation | F9: Do not combine upper bound with a profit share as if separately additive.
A10: OPS_SHARE_MIN | B10: 0.33 | C10: share of agreed budget | D10: User-stated target; uncontracted | E10: Current conversation | F10: Covers core-team management/administration, relationship work and representation.
A11: OPS_SHARE_MAX | B11: 0.5 | C11: share of agreed budget | D11: User-stated target; uncontracted | E11: Current conversation | F11: Target band only; actual split remains for partner decision.
A12: PROFIT_SHARE_MAX | B12: 0.33 | C12: share of verified positive residual | D12: Unapproved decision; inactive | E12: Current conversation; prior partner decision gate | F12: Discussed ceiling only. No profit distribution or reinvestment rule is adopted.
A13: ADVANCE_MIN | B13: 0.3 | C13: share of agreed contract total | D13: User-approved minimum; uncontracted | E13: Current conversation | F13: Later milestone amounts and trigger criteria remain TBD.
A14: MAX_PAYMENTS | B14: 3 | C14: payments per contract | D14: User-approved maximum; uncontracted | E14: Current conversation | F14: Workbook offers three payment-share slots.
A15: OPS_RUNWAY_MAX | B15: 3 | C15: calendar months after launch | D15: User-stated cap; unapproved funding | E15: Current conversation | F15: Only a possible community-service runway; monthly cost and continuation decision remain unknown.
A16: CONTRACT_CURRENCY | C16: currency code | D16: Decision required | E16: Partner/client contract | F16: Client prefers GBP; confirm contract currency with partners/client before entering the budget. No FX conversion is performed.
A17: CONTRACT_BUDGET | C17: contract currency; one-time | D17: Decision required | E17: Final scope and commercial agreement | F17: Enter only after requirements, scope, and contract currency are approved.
A18: DEV_ACTUAL_COST | C18: contract currency; one-time | D18: Decision required | E18: Developer quotes/contracts | F18: Verified developer cost, not the rate-sensitivity proxy.
A19: CORE_TEAM_ACTUAL_COST | C19: contract currency; one-time | D19: Decision required | E19: Three partner fee agreement | F19: Agreed partner delivery fees, excluding DEMO_MODULE_REUSE_FEE (Inputs!B30) to prevent double-counting.
A20: REP_ACTUAL_COST | C20: contract currency; one-time | D20: Decision required | E20: Receipts/approved budget | F20: Representation and other agreed project outlays.
A21: OTHER_ACTUAL_COST | C21: contract currency; one-time | D21: Decision required | E21: Verified supplier quotes/contracts | F21: Other direct project costs; enter zero only if verified.
A22: APPROVED_RESIDUAL_SHARE | C22: share of verified positive residual | D22: Decision required | E22: Partner agreement | F22: Must not exceed the unapproved 33% discussion ceiling unless partners explicitly revise it.
A23: OPS_MONTHLY_COST | C23: contract currency / month | D23: Decision required | E23: Operating plan after pilot | F23: Used only to calculate an optional runway scenario.
A24: SAAS_MONTHLY_COST | C24: contract currency / month | D24: Decision required | E24: Selected production providers and usage profile | F24: Not included in fixed-core sensitivity.
A25: DEV_SHARE_SELECTED | C25: share of agreed budget | D25: Decision required | E25: Partner budget decision | F25: Optional check against the target band.
A26: OPS_SHARE_SELECTED | C26: share of agreed budget | D26: Decision required | E26: Partner budget decision | F26: Optional check against the target band.
A27: PAYMENT_1_SHARE | C27: share of agreed contract total | D27: Decision required | E27: Final payment schedule | F27: Payment 1 is the advance; must be at least the user-approved minimum.
... A30: GRAPH_SEARCH_REUSE_ALLOCATION | C30: contract currency; one-time internal allocation | D30: Partner decision required | E30: Internal partner allocation for graph/search reuse only if separately agreed. Not a separate client fee; no historical payment or hours inferred. | F30: Proposed internal compensation for the search + group-formation demo module; amount is TBD and is not inferred from market benchmarks. Pay the author after receipt of the first client payment. Do not duplicate in CORE_TEAM_ACTUAL_COST (B19).
A31: Project-wide partner rates and operating-period inputs
A32: Input ID | B32: Value | C32: Unit / period | D32: Status | E32: Origin / locator | F32: Notes / calculation use
A33: RATE_PARTNER_BD | C33: contract currency/person-hour | D33: Partner input required | E33: Partner agreement | F33: Partner 1: business development; no salary comparator substituted.
A34: RATE_PARTNER_OSINT_COMMS_EVENTS | C34: contract currency/person-hour | D34: Partner input required | E34: Partner agreement | F34: Partner 2: OSINT, external communications and event management.
A35: RATE_PARTNER_PRODUCT_OWNER | C35: contract currency/person-hour | D35: Partner input required | E35: Partner agreement | F35: Partner 3: Product Owner and developer coordination.
A36: RATE_SPECIALIST_TRAINER | C36: contract currency/person-hour | D36: Partner input required | E36: Training scope/partner agreement | F36: One-time OSINT/data-management training; max one day; actual effort TBD.
A37: RATE_ANALYST | C37: contract currency/person-hour | D37: Partner input required | E37: Analyst agreement | F37: At least one analyst; hours allocated once across work packages.
A38: RATE_EXTERNAL_REVIEWER | C38: contract currency/person-hour | D38: Decision required | E38: Client/reviewer agreement | F38: Only if external reviewers are paid; neither payment nor unpaid status assumed.
A39: RATE_ASSISTANT_OPTIONAL | C39: contract currency/person-hour | D39: Optional; rate TBD | E39: Partner agreement | F39: Optional assistant; excluded unless selected and effort is supplied.
A40: WORKDAY_HOURS | B40: 8 | C40: hours/working day | D40: [ASSUMPTION] conversion only | E40: Current user direction | F40: Only converts stated 2–3 T&I preparation days for one person.
A41: ANALYST_MIN_COUNT | B41: 1 | C41: people | D41: User-stated requirement | E41: Current user direction | F41: Staffing minimum only; not duration or cost.
A42: TRAINING_MAX_DAYS | B42: 1 | C42: working day | D42: User-stated upper bound | E42: Current user direction | F42: Maximum for one-time OSINT/data-management training; not base hours.
A43: TRAINING_MAX_HOURS | B43: =B40*B42 | C43: hours; conditional cap | D43: Formula from assumption/cap | E43: Inputs!B40 × Inputs!B42 | F43: Upper bound only; not included as base training hours.
A44: ASSISTANT_INCLUDED | C44: Yes/No | D44: Optional decision | E44: Partner scope decision | F44: Select Yes only after scope approval; effort and rate remain separate.
A45: OPS_MONTHS_INCLUDED | C45: months | D45: Decision required | E45: Approved support period | F45: No default; do not reuse unapproved runway cap.
A46: SAAS_MONTHS_INCLUDED | C46: months | D46: Decision required | E46: Approved SaaS period | F46: No default; used with monthly cost in Inputs!B24.
A47: AGREED_PROJECT_REFERENCE | C47: contract currency; whole-project total for stated scope and period | D47: Partner/client agreement required | E47: Documented agreement / decision record | F47: Required for budget-variance percentages. Leave blank until a numeric whole-project reference is expressly agreed; scope, currency and period must match Project_Budget.

Sheet Project_Budget
A1: ISRM Expert Network — Project-wide budget and scope gates / ISRM Expert Network — Загальний бюджет і контрольні рішення
A2: Partner review working model only; not a quotation, approved price or delivery commitment. / Робоча модель лише для розгляду партнерами; не котировка, не затверджена ціна й не зобов’язання виконати роботи.
A3: Scope covers Tracks 1–5 and Gate 4A. Historical Budget_Model and Work_Packages remain historical only. / Обсяг охоплює треки 1–5 і ворота 4A. Історичні Budget_Model і Work_Packages не є актуальною оцінкою.
A4: Blank inputs mean unknown, never zero. Totals remain TBD until currency, hours/rates, supplier quotes and scope decisions are resolved. / Порожні входи означають «невідомо», а не нуль. Підсумки залишаються TBD до погодження валюти, годин/ставок, котирувань і рішень щодо обсягу.
A5: Blue = user input; green = formula/link; yellow = assumption; orange = unresolved gate; gray = excluded/reference. Taxes excluded. / Синій = ввід користувача; зелений = формула/посилання; жовтий = припущення; помаранчевий = невирішені ворота; сірий = виключено/довідка. Податки не враховано.
A6: ID / Код | B6: Track/gate / Трек/ворота | C6: Deliverable/cost line / Результат / стаття витрат | D6: Responsible function/source / Відповідальна функція / джерело | E6: Cost basis / База розрахунку | F6: Lower-bound effort input / Ввід: нижня межа | G6: Reference effort input / Ввід: орієнтир | H6: Upper-bound effort input / Ввід: верхня межа | I6: Input unit / Одиниця входу | J6: Rate/quote per unit / Ставка/котирування за одиницю | K6: Lower-bound cost / Вартість: нижня межа | L6: Reference cost / Вартість: орієнтир | M6: Upper-bound cost / Вартість: верхня межа | N6: Budget treatment / Облік у бюджеті | O6: Evidence/formula/open condition / Джерело, формула або відкрита умова | P6: KPI/acceptance measure / KPI або критерій приймання | Q6: KPI target/status / Ціль KPI / статус | R6: Deliverable/cost line (UA) / Результат / стаття витрат (укр.)
A7: TI-01 | B7: Track 1 | C7: Prepare Trust & Influence strategic session | D7: =IF('Partner_Effort'!C6="","",'Partner_Effort'!C6) | E7: Partner hours × rate | F7: =IF('Partner_Effort'!D6="","",'Partner_Effort'!D6) | G7: =IF('Partner_Effort'!E6="","",'Partner_Effort'!E6) | H7: =IF('Partner_Effort'!F6="","",'Partner_Effort'!F6) | I7: person-hours | K7: =IF(OR(Inputs!$B$16="",F7="",J7=""),"TBD",F7*J7) | L7: =IF(OR(Inputs!$B$16="",G7="",J7=""),"TBD",G7*J7) | M7: =IF(OR(Inputs!$B$16="",H7="",J7=""),"TBD",H7*J7) | N7: Mandatory | O7: ='Partner_Effort'!H6 | P7: Session brief, agenda, evidence questions and pre-read reviewed. | Q7: Client/board acceptance; numeric target TBD. | R7: Підготувати стратегічну сесію Trust & Influence
A8: TI-02 | B8: Track 1 | C8: Facilitate Trust & Influence strategic session | D8: =IF('Partner_Effort'!C7="","",'Partner_Effort'!C7) | E8: Partner hours × rate | F8: =IF('Partner_Effort'!D7="","",'Partner_Effort'!D7) | G8: =IF('Partner_Effort'!E7="","",'Partner_Effort'!E7) | H8: =IF('Partner_Effort'!F7="","",'Partner_Effort'!F7) | I8: person-hours | K8: =IF(OR(Inputs!$B$16="",F8="",J8=""),"TBD",F8*J8) | L8: =IF(OR(Inputs!$B$16="",G8="",J8=""),"TBD",G8*J8) | M8: =IF(OR(Inputs!$B$16="",H8="",J8=""),"TBD",H8*J8) | N8: Mandatory | O8: ='Partner_Effort'!H7 | P8: Decisions and design principles approved. | Q8: Client/board acceptance; numeric target TBD. | R8: Провести стратегічну сесію Trust & Influence
A9: TI-03 | B9: Track 1 | C9: Synthesize and document session decisions | D9: =IF('Partner_Effort'!C8="","",'Partner_Effort'!C8) | E9: Partner hours × rate | F9: =IF('Partner_Effort'!D8="","",'Partner_Effort'!D8) | G9: =IF('Partner_Effort'!E8="","",'Partner_Effort'!E8) | H9: =IF('Partner_Effort'!F8="","",'Partner_Effort'!F8) | I9: person-hours | K9: =IF(OR(Inputs!$B$16="",F9="",J9=""),"TBD",F9*J9) | L9: =IF(OR(Inputs!$B$16="",G9="",J9=""),"TBD",G9*J9) | M9: =IF(OR(Inputs!$B$16="",H9="",J9=""),"TBD",H9*J9) | N9: Mandatory | O9: ='Partner_Effort'!H8 | P9: Decision log and owners reviewed. | Q9: Client/board acceptance; numeric target TBD. | R9: Узагальнити й задокументувати рішення сесії
A10: TI-04 | B10: Track 1 | C10: Co-design Trust & Influence index/model | D10: =IF('Partner_Effort'!C9="","",'Partner_Effort'!C9) | E10: Partner hours × rate | F10: =IF('Partner_Effort'!D9="","",'Partner_Effort'!D9) | G10: =IF('Partner_Effort'!E9="","",'Partner_Effort'!E9) | H10: =IF('Partner_Effort'!F9="","",'Partner_Effort'!F9) | I10: person-hours | K10: =IF(OR(Inputs!$B$16="",F10="",J10=""),"TBD",F10*J10) | L10: =IF(OR(Inputs!$B$16="",G10="",J10=""),"TBD",G10*J10) | M10: =IF(OR(Inputs!$B$16="",H10="",J10=""),"TBD",H10*J10) | N10: Mandatory | O10: ='Partner_Effort'!H9 | P10: Versioned model and limits approved. | Q10: Client/board acceptance; numeric target TBD. | R10: Спільно розробити індекс / модель Trust & Influence
A11: TI-05 | B11: Track 1 | C11: Draft assessment protocol and correction/appeal path | D11: =IF('Partner_Effort'!C10="","",'Partner_Effort'!C10) | E11: Partner hours × rate | F11: =IF('Partner_Effort'!D10="","",'Partner_Effort'!D10) | G11: =IF('Partner_Effort'!E10="","",'Partner_Effort'!E10) | H11: =IF('Partner_Effort'!F10="","",'Partner_Effort'!F10) | I11: person-hours | K11: =IF(OR(Inputs!$B$16="",F11="",J11=""),"TBD",F11*J11) | L11: =IF(OR(Inputs!$B$16="",G11="",J11=""),"TBD",G11*J11) | M11: =IF(OR(Inputs!$B$16="",H11="",J11=""),"TBD",H11*J11) | N11: Mandatory | O11: ='Partner_Effort'!H10 | P11: Repeatable protocol and audit/correction rules approved. | Q11: Client/board acceptance; numeric target TBD. | R11: Підготувати протокол оцінювання та порядок виправлення / оскарження
A12: TI-06 | B12: Track 1 | C12: Select practice leaders and regional representatives | D12: =IF('Partner_Effort'!C11="","",'Partner_Effort'!C11) | E12: Partner hours × rate | F12: =IF('Partner_Effort'!D11="","",'Partner_Effort'!D11) | G12: =IF('Partner_Effort'!E11="","",'Partner_Effort'!E11) | H12: =IF('Partner_Effort'!F11="","",'Partner_Effort'!F11) | I12: person-hours | K12: =IF(OR(Inputs!$B$16="",F12="",J12=""),"TBD",F12*J12) | L12: =IF(OR(Inputs!$B$16="",G12="",J12=""),"TBD",G12*J12) | M12: =IF(OR(Inputs!$B$16="",H12="",J12=""),"TBD",H12*J12) | N12: Mandatory | O12: ='Partner_Effort'!H11 | P12: Approved reviewer roster. | Q12: Client/board acceptance; numeric target TBD. | R12: Відібрати керівників практик і регіональних представників
A13: TI-07 | B13: Track 1 | C13: Prepare reviewer-group orientation/materials | D13: =IF('Partner_Effort'!C12="","",'Partner_Effort'!C12) | E13: Partner hours × rate | F13: =IF('Partner_Effort'!D12="","",'Partner_Effort'!D12) | G13: =IF('Partner_Effort'!E12="","",'Partner_Effort'!E12) | H13: =IF('Partner_Effort'!F12="","",'Partner_Effort'!F12) | I13: person-hours | K13: =IF(OR(Inputs!$B$16="",F13="",J13=""),"TBD",F13*J13) | L13: =IF(OR(Inputs!$B$16="",G13="",J13=""),"TBD",G13*J13) | M13: =IF(OR(Inputs!$B$16="",H13="",J13=""),"TBD",H13*J13) | N13: Mandatory | O13: ='Partner_Effort'!H12 | P13: Materials map to approved model/protocol. | Q13: Client/board acceptance; numeric target TBD. | R13: Підготувати матеріали для орієнтації групи рецензентів
A14: TI-08 | B14: Track 1 | C14: Deliver reviewer-group orientation/training | D14: =IF('Partner_Effort'!C13="","",'Partner_Effort'!C13) | E14: Partner hours × rate | F14: =IF('Partner_Effort'!D13="","",'Partner_Effort'!D13) | G14: =IF('Partner_Effort'!E13="","",'Partner_Effort'!E13) | H14: =IF('Partner_Effort'!F13="","",'Partner_Effort'!F13) | I14: person-hours | K14: =IF(OR(Inputs!$B$16="",F14="",J14=""),"TBD",F14*J14) | L14: =IF(OR(Inputs!$B$16="",G14="",J14=""),"TBD",G14*J14) | M14: =IF(OR(Inputs!$B$16="",H14="",J14=""),"TBD",H14*J14) | N14: Mandatory | O14: ='Partner_Effort'!H13 | P14: Attendance recorded; not proof of sector-wide validity. | Q14: Client/board acceptance; numeric target TBD. | R14: Провести орієнтацію / навчання групи рецензентів
A15: TI-09 | B15: Track 3 | C15: Apply model/protocol to expert reviews and adjudicate exceptions | D15: =IF('Partner_Effort'!C14="","",'Partner_Effort'!C14) | E15: Partner hours × rate | F15: =IF('Partner_Effort'!D14="","",'Partner_Effort'!D14) | G15: =IF('Partner_Effort'!E14="","",'Partner_Effort'!E14) | H15: =IF('Partner_Effort'!F14="","",'Partner_Effort'!F14) | I15: person-hours | K15: =IF(OR(Inputs!$B$16="",F15="",J15=""),"TBD",F15*J15) | L15: =IF(OR(Inputs!$B$16="",G15="",J15=""),"TBD",G15*J15) | M15: =IF(OR(Inputs!$B$16="",H15="",J15=""),"TBD",H15*J15) | N15: Mandatory | O15: ='Partner_Effort'!H14 | P15: Human review and exceptions logged. | Q15: Client/board acceptance; numeric target TBD. | R15: Застосувати модель / протокол до перевірок експертів і розглянути винятки
A16: STR-01 | B16: Track 1 | C16: Prepare/facilitate additional client strategy sessions | D16: =IF('Partner_Effort'!C15="","",'Partner_Effort'!C15) | E16: Partner hours × rate | F16: =IF('Partner_Effort'!D15="","",'Partner_Effort'!D15) | G16: =IF('Partner_Effort'!E15="","",'Partner_Effort'!E15) | H16: =IF('Partner_Effort'!F15="","",'Partner_Effort'!F15) | I16: person-hours | K16: =IF(OR(Inputs!$B$16="",F16="",J16=""),"TBD",F16*J16) | L16: =IF(OR(Inputs!$B$16="",G16="",J16=""),"TBD",G16*J16) | M16: =IF(OR(Inputs!$B$16="",H16="",J16=""),"TBD",H16*J16) | N16: Mandatory | O16: ='Partner_Effort'!H15 | P16: Priorities, decisions and owners documented. | Q16: Client/board acceptance; numeric target TBD. | R16: Підготувати / провести додаткові стратегічні сесії з клієнтом
A17: STR-02 | B17: Track 1 | C17: Prioritize development directions and expertise gaps | D17: =IF('Partner_Effort'!C16="","",'Partner_Effort'!C16) | E17: Partner hours × rate | F17: =IF('Partner_Effort'!D16="","",'Partner_Effort'!D16) | G17: =IF('Partner_Effort'!E16="","",'Partner_Effort'!E16) | H17: =IF('Partner_Effort'!F16="","",'Partner_Effort'!F16) | I17: person-hours | K17: =IF(OR(Inputs!$B$16="",F17="",J17=""),"TBD",F17*J17) | L17: =IF(OR(Inputs!$B$16="",G17="",J17=""),"TBD",G17*J17) | M17: =IF(OR(Inputs!$B$16="",H17="",J17=""),"TBD",H17*J17) | N17: Mandatory | O17: ='Partner_Effort'!H16 | P17: Priorities have rationale and client decision. | Q17: Client/board acceptance; numeric target TBD. | R17: Визначити пріоритети розвитку та прогалини в експертизі
A18: STR-03 | B18: Track 1 | C18: Set criteria/process to review existing network experts | D18: =IF('Partner_Effort'!C17="","",'Partner_Effort'!C17) | E18: Partner hours × rate | F18: =IF('Partner_Effort'!D17="","",'Partner_Effort'!D17) | G18: =IF('Partner_Effort'!E17="","",'Partner_Effort'!E17) | H18: =IF('Partner_Effort'!F17="","",'Partner_Effort'!F17) | I18: person-hours | K18: =IF(OR(Inputs!$B$16="",F18="",J18=""),"TBD",F18*J18) | L18: =IF(OR(Inputs!$B$16="",G18="",J18=""),"TBD",G18*J18) | M18: =IF(OR(Inputs!$B$16="",H18="",J18=""),"TBD",H18*J18) | N18: Mandatory | O18: ='Partner_Effort'!H17 | P18: Review plan and consent/evidence boundaries approved. | Q18: Client/board acceptance; numeric target TBD. | R18: Визначити критерії та процес перевірки наявних експертів мережі
A19: STR-04 | B19: Track 4 | C19: Prepare community questionnaire/campaign materials | D19: =IF('Partner_Effort'!C18="","",'Partner_Effort'!C18) | E19: Partner hours × rate | F19: =IF('Partner_Effort'!D18="","",'Partner_Effort'!D18) | G19: =IF('Partner_Effort'!E18="","",'Partner_Effort'!E18) | H19: =IF('Partner_Effort'!F18="","",'Partner_Effort'!F18) | I19: person-hours | J19: =IF(Inputs!$B$34="","",Inputs!$B$34) | K19: =IF(OR(Inputs!$B$16="",F19="",J19=""),"TBD",F19*J19) | L19: =IF(OR(Inputs!$B$16="",G19="",J19=""),"TBD",G19*J19) | M19: =IF(OR(Inputs!$B$16="",H19="",J19=""),"TBD",H19*J19) | N19: Mandatory | O19: ='Partner_Effort'!H18 | P19: Approved survey and outreach pack. | Q19: Client/board acceptance; numeric target TBD. | R19: Підготувати опитувальник спільноти й матеріали кампанії
A20: STR-05 | B20: Track 4 | C20: Coordinate and operate approved outreach/survey campaign | D20: =IF('Partner_Effort'!C19="","",'Partner_Effort'!C19) | E20: Partner hours × rate | F20: =IF('Partner_Effort'!D19="","",'Partner_Effort'!D19) | G20: =IF('Partner_Effort'!E19="","",'Partner_Effort'!E19) | H20: =IF('Partner_Effort'!F19="","",'Partner_Effort'!F19) | I20: person-hours | J20: =IF(Inputs!$B$34="","",Inputs!$B$34) | K20: =IF(OR(Inputs!$B$16="",F20="",J20=""),"TBD",F20*J20) | L20: =IF(OR(Inputs!$B$16="",G20="",J20=""),"TBD",G20*J20) | M20: =IF(OR(Inputs!$B$16="",H20="",J20=""),"TBD",H20*J20) | N20: Mandatory | O20: ='Partner_Effort'!H19 | P20: Authorized-channel log and observed results. | Q20: Client/board acceptance; numeric target TBD. | R20: Координувати й провести погоджену кампанію залучення / опитування
A21: STR-06 | B21: Track 4 | C21: Analyze responses and prepare client/board findings | D21: =IF('Partner_Effort'!C20="","",'Partner_Effort'!C20) | E21: Partner hours × rate | F21: =IF('Partner_Effort'!D20="","",'Partner_Effort'!D20) | G21: =IF('Partner_Effort'!E20="","",'Partner_Effort'!E20) | H21: =IF('Partner_Effort'!F20="","",'Partner_Effort'!F20) | I21: person-hours | J21: =IF(Inputs!$B$37="","",Inputs!$B$37) | K21: =IF(OR(Inputs!$B$16="",F21="",J21=""),"TBD",F21*J21) | L21: =IF(OR(Inputs!$B$16="",G21="",J21=""),"TBD",G21*J21) | M21: =IF(OR(Inputs!$B$16="",H21="",J21=""),"TBD",H21*J21) | N21: Mandatory | O21: ='Partner_Effort'!H20 | P21: Observed associations distinguished from causation. | Q21: Client/board acceptance; numeric target TBD. | R21: Проаналізувати відповіді та підготувати висновки для клієнта / ради
A22: OPS-01 | B22: Cross-track | C22: Client support and decision coordination | D22: =IF('Partner_Effort'!C21="","",'Partner_Effort'!C21) | E22: Partner hours × rate | F22: =IF('Partner_Effort'!D21="","",'Partner_Effort'!D21) | G22: =IF('Partner_Effort'!E21="","",'Partner_Effort'!E21) | H22: =IF('Partner_Effort'!F21="","",'Partner_Effort'!F21) | I22: person-hours | J22: =IF(Inputs!$B$33="","",Inputs!$B$33) | K22: =IF(OR(Inputs!$B$16="",F22="",J22=""),"TBD",F22*J22) | L22: =IF(OR(Inputs!$B$16="",G22="",J22=""),"TBD",G22*J22) | M22: =IF(OR(Inputs!$B$16="",H22="",J22=""),"TBD",H22*J22) | N22: Mandatory | O22: ='Partner_Effort'!H21 | P22: Decision, approval, risk/change log maintained. | Q22: Client/board acceptance; numeric target TBD. | R22: Підтримка клієнта й координація рішень
A23: OPS-02 | B23: Track 4 | C23: Pilot operational coordination; dossier minutes excluded until measured | D23: =IF('Partner_Effort'!C22="","",'Partner_Effort'!C22) | E23: Partner hours × rate | F23: =IF('Partner_Effort'!D22="","",'Partner_Effort'!D22) | G23: =IF('Partner_Effort'!E22="","",'Partner_Effort'!E22) | H23: =IF('Partner_Effort'!F22="","",'Partner_Effort'!F22) | I23: person-hours | J23: =IF(Inputs!$B$34="","",Inputs!$B$34) | K23: =IF(OR(Inputs!$B$16="",F23="",J23=""),"TBD",F23*J23) | L23: =IF(OR(Inputs!$B$16="",G23="",J23=""),"TBD",G23*J23) | M23: =IF(OR(Inputs!$B$16="",H23="",J23=""),"TBD",H23*J23) | N23: Mandatory | O23: ='Partner_Effort'!H22 | P23: Pilot hand-offs/exceptions logged. | Q23: Client/board acceptance; numeric target TBD. | R23: Операційна координація пілота; хвилини роботи з досьє виключено до вимірювання
A24: OPS-03 | B24: Track 2 | C24: Developer coordination, scope and acceptance | D24: =IF('Partner_Effort'!C23="","",'Partner_Effort'!C23) | E24: Partner hours × rate | F24: =IF('Partner_Effort'!D23="","",'Partner_Effort'!D23) | G24: =IF('Partner_Effort'!E23="","",'Partner_Effort'!E23) | H24: =IF('Partner_Effort'!F23="","",'Partner_Effort'!F23) | I24: person-hours | J24: =IF(Inputs!$B$35="","",Inputs!$B$35) | K24: =IF(OR(Inputs!$B$16="",F24="",J24=""),"TBD",F24*J24) | L24: =IF(OR(Inputs!$B$16="",G24="",J24=""),"TBD",G24*J24) | M24: =IF(OR(Inputs!$B$16="",H24="",J24=""),"TBD",H24*J24) | N24: Mandatory | O24: ='Partner_Effort'!H23 | P24: Requirements/acceptance trace to scope. | Q24: Client/board acceptance; numeric target TBD. | R24: Координація розробників, обсягу робіт і критеріїв приймання
A25: TRN-01 | B25: Track 1 | C25: One-time OSINT/data-management training | D25: Specialist trainer | E25: hourly | I25: person-hours | J25: =IF(Inputs!$B$36="","",Inputs!$B$36) | K25: =IF(OR(Inputs!$B$16="",F25="",J25=""),"TBD",F25*J25) | L25: =IF(OR(Inputs!$B$16="",G25="",J25=""),"TBD",G25*J25) | M25: =IF(OR(Inputs!$B$16="",H25="",J25=""),"TBD",H25*J25) | N25: Mandatory | O25: Max one working day; actual duration, attendees and prep TBD; cap is not base hours. | P25: Training objectives and completion recorded. | Q25: Numeric target TBD unless approved. | R25: Одноразове навчання з OSINT та управління даними
A26: T3-AN-01 | B26: Track 3 | C26: Analyst: data governance, research and knowledge-base work | D26: At least one analyst | E26: hourly | I26: person-hours | J26: =IF(Inputs!$B$37="","",Inputs!$B$37) | K26: =IF(OR(Inputs!$B$16="",F26="",J26=""),"TBD",F26*J26) | L26: =IF(OR(Inputs!$B$16="",G26="",J26=""),"TBD",G26*J26) | M26: =IF(OR(Inputs!$B$16="",H26="",J26=""),"TBD",H26*J26) | N26: Mandatory | O26: Hours TBD; allocate once across packages, without double-counting. | P26: Source-attributed data/knowledge output accepted. | Q26: Numeric target TBD unless approved. | R26: Аналітик: управління даними, дослідження та робота з базою знань
A27: SW-01 | B27: Track 2 | C27: Residual application implementation, QA, security and deployment | D27: Developer/vendor | E27: quote | I27: contract currency/project | K27: =IF(OR(Inputs!$B$16="",F27=""),"TBD",F27) | L27: =IF(OR(Inputs!$B$16="",G27=""),"TBD",G27) | M27: =IF(OR(Inputs!$B$16="",H27=""),"TBD",H27) | N27: Mandatory | O27: Quote after demo, residual scope, acceptance, data access, IP and support are reconciled; no historical greenfield estimate. | P27: Agreed workflows pass UAT/security/QA. | Q27: Numeric target TBD unless approved. | R27: Залишкова розробка застосунку, QA, безпека й розгортання
A28: DATA-01 | B28: Track 3 | C28: Data model, analytics, dashboard and knowledge-base integration | D28: Developer/data vendor | E28: quote | I28: contract currency/project | K28: =IF(OR(Inputs!$B$16="",F28=""),"TBD",F28) | L28: =IF(OR(Inputs!$B$16="",G28=""),"TBD",G28) | M28: =IF(OR(Inputs!$B$16="",H28=""),"TBD",H28) | N28: Mandatory | O28: Quote after data rights, provenance, owners, metrics and refresh rules are agreed. | P28: Lineage/access/refresh rules and outputs accepted. | Q28: Numeric target TBD unless approved. | R28: Модель даних, аналітика, панель і інтеграція бази знань
A29: COMM-EXT | B29: Track 4 | C29: Campaign, survey, publication, translation and event direct expenses | D29: External suppliers | E29: quote | I29: contract currency/project | K29: =IF(OR(Inputs!$B$16="",F29=""),"TBD",F29) | L29: =IF(OR(Inputs!$B$16="",G29=""),"TBD",G29) | M29: =IF(OR(Inputs!$B$16="",H29=""),"TBD",H29) | N29: Mandatory | O29: Quote/verified cost required; no audience or fee assumed. | P29: Approved assets/events delivered; channel results recorded. | Q29: Numeric target TBD unless approved. | R29: Прямі витрати кампанії, опитування, публікації, перекладу й заходів
A30: DOS-PREP | B30: Dossier pilot | C30: Human preparation per dossier | D30: Analyst/operator | E30: dossier-hour | F30: =IF('Revised_Scope'!C27="TBD","",'Revised_Scope'!C27) | G30: =IF('Revised_Scope'!C28="TBD","",'Revised_Scope'!C28) | H30: =IF('Revised_Scope'!C29="TBD","",'Revised_Scope'!C29) | I30: person-hours | J30: =IF(Inputs!$B$37="","",Inputs!$B$37) | K30: =IF(OR(Inputs!$B$16="",F30="",J30=""),"TBD",F30*J30) | L30: =IF(OR(Inputs!$B$16="",G30="",J30=""),"TBD",G30*J30) | M30: =IF(OR(Inputs!$B$16="",H30="",J30=""),"TBD",H30*J30) | N30: Decision required | O30: Hours link to Revised_Scope; possible volume only; measure in approved live pilot. | P30: Observed minutes per dossier; target TBD. | Q30: Numeric target TBD unless approved. | R30: Людська підготовка одного досьє
A31: DOS-VERIFY | B31: Dossier pilot | C31: Human evidence review/verification | D31: Selected reviewer(s) | E31: dossier-hour | F31: =IF('Revised_Scope'!D27="TBD","",'Revised_Scope'!D27) | G31: =IF('Revised_Scope'!D28="TBD","",'Revised_Scope'!D28) | H31: =IF('Revised_Scope'!D29="TBD","",'Revised_Scope'!D29) | I31: person-hours | J31: =IF(Inputs!$B$38="","",Inputs!$B$38) | K31: =IF(OR(Inputs!$B$16="",F31="",J31=""),"TBD",F31*J31) | L31: =IF(OR(Inputs!$B$16="",G31="",J31=""),"TBD",G31*J31) | M31: =IF(OR(Inputs!$B$16="",H31="",J31=""),"TBD",H31*J31) | N31: Decision required | O31: Time linked from Revised_Scope; payment status unmeasured. | P31: Review traceability; threshold to be agreed. | Q31: Numeric target TBD unless approved. | R31: Людський перегляд / перевірка доказів
A32: DOS-REWORK | B32: Dossier pilot | C32: Correction, appeal and rework | D32: Reviewer/operator | E32: dossier-hour | F32: =IF('Revised_Scope'!E27="TBD","",'Revised_Scope'!E27) | G32: =IF('Revised_Scope'!E28="TBD","",'Revised_Scope'!E28) | H32: =IF('Revised_Scope'!E29="TBD","",'Revised_Scope'!E29) | I32: person-hours | J32: =IF(Inputs!$B$38="","",Inputs!$B$38) | K32: =IF(OR(Inputs!$B$16="",F32="",J32=""),"TBD",F32*J32) | L32: =IF(OR(Inputs!$B$16="",G32="",J32=""),"TBD",G32*J32) | M32: =IF(OR(Inputs!$B$16="",H32="",J32=""),"TBD",H32*J32) | N32: Decision required | O32: Measured only; no exception/rework rate assumed. | P32: Observed minutes and cases reported. | Q32: Numeric target TBD unless approved. | R32: Виправлення, оскарження та повторна робота
A33: DOS-CLIENT | B33: Dossier pilot | C33: Client decision/approval effort | D33: Client-side approver | E33: dossier-client | F33: =IF('Revised_Scope'!F27="TBD","",'Revised_Scope'!F27) | G33: =IF('Revised_Scope'!F28="TBD","",'Revised_Scope'!F28) | H33: =IF('Revised_Scope'!F29="TBD","",'Revised_Scope'!F29) | I33: person-hours | K33: Not priced — client-side effort | L33: Not priced — client-side effort | M33: Not priced — client-side effort | N33: Client-side effort | O33: Client hours shown separately and excluded from supplier price; batch/per-dossier allocation TBD. | P33: Client approval effort measured separately. | Q33: Numeric target TBD unless approved. | R33: Час клієнта на ухвалення / погодження рішень
A34: DOS-API | B34: Dossier pilot | C34: AI provider/API usage for dossier preparation | D34: Selected provider | E34: dossier-api | F34: =IF('Revised_Scope'!I27="TBD","",'Revised_Scope'!I27) | G34: =IF('Revised_Scope'!I28="TBD","",'Revised_Scope'!I28) | H34: =IF('Revised_Scope'!I29="TBD","",'Revised_Scope'!I29) | I34: contract currency/scenario | K34: =IF(OR(Inputs!$B$16="",F34=""),"TBD",F34) | L34: =IF(OR(Inputs!$B$16="",G34=""),"TBD",G34) | M34: =IF(OR(Inputs!$B$16="",H34=""),"TBD",H34) | N34: Decision required | O34: Linked to Revised_Scope; provider/model/profile unselected. | P34: Metered cost per dossier; no cost assumed. | Q34: Numeric target TBD unless approved. | R34: Використання AI-провайдера / API для підготовки досьє
A35: GATE-4A | B35: Track 4A | C35: Pilot evaluation and written continuation decision | D35: Partners/client/evaluator | E35: quote | I35: contract currency/project | K35: =IF(OR(Inputs!$B$16="",F35=""),"TBD",F35) | L35: =IF(OR(Inputs!$B$16="",G35=""),"TBD",G35) | M35: =IF(OR(Inputs!$B$16="",H35=""),"TBD",H35) | N35: Decision required | O35: Go/no-go scope and evaluation design not selected. | P35: Written stop/continue decision against agreed criteria. | Q35: Numeric target TBD unless approved. | R35: Оцінка пілота й письмове рішення про продовження
A36: T5-BUILD | B36: Track 5 | C36: Conditional AI/OSINT/chatbot implementation/integration | D36: Developer/vendor | E36: quote | I36: contract currency/project | K36: =IF(OR(Inputs!$B$16="",F36=""),"TBD",F36) | L36: =IF(OR(Inputs!$B$16="",G36=""),"TBD",G36) | M36: =IF(OR(Inputs!$B$16="",H36=""),"TBD",H36) | N36: Decision required | O36: Only after Gate 4A approval and data rights/readiness. | P36: Agreed citations, audit, human review and rollback tested. | Q36: Numeric target TBD unless approved. | R36: Умовна розробка / інтеграція AI, OSINT або чатбота
A37: T5-USAGE | B37: Track 5 | C37: Conditional model/API/OSINT usage | D37: Selected provider(s) | E37: quote | I37: contract currency/project-period | K37: =IF(OR(Inputs!$B$16="",F37=""),"TBD",F37) | L37: =IF(OR(Inputs!$B$16="",G37=""),"TBD",G37) | M37: =IF(OR(Inputs!$B$16="",H37=""),"TBD",H37) | N37: Decision required | O37: Provider, duration and workload profile not selected. | P37: Usage/cost against approved ceiling; ceiling TBD. | Q37: Numeric target TBD unless approved. | R37: Умовне використання моделей / API / OSINT
A38: LEGAL-01 | B38: Cross-track | C38: Privacy, legal, security and data-rights review | D38: Qualified reviewer | E38: quote | I38: contract currency/project | K38: =IF(OR(Inputs!$B$16="",F38=""),"TBD",F38) | L38: =IF(OR(Inputs!$B$16="",G38=""),"TBD",G38) | M38: =IF(OR(Inputs!$B$16="",H38=""),"TBD",H38) | N38: Mandatory | O38: Scope depends on lawful basis, data access, jurisdiction and providers. | P38: Review completed and control actions tracked. | Q38: Numeric target TBD unless approved. | R38: Перевірка приватності, права, безпеки й прав на дані
A39: OPS-RUN | B39: Post-launch | C39: Post-launch operations/support for agreed period | D39: Service team | E39: monthly | F39: =IF(Inputs!$B$45="","",Inputs!$B$45) | G39: =IF(Inputs!$B$45="","",Inputs!$B$45) | H39: =IF(Inputs!$B$45="","",Inputs!$B$45) | I39: months | J39: =IF(Inputs!$B$23="","",Inputs!$B$23) | K39: =IF(OR(Inputs!$B$16="",F39="",J39=""),"TBD",F39*J39) | L39: =IF(OR(Inputs!$B$16="",G39="",J39=""),"TBD",G39*J39) | M39: =IF(OR(Inputs!$B$16="",H39="",J39=""),"TBD",H39*J39) | N39: Decision required | O39: Inputs!B23 monthly rate × Inputs!B45 duration; no default period. | P39: Service levels agreed. | Q39: Numeric target TBD unless approved. | R39: Операції / підтримка після запуску за погоджений період
A40: SAAS-RUN | B40: Post-launch | C40: Hosting, licences and recurring SaaS | D40: Selected providers | E40: monthly | F40: =IF(Inputs!$B$46="","",Inputs!$B$46) | G40: =IF(Inputs!$B$46="","",Inputs!$B$46) | H40: =IF(Inputs!$B$46="","",Inputs!$B$46) | I40: months | J40: =IF(Inputs!$B$24="","",Inputs!$B$24) | K40: =IF(OR(Inputs!$B$16="",F40="",J40=""),"TBD",F40*J40) | L40: =IF(OR(Inputs!$B$16="",G40="",J40=""),"TBD",G40*J40) | M40: =IF(OR(Inputs!$B$16="",H40="",J40=""),"TBD",H40*J40) | N40: Decision required | O40: Inputs!B24 monthly cost × Inputs!B46 duration; providers/period TBD. | P40: Availability/retention/backup/licence terms verified. | Q40: Numeric target TBD unless approved. | R40: Хостинг, ліцензії та регулярні SaaS-витрати
A41: ASSIST-01 | B41: Optional | C41: Optional assistant capacity | D41: Assistant | E41: assistant | I41: person-hours | J41: =IF(Inputs!$B$39="","",Inputs!$B$39) | K41: =IF(OR(Inputs!$B$16="",F41="",J41=""),"TBD",F41*J41) | L41: =IF(OR(Inputs!$B$16="",G41="",J41=""),"TBD",G41*J41) | M41: =IF(OR(Inputs!$B$16="",H41="",J41=""),"TBD",H41*J41) | N41: =IF(Inputs!$B$44="Yes","Selected — include","Optional — excluded") | O41: Only if Inputs!B44=Yes; hours/rate not assumed. | P41: Task scope agreed before entry. | Q41: Numeric target TBD unless approved. | R41: Необов’язкова потужність асистента
A42: TRAVEL-01 | B42: Cross-track | C42: Approved travel/fieldwork/in-person meeting expenses | D42: Approved suppliers/partners | E42: quote | I42: contract currency/project | K42: =IF(OR(Inputs!$B$16="",F42=""),"TBD",F42) | L42: =IF(OR(Inputs!$B$16="",G42=""),"TBD",G42) | M42: =IF(OR(Inputs!$B$16="",H42=""),"TBD",H42) | N42: Decision required | O42: Only if required and approved; no frequency/amount assumed. | P42: Authorization and receipts/quotes recorded. | Q42: Numeric target TBD unless approved. | R42: Погоджені витрати на поїздки / польову роботу / очну зустріч
A43: REUSE-ALLOC | B43: Internal allocation | C43: Graph/search reuse — conditional internal allocation after partner agreement; not a client fee | D43: Internal partner allocation | E43: demo | I43: contract currency/module | K43: =IF(OR(Inputs!$B$16="",Inputs!$B$30=""),"TBD",Inputs!$B$30) | L43: =IF(OR(Inputs!$B$16="",Inputs!$B$30=""),"TBD",Inputs!$B$30) | M43: =IF(OR(Inputs!$B$16="",Inputs!$B$30=""),"TBD",Inputs!$B$30) | N43: Internal allocation | O43: Inputs!B30; only if reused. Not additive or double-counted. | P43: Reuse boundary/fee agreed; paid after first client payment. | Q43: Numeric target TBD unless approved. | R43: Винагорода за повторне використання демо-модуля після першого платежу клієнта
A45: Project-wide scenario roll-up — pre-tax, contract currency only / Зведення сценаріїв усього проєкту — до податків, лише у валюті контракту
A46: Summary item / Показник | B46: Low / Низький | C46: Base / Базовий | D46: High / Високий | E46: Interpretation / Тлумачення
A47: Track 1 — Strategy, consulting & reports | E47: Core partner work; T&I prep remains conditional. | K47: =IF(COUNTIFS($B$7:$B$43,"Track 1",$N$7:$N$43,"Mandatory",$K$7:$K$43,"TBD")+COUNTIFS($B$7:$B$43,"Track 1",$N$7:$N$43,"Selected — include",$K$7:$K$43,"TBD")>0,"TBD",SUMIFS($K$7:$K$43,$B$7:$B$43,"Track 1",$N$7:$N$43,"Mandatory")+SUMIFS($K$7:$K$43,$B$7:$B$43,"Track 1",$N$7:$N$43,"Selected — include")) | L47: =IF(COUNTIFS($B$7:$B$43,"Track 1",$N$7:$N$43,"Mandatory",$L$7:$L$43,"TBD")+COUNTIFS($B$7:$B$43,"Track 1",$N$7:$N$43,"Selected — include",$L$7:$L$43,"TBD")>0,"TBD",SUMIFS($L$7:$L$43,$B$7:$B$43,"Track 1",$N$7:$N$43,"Mandatory")+SUMIFS($L$7:$L$43,$B$7:$B$43,"Track 1",$N$7:$N$43,"Selected — include")) | M47: =IF(COUNTIFS($B$7:$B$43,"Track 1",$N$7:$N$43,"Mandatory",$M$7:$M$43,"TBD")+COUNTIFS($B$7:$B$43,"Track 1",$N$7:$N$43,"Selected — include",$M$7:$M$43,"TBD")>0,"TBD",SUMIFS($M$7:$M$43,$B$7:$B$43,"Track 1",$N$7:$N$43,"Mandatory")+SUMIFS($M$7:$M$43,$B$7:$B$43,"Track 1",$N$7:$N$43,"Selected — include"))
A48: Track 2 — Functional integrated application | E48: Residual build only. | K48: =IF(COUNTIFS($B$7:$B$43,"Track 2",$N$7:$N$43,"Mandatory",$K$7:$K$43,"TBD")+COUNTIFS($B$7:$B$43,"Track 2",$N$7:$N$43,"Selected — include",$K$7:$K$43,"TBD")>0,"TBD",SUMIFS($K$7:$K$43,$B$7:$B$43,"Track 2",$N$7:$N$43,"Mandatory")+SUMIFS($K$7:$K$43,$B$7:$B$43,"Track 2",$N$7:$N$43,"Selected — include")) | L48: =IF(COUNTIFS($B$7:$B$43,"Track 2",$N$7:$N$43,"Mandatory",$L$7:$L$43,"TBD")+COUNTIFS($B$7:$B$43,"Track 2",$N$7:$N$43,"Selected — include",$L$7:$L$43,"TBD")>0,"TBD",SUMIFS($L$7:$L$43,$B$7:$B$43,"Track 2",$N$7:$N$43,"Mandatory")+SUMIFS($L$7:$L$43,$B$7:$B$43,"Track 2",$N$7:$N$43,"Selected — include")) | M48: =IF(COUNTIFS($B$7:$B$43,"Track 2",$N$7:$N$43,"Mandatory",$M$7:$M$43,"TBD")+COUNTIFS($B$7:$B$43,"Track 2",$N$7:$N$43,"Selected — include",$M$7:$M$43,"TBD")>0,"TBD",SUMIFS($M$7:$M$43,$B$7:$B$43,"Track 2",$N$7:$N$43,"Mandatory")+SUMIFS($M$7:$M$43,$B$7:$B$43,"Track 2",$N$7:$N$43,"Selected — include"))
A49: Track 3 — Analytics, data & knowledge | E49: Analyst/vendor work; dossier pilot separate. | K49: =IF(COUNTIFS($B$7:$B$43,"Track 3",$N$7:$N$43,"Mandatory",$K$7:$K$43,"TBD")+COUNTIFS($B$7:$B$43,"Track 3",$N$7:$N$43,"Selected — include",$K$7:$K$43,"TBD")>0,"TBD",SUMIFS($K$7:$K$43,$B$7:$B$43,"Track 3",$N$7:$N$43,"Mandatory")+SUMIFS($K$7:$K$43,$B$7:$B$43,"Track 3",$N$7:$N$43,"Selected — include")) | L49: =IF(COUNTIFS($B$7:$B$43,"Track 3",$N$7:$N$43,"Mandatory",$L$7:$L$43,"TBD")+COUNTIFS($B$7:$B$43,"Track 3",$N$7:$N$43,"Selected — include",$L$7:$L$43,"TBD")>0,"TBD",SUMIFS($L$7:$L$43,$B$7:$B$43,"Track 3",$N$7:$N$43,"Mandatory")+SUMIFS($L$7:$L$43,$B$7:$B$43,"Track 3",$N$7:$N$43,"Selected — include")) | M49: =IF(COUNTIFS($B$7:$B$43,"Track 3",$N$7:$N$43,"Mandatory",$M$7:$M$43,"TBD")+COUNTIFS($B$7:$B$43,"Track 3",$N$7:$N$43,"Selected — include",$M$7:$M$43,"TBD")>0,"TBD",SUMIFS($M$7:$M$43,$B$7:$B$43,"Track 3",$N$7:$N$43,"Mandatory")+SUMIFS($M$7:$M$43,$B$7:$B$43,"Track 3",$N$7:$N$43,"Selected — include"))
A50: Track 4 — Communications, publications & events | E50: Partner work and direct costs. | K50: =IF(COUNTIFS($B$7:$B$43,"Track 4",$N$7:$N$43,"Mandatory",$K$7:$K$43,"TBD")+COUNTIFS($B$7:$B$43,"Track 4",$N$7:$N$43,"Selected — include",$K$7:$K$43,"TBD")>0,"TBD",SUMIFS($K$7:$K$43,$B$7:$B$43,"Track 4",$N$7:$N$43,"Mandatory")+SUMIFS($K$7:$K$43,$B$7:$B$43,"Track 4",$N$7:$N$43,"Selected — include")) | L50: =IF(COUNTIFS($B$7:$B$43,"Track 4",$N$7:$N$43,"Mandatory",$L$7:$L$43,"TBD")+COUNTIFS($B$7:$B$43,"Track 4",$N$7:$N$43,"Selected — include",$L$7:$L$43,"TBD")>0,"TBD",SUMIFS($L$7:$L$43,$B$7:$B$43,"Track 4",$N$7:$N$43,"Mandatory")+SUMIFS($L$7:$L$43,$B$7:$B$43,"Track 4",$N$7:$N$43,"Selected — include")) | M50: =IF(COUNTIFS($B$7:$B$43,"Track 4",$N$7:$N$43,"Mandatory",$M$7:$M$43,"TBD")+COUNTIFS($B$7:$B$43,"Track 4",$N$7:$N$43,"Selected — include",$M$7:$M$43,"TBD")>0,"TBD",SUMIFS($M$7:$M$43,$B$7:$B$43,"Track 4",$N$7:$N$43,"Mandatory")+SUMIFS($M$7:$M$43,$B$7:$B$43,"Track 4",$N$7:$N$43,"Selected — include"))
A51: Track 4A — Pilot evaluation gate | E51: Not included until go/no-go scope is decided. | K51: =IF(COUNTIFS($B$7:$B$43,"Track 4A",$N$7:$N$43,"Decision required",$K$7:$K$43,"TBD")>0,"TBD",SUMIFS($K$7:$K$43,$B$7:$B$43,"Track 4A",$N$7:$N$43,"Decision required")) | L51: =IF(COUNTIFS($B$7:$B$43,"Track 4A",$N$7:$N$43,"Decision required",$L$7:$L$43,"TBD")>0,"TBD",SUMIFS($L$7:$L$43,$B$7:$B$43,"Track 4A",$N$7:$N$43,"Decision required")) | M51: =IF(COUNTIFS($B$7:$B$43,"Track 4A",$N$7:$N$43,"Decision required",$M$7:$M$43,"TBD")>0,"TBD",SUMIFS($M$7:$M$43,$B$7:$B$43,"Track 4A",$N$7:$N$43,"Decision required"))
A52: Track 5 — Conditional AI/OSINT/chatbot | E52: Excluded until Track 4A approval. | K52: =IF(COUNTIFS($B$7:$B$43,"Track 5",$N$7:$N$43,"Decision required",$K$7:$K$43,"TBD")>0,"TBD",SUMIFS($K$7:$K$43,$B$7:$B$43,"Track 5",$N$7:$N$43,"Decision required")) | L52: =IF(COUNTIFS($B$7:$B$43,"Track 5",$N$7:$N$43,"Decision required",$L$7:$L$43,"TBD")>0,"TBD",SUMIFS($L$7:$L$43,$B$7:$B$43,"Track 5",$N$7:$N$43,"Decision required")) | M52: =IF(COUNTIFS($B$7:$B$43,"Track 5",$N$7:$N$43,"Decision required",$M$7:$M$43,"TBD")>0,"TBD",SUMIFS($M$7:$M$43,$B$7:$B$43,"Track 5",$N$7:$N$43,"Decision required"))
A53: Dossier pilot — possible volume scenarios | E53: Possible volume only; minutes/API costs need measurement/quote. | K53: =IF(COUNTIFS($B$7:$B$43,"Dossier pilot",$N$7:$N$43,"Decision required",$K$7:$K$43,"TBD")>0,"TBD",SUMIFS($K$7:$K$43,$B$7:$B$43,"Dossier pilot",$N$7:$N$43,"Decision required")) | L53: =IF(COUNTIFS($B$7:$B$43,"Dossier pilot",$N$7:$N$43,"Decision required",$L$7:$L$43,"TBD")>0,"TBD",SUMIFS($L$7:$L$43,$B$7:$B$43,"Dossier pilot",$N$7:$N$43,"Decision required")) | M53: =IF(COUNTIFS($B$7:$B$43,"Dossier pilot",$N$7:$N$43,"Decision required",$M$7:$M$43,"TBD")>0,"TBD",SUMIFS($M$7:$M$43,$B$7:$B$43,"Dossier pilot",$N$7:$N$43,"Decision required"))
A54: Post-launch operations and SaaS | E54: Period/monthly costs not selected. | K54: =IF(COUNTIFS($B$7:$B$43,"Post-launch",$N$7:$N$43,"Decision required",$K$7:$K$43,"TBD")>0,"TBD",SUMIFS($K$7:$K$43,$B$7:$B$43,"Post-launch",$N$7:$N$43,"Decision required")) | L54: =IF(COUNTIFS($B$7:$B$43,"Post-launch",$N$7:$N$43,"Decision required",$L$7:$L$43,"TBD")>0,"TBD",SUMIFS($L$7:$L$43,$B$7:$B$43,"Post-launch",$N$7:$N$43,"Decision required")) | M54: =IF(COUNTIFS($B$7:$B$43,"Post-launch",$N$7:$N$43,"Decision required",$M$7:$M$43,"TBD")>0,"TBD",SUMIFS($M$7:$M$43,$B$7:$B$43,"Post-launch",$N$7:$N$43,"Decision required"))
A55: Optional assistant | E55: Excluded unless selected and estimated. | K55: =IF(COUNTIFS($N$7:$N$43,"Optional — excluded",$K$7:$K$43,"TBD")>0,"TBD",SUMIFS($K$7:$K$43,$N$7:$N$43,"Optional — excluded")) | L55: =IF(COUNTIFS($N$7:$N$43,"Optional — excluded",$L$7:$L$43,"TBD")>0,"TBD",SUMIFS($L$7:$L$43,$N$7:$N$43,"Optional — excluded")) | M55: =IF(COUNTIFS($N$7:$N$43,"Optional — excluded",$M$7:$M$43,"TBD")>0,"TBD",SUMIFS($M$7:$M$43,$N$7:$N$43,"Optional — excluded"))
A56: Demo reuse fee — internal allocation | E56: Not additive; conditional on reuse/first client payment. | K56: =IF(COUNTIFS($N$7:$N$43,"Internal allocation",$K$7:$K$43,"TBD")>0,"TBD",SUMIFS($K$7:$K$43,$N$7:$N$43,"Internal allocation")) | L56: =IF(COUNTIFS($N$7:$N$43,"Internal allocation",$L$7:$L$43,"TBD")>0,"TBD",SUMIFS($L$7:$L$43,$N$7:$N$43,"Internal allocation")) | M56: =IF(COUNTIFS($N$7:$N$43,"Internal allocation",$M$7:$M$43,"TBD")>0,"TBD",SUMIFS($M$7:$M$43,$N$7:$N$43,"Internal allocation"))
A57: Selected-scope total — mandatory + selected | E57: Subtotal excludes unresolved gates; pre-tax. | K57: =IF(COUNTIFS($N$7:$N$43,"Mandatory",$K$7:$K$43,"TBD")+COUNTIFS($N$7:$N$43,"Selected — include",$K$7:$K$43,"TBD")>0,"TBD",SUMIFS($K$7:$K$43,$N$7:$N$43,"Mandatory")+SUMIFS($K$7:$K$43,$N$7:$N$43,"Selected — include")) | L57: =IF(COUNTIFS($N$7:$N$43,"Mandatory",$L$7:$L$43,"TBD")+COUNTIFS($N$7:$N$43,"Selected — include",$L$7:$L$43,"TBD")>0,"TBD",SUMIFS($L$7:$L$43,$N$7:$N$43,"Mandatory")+SUMIFS($L$7:$L$43,$N$7:$N$43,"Selected — include")) | M57: =IF(COUNTIFS($N$7:$N$43,"Mandatory",$M$7:$M$43,"TBD")+COUNTIFS($N$7:$N$43,"Selected — include",$M$7:$M$43,"TBD")>0,"TBD",SUMIFS($M$7:$M$43,$N$7:$N$43,"Mandatory")+SUMIFS($M$7:$M$43,$N$7:$N$43,"Selected — include"))
A58: Full-project price status | B58: =IF(COUNTIF($N$7:$N$43,"Decision required")>0,"TBD — resolve scope gates",IF(COUNTIFS($N$7:$N$43,"Mandatory",$L$7:$L$43,"TBD")+COUNTIFS($N$7:$N$43,"Selected — include",$L$7:$L$43,"TBD")>0,"TBD — required inputs missing","Ready for review"))
A59: Lower-bound estimate vs agreed project reference | B59: =IF(OR(Inputs!B47="",Inputs!B47<=0,K57="TBD"),"TBD",K57/Inputs!B47-1) | E59: Formula: (lower-bound whole-project total − agreed reference whole-project total) ÷ agreed reference whole-project total; same scope, currency and period required.
A60: Upper-bound estimate vs agreed project reference | B60: =IF(OR(Inputs!B47="",Inputs!B47<=0,M57="TBD"),"TBD",M57/Inputs!B47-1) | E60: Formula: (upper-bound whole-project total − agreed reference whole-project total) ÷ agreed reference whole-project total; same scope, currency and period required.

Sheet Work_Packages
A1: Historical greenfield fixed-core packages — earlier scope only
A2: HISTORICAL REFERENCE: These Low/Base/High packages are not an estimate for the revised workflow. Do not use their totals as the current client budget or subtract unverified reuse hours.
A4: WBS ID | B4: Work package | C4: Included scope / completion outcome | D4: Dependencies | E4: Low person-hours | F4: Base person-hours | G4: High person-hours | H4: Status / source locator
A5: CORE-01 | B5: Discovery, product and security architecture | C5: Define user journeys, role/access matrix, domain model, acceptance scenarios, privacy rules and architecture decision record. Output: reviewed implementation backlog and unresolved-decision register. | D5: — | E5: 120 | F5: 160 | G5: 220 | H5: [ASSUMPTION]; source Pricing Model > Core Estimate, row 7.
A6: CORE-02 | B6: UX, design system and accessible responsive UI | C6: Design one-page network workspace, explicit mode/layer states, stacked panels, responsive touch layout, keyboard operation and bilingual UI. | D6: CORE-01 | E6: 100 | F6: 140 | G6: 190 | H6: [ASSUMPTION]; source Pricing Model > Core Estimate, row 8.
A7: CORE-03 | B7: Identity, authorization, consent and audit foundation | C7: Implement managed sign-in, role/scope checks, guest/member/operator/admin access, profile visibility/consent, contact separation and audit events. | D7: CORE-01 | E7: 180 | F7: 240 | G7: 330 | H7: [ASSUMPTION]; source Pricing Model > Core Estimate, row 9.
A8: CORE-04 | B8: Live data model and operator workspace | C8: Build schema, migrations, validation/import staging, provenance, deduplication review, correction workflow, operator queues and live graph APIs. Use synthetic/de-identified data until rights are approved. | D8: CORE-01, CORE-03 | E8: 180 | F8: 260 | G8: 380 | H8: [ASSUMPTION]; source Pricing Model > Core Estimate, row 10.
A9: CORE-05 | B9: Expert profiles and evidence-backed verification | C9: Implement profiles, evidence source/date/reviewer, verification states, provenance, corrections, appeal/review workflow and disclosure rules. No composite Trust/Influence score. | D9: CORE-03, CORE-04 | E9: 200 | F9: 290 | G9: 420 | H9: [ASSUMPTION]; source Pricing Model > Core Estimate, row 11.
A10: CORE-06 | B10: Expert search, filters and layered network graph | C10: Implement searchable profiles, sector/geography/topic filters, expert and feature layers, layer toggles, dependencies view, graph-to-dossier navigation and text-accessible equivalent. | D10: CORE-02, CORE-04, CORE-05 | E10: 180 | F10: 260 | G10: 380 | H10: [ASSUMPTION]; source Pricing Model > Core Estimate, row 12.
A11: CORE-07 | B11: Community collaboration and basic events | C11: Implement groups, member feed/posts, comments, shared resources, basic opportunities, event notices, moderation, delegated group administration and transactional email. No complex PM or E2EE. | D11: CORE-02, CORE-03, CORE-04 | E11: 220 | F11: 320 | G11: 470 | H11: [ASSUMPTION]; source Pricing Model > Core Estimate, row 13.
A12: CORE-08 | B12: Expert intake, recruitment and onboarding | C12: Implement consent-aware intake, campaign records, source tracking, candidate triage, human-reviewed verification handoff, onboarding and membership status. No autonomous AI decisions or social-platform automation. | D12: CORE-03, CORE-04, CORE-05, CORE-07 | E12: 160 | F12: 240 | G12: 360 | H12: [ASSUMPTION]; source Pricing Model > Core Estimate, row 14.
A13: CORE-09 | B13: Engagement operations and basic health analytics | C13: Implement group-owner tools, activity/participation measures, dormant-group signals, re-engagement tasks and basic role assignment workflow. No ranking or automatic privilege elevation. | D13: CORE-03, CORE-07, CORE-08 | E13: 140 | F13: 210 | G13: 320 | H13: [ASSUMPTION]; source Pricing Model > Core Estimate, row 15.
A14: CORE-10 | B14: Security hardening and privacy verification | C14: Threat-model core flows, verify authorization and minimization, configure secrets/encryption/secure defaults, test access/audit paths, prepare incident and retention controls. | D14: CORE-03, CORE-04, CORE-05, CORE-07, CORE-08, CORE-09 | E14: 80 | F14: 120 | G14: 180 | H14: [ASSUMPTION]; source Pricing Model > Core Estimate, row 16.
A15: CORE-11 | B15: Quality assurance, accessibility and acceptance testing | C15: Test role/data isolation, imports, graph interactions, workflows, failure paths, mobile/touch/keyboard and bilingual presentation; prepare acceptance scripts and regression coverage. | D15: CORE-02 through CORE-10 | E15: 180 | F15: 270 | G15: 400 | H15: [ASSUMPTION]; source Pricing Model > Core Estimate, row 17.
A16: CORE-12 | B16: Deployment, observability, backup and operational handover | C16: Create environments, CI/CD, monitoring/error logs, backup/restore checks, operational runbook and release handover. | D16: CORE-03, CORE-04, CORE-10, CORE-11 | E16: 100 | F16: 150 | G16: 230 | H16: [ASSUMPTION]; source Pricing Model > Core Estimate, row 18.
A17: CORE-13 | B17: Delivery management and client acceptance | C17: Coordinate dependencies, decisions, demonstrations, review cycles, issue triage, scope control and handover documentation through acceptance. | D17: CORE-01 through CORE-12 | E17: 100 | F17: 150 | G17: 240 | H17: [ASSUMPTION]; source Pricing Model > Core Estimate, row 19.
A18: TOTAL — fixed core | E18: =SUM(E5:E17) | F18: =SUM(F5:F17) | G18: =SUM(G5:G17) | H18: Formula totals of assumption inputs; source workbook Core Estimate rows 7–19.

Sheet Budget_Model
A1: Historical greenfield sensitivity, allocation checks and residual economics
A2: HISTORICAL REFERENCE ONLY — rate sensitivities below use the earlier 13-package Low/Base/High estimate; they are not a revised-scope quote or current client price.
A3: A. Historical published-rate sensitivity — not a revised-scope proposal price
A4: Effort case | B4: Person-hours | C4: Ukraine low ($/h) | D4: Ukraine high ($/h) | E4: Ukraine low sensitivity (USD) | F4: Ukraine high sensitivity (USD) | G4: US low ($/h) | H4: US high ($/h) | I4: US low sensitivity (USD) | J4: US high sensitivity (USD)
A5: Low | B5: =Work_Packages!E18 | C5: =Inputs!B4 | D5: =Inputs!B5 | E5: =B5*C5 | F5: =B5*D5 | G5: =Inputs!B6 | H5: =Inputs!B7 | I5: =B5*G5 | J5: =B5*H5
A6: Base | B6: =Work_Packages!F18 | C6: =Inputs!B4 | D6: =Inputs!B5 | E6: =B6*C6 | F6: =B6*D6 | G6: =Inputs!B6 | H6: =Inputs!B7 | I6: =B6*G6 | J6: =B6*H6
A7: High | B7: =Work_Packages!G18 | C7: =Inputs!B4 | D7: =Inputs!B5 | E7: =B7*C7 | F7: =B7*D7 | G7: =Inputs!B6 | H7: =Inputs!B7 | I7: =B7*G7 | J7: =B7*H7
A9: Interpretation | B9: Formula: assumed person-hours × published provider rate endpoint. These figures omit confirmed partner fees, selected implementation location, taxes, contingency, FX, hosting, licences, AI usage, recurring support, and profit. They are sensitivity examples, not a complete project budget.
A12: B. Target allocation ranges — do not sum endpoints as a final budget
A13: Contract currency and total budget | B13: =IF(OR(Inputs!B16="",Inputs!B17=""),"TBD",Inputs!B16&" "&TEXT(Inputs!B17,"0.00")) | D13: Selected developer share within target band | E13: =IF(Inputs!B25="","TBD",IF(OR(Inputs!B25<Inputs!B8,Inputs!B25>Inputs!B9),"OUTSIDE TARGET","WITHIN TARGET"))
A14: Developer target — lower | B14: =IF(OR(Inputs!B16="",Inputs!B17=""),"TBD",Inputs!B17*Inputs!B8) | D14: Selected operations share within target band | E14: =IF(Inputs!B26="","TBD",IF(OR(Inputs!B26<Inputs!B10,Inputs!B26>Inputs!B11),"OUTSIDE TARGET","WITHIN TARGET"))
A15: Developer target — upper | B15: =IF(OR(Inputs!B16="",Inputs!B17=""),"TBD",Inputs!B17*Inputs!B9) | D15: Combined minimum target share | E15: =Inputs!B8+Inputs!B10
A16: Core team / admin / relationships / representation — lower | B16: =IF(OR(Inputs!B16="",Inputs!B17=""),"TBD",Inputs!B17*Inputs!B10) | D16: Combined maximum target share | E16: =Inputs!B9+Inputs!B11
A17: Core team / admin / relationships / representation — upper | B17: =IF(OR(Inputs!B16="",Inputs!B17=""),"TBD",Inputs!B17*Inputs!B11) | D17: Profit/reinvestment ceiling | E17: =Inputs!B12
A18: Target-band envelope, both categories at minimum | B18: =Inputs!B8+Inputs!B10 | D18: Allocation note | E18: The maximum developer and operations target bands already sum to the full budget. Any profit/reinvestment is only a share of positive residual after verified costs; it is not an extra allocation on top.
A19: Target-band envelope, both categories at maximum | B19: =Inputs!B9+Inputs!B11
A20: Unallocated share at selected targets (not profit) | B20: =IF(OR(Inputs!B25="",Inputs!B26=""),"TBD",IF(Inputs!B25+Inputs!B26>1,"OVER 100%",1-Inputs!B25-Inputs!B26))
A21: C. Actual costs and residual — profit/reinvestment only after verified costs
A22: Verified direct-cost subtotal | B22: =IF(OR(Inputs!B18="",Inputs!B19="",Inputs!B20="",Inputs!B21="",Inputs!B30=""),"TBD",SUM(Inputs!B18:B21,Inputs!B30))
A23: Residual after verified costs | B23: =IF(OR(Inputs!B16="",Inputs!B17="",Inputs!B18="",Inputs!B19="",Inputs!B20="",Inputs!B21="",Inputs!B30=""),"TBD",Inputs!B17-SUM(Inputs!B18:B21,Inputs!B30))
A24: Residual state | B24: =IF(B23="TBD","TBD",IF(B23<0,"OVER BUDGET",IF(B23=0,"NO RESIDUAL","POSITIVE RESIDUAL")))
A25: Approved share / reinvestment amount | B25: =IF(OR(B23="TBD",Inputs!B22=""),"TBD",IF(Inputs!B22>Inputs!B12,"REVIEW: above unapproved ceiling",IF(B23<=0,"NO POSITIVE RESIDUAL",B23*Inputs!B22)))
A26: Optional community-service runway ceiling | B26: =IF(Inputs!B23="","TBD",Inputs!B23*Inputs!B15)
A27: Optional SaaS operating cost input | B27: =IF(Inputs!B24="","TBD",Inputs!B24)
A29: D. Payment schedule check
A30: Payment shares: 1 / 2 / 3 | B30: =IF(OR(Inputs!B16="",Inputs!B17="",Inputs!B27=""),"TBD",SUM(Inputs!B27:B29))
A31: Payment schedule status | B31: =IF(OR(Inputs!B16="",Inputs!B17="",Inputs!B27=""),"TBD",IF(OR(Inputs!B27<0,Inputs!B27>1,AND(Inputs!B28<>"",OR(Inputs!B28<0,Inputs!B28>1)),AND(Inputs!B29<>"",OR(Inputs!B29<0,Inputs!B29>1))),"CHECK SHARE RANGE",IF(AND(Inputs!B29<>"",Inputs!B28=""),"PAYMENTS MUST BE IN ORDER",IF(SUM(Inputs!B27:B29)<>1,"CHECK TOTAL = 100%",IF(Inputs!B27<Inputs!B13,"ADVANCE BELOW MINIMUM","OK — within 3-payment cap")))))
A33: Historical sensitivity uses USD company-directory rates and earlier package hours only; it is not the current budget. The UK contractor comparison below is shown separately in GBP. No market rate is selected as a project or partner rate.
A36: E. Market reference for discussion — not an input to the partner fee or client budget
A37: Jurisdiction | B37: Comparator class | C37: Low (source) | D37: High (source) | E37: Source unit | F37: Low normalized | G37: High normalized | H37: Normalized unit | I37: Formula / limitation | J37: Source and period
A38: United Kingdom | B38: Clutch provider-company rate | C38: Unknown | D38: Unknown | E38: USD/provider-hour | F38: — | G38: — | H38: Not available | I38: Clutch country-level provider data is explicitly Unknown; no UK agency rate is imputed. | J38: Source page
A39: United Kingdom | B39: Lorien software-engineer contractors | C39: =Market_Comparison!C8 | D39: =Market_Comparison!D8 | E39: GBP/contractor-day | F39: =Market_Comparison!F8 | G39: =Market_Comparison!G8 | H39: GBP/contractor-hour | I39: Normalize as GBP/contractor-day ÷ 7.5 hours/day; this is not an all-in provider-company price. | J39: Source page
A40: United States | B40: Clutch software-development provider companies | C40: =Market_Comparison!C5 | D40: =Market_Comparison!D5 | E40: USD/provider-hour | F40: — | G40: — | H40: USD/provider-hour | I40: Directory band only; not a matched supplier quote. No FX conversion to GBP. | J40: Source page
A41: Ukraine | B41: Clutch software-development provider companies | C41: =Market_Comparison!C6 | D41: =Market_Comparison!D6 | E41: USD/provider-hour | F41: — | G41: — | H41: USD/provider-hour | I41: Directory band only; not a matched supplier quote. No FX conversion to GBP. | J41: Source page
A43: These are market comparators only. No project price is calculated from them. A client budget requires the reconciled scope, selected supplier quote, agreed partner fees, confirmed external costs and a contract currency; the UK contractor/day-rate class is not directly comparable to US/Ukraine provider-company listings.
A45: F. Existing demo module — partner fee to agree; payable only after first client payment is received
A46: Module / scope | B46: Agreed fee | C46: Currency | D46: Payment trigger | E46: Reuse condition | F46: First instalment amount (expected) | G46: Balance after fee if first instalment received | H46: Coverage check | I46: Decision status | J46: Input / caveat
A47: Search + group formation; excludes persistence, extended dossier and project management | B47: =IF(Inputs!B30="","TBD",Inputs!B30) | C47: =IF(Inputs!B30="","TBD",IF(Inputs!B16="","TBD",Inputs!B16)) | D47: Pay the demo author only after receipt of the first client payment. | E47: Only if this module is reused in the application; partners must agree fee and reuse boundary. | F47: =IF(OR(Inputs!B17="",Inputs!B27=""),"TBD",Inputs!B17*Inputs!B27) | G47: =IF(OR(Inputs!B17="",Inputs!B27="",Inputs!B30=""),"TBD",Inputs!B17*Inputs!B27-Inputs!B30) | H47: =IF(OR(Inputs!B17="",Inputs!B27="",Inputs!B30=""),"TBD",IF(Inputs!B17*Inputs!B27>=Inputs!B30,"Covered by first instalment","First instalment does not cover fee")) | I47: =IF(Inputs!B30="","PARTNER DECISION REQUIRED",IF(OR(Inputs!B16="",Inputs!B17="",Inputs!B27=""),"FEE ENTERED — COMPLETE CONTRACT INPUTS","FEE ENTERED — VERIFY AGREEMENT, REUSE AND RECEIPT")) | J47: Inputs!B30; amount intentionally blank until agreed. Expected instalment is not proof of receipt.
A49: Accounting rule: enter this one-time demo reuse fee separately in Inputs!B30 and exclude it from Inputs!B19. The fee is included once in verified direct costs/residual calculations when agreed; it is not an extra client charge on top of the agreed contract total. Do not treat the expected first instalment as received cash.

Sheet Source_Register
A1: Model-local source register — not the canonical project registry
A3: Code | B3: Value / formula | C3: Unit | D3: Period | E3: Status | F3: Origin / locator | G3: Formula / method | H3: Connectedness | I3: Limit / caveat | J3: Evidence tier/class
A4: EFFORT-LOW | B4: =Work_Packages!E18 | C4: person-hours | D4: one-time fixed-core slice | E4: [ASSUMPTION] | F4: Source pricing workbook > Core Estimate, rows 7–19 | G4: SUM low-hour inputs | H4: Rate sensitivity by low/base/high scope | I4: No reuse credit for current code; no schedule implied. | J4: Tier 5 — legacy internal assumption/source workbook
A5: EFFORT-BASE | B5: =Work_Packages!F18 | C5: person-hours | D5: one-time fixed-core slice | E5: [ASSUMPTION] | F5: Source pricing workbook > Core Estimate, rows 7–19 | G5: SUM base-hour inputs | H5: Rate sensitivity by low/base/high scope | I5: No reuse credit for current code; no schedule implied. | J5: Tier 5 — legacy internal assumption/source workbook
A6: EFFORT-HIGH | B6: =Work_Packages!G18 | C6: person-hours | D6: one-time fixed-core slice | E6: [ASSUMPTION] | F6: Source pricing workbook > Core Estimate, rows 7–19 | G6: SUM high-hour inputs | H6: Rate sensitivity by low/base/high scope | I6: No reuse credit for current code; no schedule implied. | J6: Tier 5 — legacy internal assumption/source workbook
A7: UA-RATE-LOW | B7: =Inputs!B4 | C7: USD/provider-hour | D7: Clutch published 2026 band | E7: Source-reported | F7: Clutch pricing guide, updated Sep 2026 | G7: Published country band endpoint | H7: Ukraine-rate sensitivity, not final fee | I7: Not a national floor or matched quote. | J7: Tier 4 — private provider directory
A8: UA-RATE-HIGH | B8: =Inputs!B5 | C8: USD/provider-hour | D8: Clutch published 2026 band | E8: Source-reported | F8: Clutch pricing guide, updated Sep 2026 | G8: Published country band endpoint | H8: Ukraine-rate sensitivity, not final fee | I8: Not a national ceiling or matched quote. | J8: Tier 4 — private provider directory
A9: US-RATE-LOW | B9: =Inputs!B6 | C9: USD/provider-hour | D9: Clutch published 2026 band | E9: Source-reported | F9: Clutch pricing guide, updated Sep 2026 | G9: Published country band endpoint | H9: US comparative sensitivity only | I9: Not a national floor or matched quote. | J9: Tier 4 — private provider directory
A10: US-RATE-HIGH | B10: =Inputs!B7 | C10: USD/provider-hour | D10: Clutch published 2026 band | E10: Source-reported | F10: Clutch pricing guide, updated Sep 2026 | G10: Published country band endpoint | H10: US comparative sensitivity only | I10: Not a national ceiling or matched quote. | J10: Tier 4 — private provider directory
A11: DEV-SHARE | B11: =TEXT(Inputs!B8,"0%")&"–"&TEXT(Inputs!B9,"0%") | C11: fraction of agreed budget | D11: per project | E11: User-stated target; uncontracted | F11: Current conversation | G11: 33%–50% target band | H11: Allocation scenario only | I11: Not fees or an approved contract split. | J11: User input/unapproved decision; no external tier
A12: OPS-SHARE | B12: =TEXT(Inputs!B10,"0%")&"–"&TEXT(Inputs!B11,"0%") | C12: fraction of agreed budget | D12: per project | E12: User-stated target; uncontracted | F12: Current conversation | G12: 33%–50% target band | H12: Allocation scenario only | I12: Not fees or an approved contract split. | J12: User input/unapproved decision; no external tier
A13: PROFIT-CEILING | B13: =Inputs!B12 | C13: fraction of positive residual | D13: post verified costs | E13: Unapproved decision; inactive | F13: Current conversation | G13: No distribution/reinvestment formula until approved | H13: Residual-profit decision only | I13: Not applied to project budget; denominator is not total contract. | J13: User input/unapproved decision; no external tier
A14: ADVANCE-MIN | B14: =Inputs!B13 | C14: fraction of contract total | D14: per contract | E14: User-approved constraint; uncontracted | F14: Current conversation | G14: Advance must be >= this share | H14: Payment schedule check | I14: Milestone shares remain TBD. | J14: User input/unapproved decision; no external tier
A15: PAYMENT-CAP | B15: =Inputs!B14 | C15: payments | D15: per contract | E15: User-approved constraint; uncontracted | F15: Current conversation | G15: At most this many installments | H15: Three payment input slots | I15: Does not set payment triggers. | J15: User input/unapproved decision; no external tier
A16: OPS-RUNWAY-CAP | B16: =Inputs!B15 | C16: calendar months | D16: post-launch support scenario | E16: User-stated cap; not funded | F16: Current conversation | G16: monthly operations cost × cap, once known | H16: Optional runway scenario | I16: No monthly cost or approval is assumed. | J16: User input/unapproved decision; no external tier
A17: DOSSIER-LOW | B17: =Revised_Scope!B27 | C17: possible dossiers (people) | D17: planning scenario | E17: [ASSUMPTION] user-provided range boundary | F17: Current user direction; possible 300–500 dossier cohort | G17: Lower scenario input = 300; no inference from group size or conversion | H17: Feeds dossier workload hours and variable-cost scenarios | I17: Not a verified expert count, reachable audience, opt-in count, or forecast. | J17: User-provided scenario/assumption
A18: DOSSIER-MID | B18: =Revised_Scope!B28 | C18: possible dossiers (people) | D18: planning scenario | E18: [ASSUMPTION] arithmetic midpoint | F18: Current user direction; possible 300–500 dossier cohort | G18: (300 + 500) / 2 = 400; formula in Revised_Scope!B28 | H18: Feeds dossier workload hours and variable-cost scenarios | I18: Midpoint is not a forecast or expected participation. | J18: User-provided scenario/assumption
A19: DOSSIER-HIGH | B19: =Revised_Scope!B29 | C19: possible dossiers (people) | D19: planning scenario | E19: [ASSUMPTION] user-provided range boundary | F19: Current user direction; possible 300–500 dossier cohort | G19: Upper scenario input = 500; no inference from group size or conversion | H19: Feeds dossier workload hours and variable-cost scenarios | I19: Not a verified expert count, reachable audience, opt-in count, or forecast. | J19: User-provided scenario/assumption
A20: TI-PREP-DAYS | B20: 2–3 | C20: working days | D20: preparation for Trust & Influence strategic session | E20: User-stated; not independently verified | F20: Current user direction | G20: 2–3 working days; hours shown only under explicit 8 h/day × 1 person assumptions in Partner_Effort. | H20: Separate partner consulting effort; excluded from dossier calculator | I20: Does not include the session, synthesis, model/protocol drafting, validation, or training. | J20: User-provided scenario/assumption
A21: UK-CLUTCH | B21: Unknown | C21: USD/provider-hour | D21: Clutch pricing guide updated 21 Sep 2026 | E21: Source-reported; unavailable | F21: https://clutch.co/developers/pricing | G21: UK country-level provider rate is explicitly Unknown; do not impute it. | J21: Tier 4 — provider directory
A22: UK-CTR-LOW | B22: 400 | C22: GBP/contractor-day | D22: Lorien 2026 guide | E22: Source-reported | F22: https://www.lorienglobal.com/insights/software-developer-contract-rates-in-the-uk | G22: Software engineer contractor range low endpoint; not an agency/provider quote. | J22: Tier 4 — contractor guide
A23: UK-CTR-HIGH | B23: 550 | C23: GBP/contractor-day | D23: Lorien 2026 guide | E23: Source-reported | F23: https://www.lorienglobal.com/insights/software-developer-contract-rates-in-the-uk | G23: Software engineer contractor range high endpoint; not an agency/provider quote. | J23: Tier 4 — contractor guide
A24: UK-WORKDAY | B24: 7.5 | C24: hours/contractor-day | D24: Lorien 2026 guide | E24: Source-reported conversion basis | F24: https://www.lorienglobal.com/insights/software-developer-contract-rates-in-the-uk | G24: Used only to normalize UK contractor day rate: GBP/day ÷ hours/day = GBP/hour. | J24: Tier 4 — contractor guide
A25: PRICING-UK-DDT | B25: Fixed / variable / outcome-based / hybrid selection by scope certainty | C25: Contract mechanism | D25: UK Digital, Data and Technology Playbook | E25: Official guidance | F25: https://www.gov.uk/government/publications/the-digital-data-and-technology-playbook/contracting-for-agile-guidance-note-html | G25: Supports matching payment model to scope certainty; not a claim of universal sector standard. | J25: Tier 3 — UK government guidance
A26: PRICING-US-FAR | B26: Fixed price when risk is predictable; consider alternatives or combinations when it is not | C26: Contract mechanism | D26: FAR 16.103; current page | E26: Official guidance | F26: https://www.acquisition.gov/far/16.103 | G26: Official US federal contracting guidance; cited for principles, not as a private-sector mandate. | J26: Tier 3 — US government guidance
A27: DEMO-MODULE-FEE | B27: =IF(Inputs!B30="","TBD",Inputs!B30) | C27: agreed contract currency; one-time per reused module | D27: after first client payment is received | E27: Partner decision required; amount not set | F27: Current user direction; partner agreement needed | G27: No rate or fee inferred; amount entered only after partners agree reuse boundary and fee | H27: Budget_Model fee/coverage check; included once in verified direct costs | I27: Applies only if search + group-formation module is reused; excludes persistence, extended dossier and project management. | J27: User decision/internal transfer
A28: UK-ITJW-P10 | B28: 389 | C28: GBP / contractor-day | D28: Six months to 2026-10-02 | E28: Source-reported; job-posting analytics | F28: https://www.itjobswatch.co.uk/contracts/uk/software%20engineer.do | G28: 10th percentile of 518 quoted daily rates | H28: UK contractor comparator only; not provider-company pricing | I28: Vacancy-posted day rate, not a partner fee, supplier quote or project cost. | J28: Tier 4 — job-posting analytics
A29: UK-ITJW-MEDIAN | B29: 555 | C29: GBP / contractor-day | D29: Six months to 2026-10-02 | E29: Source-reported; job-posting analytics | F29: https://www.itjobswatch.co.uk/contracts/uk/software%20engineer.do | G29: Median of 518 quoted daily rates | H29: UK contractor comparator only; not provider-company pricing | I29: Vacancy-posted day rate, not a partner fee, supplier quote or project cost. | J29: Tier 4 — job-posting analytics
A30: UK-ITJW-P90 | B30: 750 | C30: GBP / contractor-day | D30: Six months to 2026-10-02 | E30: Source-reported; job-posting analytics | F30: https://www.itjobswatch.co.uk/contracts/uk/software%20engineer.do | G30: 90th percentile of 518 quoted daily rates | H30: UK contractor comparator only; not provider-company pricing | I30: Vacancy-posted day rate, not a partner fee, supplier quote or project cost. | J30: Tier 4 — job-posting analytics
A31: UK-ONS-FT-MEDIAN | B31: 19.67 | C31: GBP/employee-hour | D31: April 2025 | E31: Tier 3 — national statistics | F31: https://www.ons.gov.uk/employmentandlabourmarket/peopleinwork/earningsandworkinghours/bulletins/annualsurveyofhoursandearnings/2025 | G31: Source median; no conversion. | H31: Context only, not a partner rate. | I31: Not contractor/provider price. | J31: Tier 3 — national statistics
A32: US-BLS-MGMT | B32: 48.97 | C32: USD/employee-hour | D32: May 2025 | E32: Tier 3 — government | F32: https://www.bls.gov/news.release/ocwage.t01.htm | G32: Source median hourly wage. | H32: Strategy/analysis analogue; not used in budget formulas. | I32: Employee wage, not consulting fee. | J32: Tier 3 — government
A33: US-BLS-PM | B33: 49.19 | C33: USD/employee-hour | D33: May 2025 | E33: Tier 3 — government | F33: https://www.bls.gov/news.release/ocwage.t01.htm | G33: Source median hourly wage. | H33: Project coordination analogue only. | I33: Employee wage, not PO contract rate. | J33: Tier 3 — government
A34: US-BLS-OPS | B34: 50.85 | C34: USD/employee-hour | D34: May 2025 | E34: Tier 3 — government | F34: https://www.bls.gov/news.release/ocwage.t01.htm | G34: Source median hourly wage. | H34: Operations analogue only. | I34: Not partner rate. | J34: Tier 3 — government
A35: US-BLS-TRAINING | B35: 33.31 | C35: USD/employee-hour | D35: May 2025 | E35: Tier 3 — government | F35: https://www.bls.gov/news.release/ocwage.t01.htm | G35: Source median hourly wage. | H35: Training analogue only. | I35: Not training quote. | J35: Tier 3 — government
A36: US-BLS-MARKET-RESEARCH | B36: 37.87 | C36: USD/employee-hour | D36: May 2025 | E36: Tier 3 — government | F36: https://www.bls.gov/news.release/ocwage.t01.htm | G36: Source median hourly wage. | H36: Research/comms analogue only. | I36: Not project quote. | J36: Tier 3 — government
A37: UA-DOU-SR-PM | B37: 3325 | C37: USD/month; survey-reported | D37: Dec 2025; senior IT PM | E37: Tier 4 — salary survey | F37: https://dou.ua/lenta/articles/salary-report-managers-winter-2026 | G37: Source median; kept monthly. | H37: Ukraine IT-sector comparator only. | I37: Not whole trusted-consultancy market or hourly. | J37: Tier 4 — salary survey
A38: UA-DOU-SR-PRODUCT | B38: 4000 | C38: USD/month; survey-reported | D38: Dec 2025; senior IT Product Manager | E38: Tier 4 — salary survey | F38: https://dou.ua/lenta/articles/salary-report-managers-winter-2026 | G38: Source median; kept monthly. | H38: Ukraine IT-sector comparator only. | I38: Not whole trusted-consultancy market or hourly. | J38: Tier 4 — salary survey
A39: UK-ASHE-ROLE-GAP | B39: Not populated | C39: not available | D39: ASHE Table 14; role values unverified | E39: Tier 3 source; no value verified | F39: https://www.ons.gov.uk/employmentandlabourmarket/peopleinwork/earningsandworkinghours/datasets/occupation4digitsoc2010ashetable14 | G39: No figure inserted; prior retrieval unavailable. | H39: Evidence gap only; not in calculations. | I39: Do not substitute all-worker median. | J39: Tier 3 source; no value verified
A40: TI-PREP-LOW | B40: =Partner_Effort!D6 | C40: person-hours | D40: one-time T&I preparation | E40: User input + [ASSUMPTION] | F40: Current direction; Partner_Effort!D6 | G40: 2 days × assumed 8 hours/day × 1 person = 16 hours. | H40: Track 1 preparation only; excludes other TI work. | I40: Confirm hours/day and person count. | J40: User input + [ASSUMPTION]
A41: TI-PREP-HIGH | B41: =Partner_Effort!F6 | C41: person-hours | D41: one-time T&I preparation | E41: User input + [ASSUMPTION] | F41: Current direction; Partner_Effort!F6 | G41: 3 days × assumed 8 hours/day × 1 person = 24 hours. | H41: Track 1 preparation only; excludes other TI work. | I41: Confirm hours/day and person count. | J41: User input + [ASSUMPTION]
A42: WORKDAY-HOURS | B42: =Inputs!B40 | C42: hours/working day | D42: TI conversion only | E42: [ASSUMPTION] | F42: Current direction; confirm | G42: Assumed 8 hours/day. | H42: Converts TI prep days only. | I42: Not agreed training duration. | J42: [ASSUMPTION]
A43: ANALYST-MIN | B43: =Inputs!B41 | C43: people | D43: staffing requirement | E43: User-stated | F43: Current direction | G43: At least one analyst. | H43: Staffing constraint only. | I43: No duration/cost implied. | J43: User-stated
A44: TRAINING-MAX-DAYS | B44: =Inputs!B42 | C44: working day | D44: one-time training | E44: User-stated cap | F44: Current direction | G44: Maximum one day. | H44: Planning cap only. | I44: Not a base-hours estimate. | J44: User-stated cap
A45: TRAINING-MAX-HOURS | B45: =Inputs!B43 | C45: hours; conditional cap | D45: one-time training | E45: [ASSUMPTION] formula | F45: Inputs!B40 × Inputs!B42 | G45: Assumed hours/day × stated maximum days. | H45: Cap only, not budgeted base hours. | I45: Confirm actual day length. | J45: [ASSUMPTION] formula

Sheet Legacy_Claims
A1: Legacy claim audit — reproducibility checks only; not a new quote
A3: A. Recompute the original DOU-to-hourly formula from the original document’s stated inputs
A4: Role | B4: Net USD/month | C4: Tax fraction | D4: ESV USD/month | E4: Hours/month | F4: EUR per USD | G4: Cost multiplier | H4: Source rate EUR/hour | I4: Recomputed EUR/hour | J4: Claim minus recomputed EUR/hour | K4: Total task hours | L4: Source cost EUR | M4: Recomputed cost EUR | N4: Cost difference EUR | O4: Evidence / scope status
A5: Solution Architect / Lead | B5: 5500 | C5: 0.05 | D5: 42 | E5: 168 | F5: 0.926 | G5: 1.35 | H5: 48.5 | I5: =(((B5*(1+C5)+D5)/E5)*F5*G5) | J5: =H5-I5 | K5: 130 | L5: =H5*K5 | M5: =I5*K5 | N5: =L5-M5 | O5: Source inputs/quoted rates; unverified assumptions
A6: Product & Security UX Designer | B6: 3200 | C6: 0.05 | D6: 42 | E6: 168 | F6: 0.926 | G6: 1.35 | H6: 30 | I6: =(((B6*(1+C6)+D6)/E6)*F6*G6) | J6: =H6-I6 | K6: 200 | L6: =H6*K6 | M6: =I6*K6 | N6: =L6-M6 | O6: Source inputs/quoted rates; unverified assumptions
A7: Senior Full-Stack Engineer | B7: 3500 | C7: 0.05 | D7: 42 | E7: 168 | F7: 0.926 | G7: 1.35 | H7: 32 | I7: =(((B7*(1+C7)+D7)/E7)*F7*G7) | J7: =H7-I7 | K7: 560 | L7: =H7*K7 | M7: =I7*K7 | N7: =L7-M7 | O7: Source inputs/quoted rates; unverified assumptions
A8: Frontend / WebGL Graph Engineer | B8: 3500 | C8: 0.05 | D8: 42 | E8: 168 | F8: 0.926 | G8: 1.35 | H8: 32 | I8: =(((B8*(1+C8)+D8)/E8)*F8*G8) | J8: =H8-I8 | K8: 300 | L8: =H8*K8 | M8: =I8*K8 | N8: =L8-M8 | O8: Source inputs/quoted rates; unverified assumptions
A9: Backend & Cryptography Engineer | B9: 3500 | C9: 0.05 | D9: 42 | E9: 168 | F9: 0.926 | G9: 1.35 | H9: 32 | I9: =(((B9*(1+C9)+D9)/E9)*F9*G9) | J9: =H9-I9 | K9: 420 | L9: =H9*K9 | M9: =I9*K9 | N9: =L9-M9 | O9: Source inputs/quoted rates; unverified assumptions
A10: DevOps & SecOps Infrastructure | B10: 3600 | C10: 0.05 | D10: 42 | E10: 168 | F10: 0.926 | G10: 1.35 | H10: 33.5 | I10: =(((B10*(1+C10)+D10)/E10)*F10*G10) | J10: =H10-I10 | K10: 110 | L10: =H10*K10 | M10: =I10*K10 | N10: =L10-M10 | O10: Source inputs/quoted rates; unverified assumptions
A11: QA / Compliance Verification | B11: 2500 | C11: 0.05 | D11: 42 | E11: 168 | F11: 0.926 | G11: 1.35 | H11: 24 | I11: =(((B11*(1+C11)+D11)/E11)*F11*G11) | J11: =H11-I11 | K11: 160 | L11: =H11*K11 | M11: =I11*K11 | N11: =L11-M11 | O11: Source inputs/quoted rates; unverified assumptions
A12: Project Delivery Manager | B12: 2800 | C12: 0.05 | D12: 42 | E12: 168 | F12: 0.926 | G12: 1.35 | H12: 26.5 | I12: =(((B12*(1+C12)+D12)/E12)*F12*G12) | J12: =H12-I12 | K12: 200 | L12: =H12*K12 | M12: =I12*K12 | N12: =L12-M12 | O12: Source inputs/quoted rates; unverified assumptions
A13: TOTAL / CROSS-CHECK | K13: =SUM(K5:K12) | L13: =SUM(L5:L12) | M13: =SUM(M5:M12) | N13: =SUM(N5:N12)
A15: ⚠ ASSUMPTION — Recalculation uses the original document’s own stated values (tax 5%, ESV USD 42, 168 hours/month, EUR/USD 0.926, multiplier 1.35). It tests arithmetic reproducibility only; it does not validate the inputs, tax treatment, exchange rate, source salaries, or the multiplier.
A17: B. Recompute the cited UK contractor day-rate band
A18: Low £/day | B18: High £/day | C18: Hours/day | D18: Recomputed low £/hour | E18: Recomputed high £/hour | F18: Claimed low £/hour | G18: Claimed high £/hour | H18: Check
A19: 650 | B19: 900 | C19: 7.5 | D19: =A19/C19 | E19: =B19/C19 | F19: 140 | G19: 200 | H19: Does not reconcile
A21: C. Evidence checks for selected legacy market claims
A22: Claim | B22: Fact-check / limit | C22: Status | D22: Primary source / locator
A23: BLS wage × 3 as typical supplier billing rate | B23: May 2023 OEWS confirms Software Developers mean wage USD 66.40/hour and 90th percentile USD 100.30/hour. These are employee wage estimates, not vendor rates. USD 66.40 × 3 = USD 199.20 is arithmetic only; BLS does not substantiate the 3.0 bill-rate multiplier. | C23: Wage verified; multiplier unsupported | D23: BLS OEWS May 2023, SOC 15-1252; BLS ECEC concepts
A24: “May 2023 / 2024” BLS period | B24: The cited URL is explicitly the May 2023 table. The year 2024 is not supported by that locator. | C24: Period mismatch | D24: https://www.bls.gov/oes/2023/may/oes151252.htm
A25: GLG filing identifier and disclosed scale | B25: The original gives CIK 0001878347; the GLG SEC S-1 filing located is CIK 1661123. That filing reports over 60,000 users across 2,700 subscription clients as of June 30, 2021; cited price/consultation-share claims lack a page/table locator in the original. | C25: Identifier mismatch; price claims unverified | D25: https://www.sec.gov/Archives/edgar/data/1661123/000119312521301055/d161028ds1.htm
A26: GLG “payback in 150–200 calls” | B26: Not reproducible as savings: platform price is EUR while consultation claims are USD; gross call price is not net avoided cost and omits expert payout and operating costs. | C26: Unsupported comparison | D26: Same GLG S-1 locator above; no FX, net-cost baseline, or calculation supplied
A27: Palantir “USD 55m average contract value” | B27: FY2023 Form 10-K instead reports average trailing-12-month revenue of USD 54.6m for its top twenty customers. This is not labeled average contract value and does not price a comparable ISRM contract. | C27: Metric mislabelled / not comparable | D27: https://www.sec.gov/Archives/edgar/data/1321655/000132165524000022/pltr-20231231.htm, Item 7, p. 66
A28: FPDS pilot contracts “from USD 1.2m” | B28: No award ID, agency, award date, solicitation or comparable scope is identified in the original; the minimum-price claim cannot be checked from the citation as written. | C28: Unverified | D28: No direct FPDS award locator supplied
A29: “Less than 16%” of USD 1.2m | B29: The numerator is EUR 198,270 and denominator USD 1,200,000. The original supplies no dated EUR/USD conversion for this comparison; same-currency arithmetic is therefore not established. | C29: Currency mismatch | D29: Original proposal §3.2; no applicable conversion source supplied
A30: UK consultant day rates vs hourly band | B30: The stated £650/7.5 and £900/7.5 equal exactly £260/3 and £120 per hour, not £140–£200/hour. The separately converted EUR totals also lack a dated FX locator. | C30: Arithmetic mismatch / FX unverified | D30: Original proposal §3.1 cites IT Jobs Watch; day-rate conversion shown in this sheet
A31: DOU-based direct-cost amounts | B31: The rate calculation and role-level quoted rates do not reconcile when the source’s own inputs are substituted; see Section A formulas and row-by-row deltas. | C31: Arithmetic mismatch; inputs unverified | D31: Original proposal §§2.2–2.3; DOU winter 2025 link cited there

Sheet Revised_Scope
A1: ISRM Expert Network — Revised Scope and Dossier Scenario Model
A2: Working model for partner review; not a client offer, confirmed estimate, or delivery commitment. Unknown effort and costs remain TBD. The historical 13-package estimate is preserved on its original sheets.
A4: A. Agreed scope and commercial treatment
A5: ID | B5: Workstream | C5: Agreed treatment / deliverables | D5: Effort or cost state | E5: Dependency / decision gate | F5: Origin / caveat
A6: DEMO-01 | B6: Completed demo module — search and group formation (no persistence, extended dossier, or project management) | C6: Treat the demo module as prior work with reuse value, not as free work and not as a full greenfield rebuild. If reused in the application, the agreed one-time fee is paid to its author only after receipt of the first client payment. Agree the fee and reuse boundary among partners; the amount remains blank until then. Do not add the internal transfer twice to the client price. | D6: Fee amount: TBD; partner decision required. | E6: Pay only if reused and only after the first client payment is received; enter one amount in Inputs!B30 and exclude it from Inputs!B19. | F6: User direction; no agreed fee amount or reliable historical time ledger is available.
A7: DEMO-02 | B7: Client-demo group formation, feature approval/configurator and proposal interactions | C7: User reports these interactions in the client-facing demo. The reviewed repository snapshot differs; reconcile the exact demo build before estimating. Do not infer missing features from the snapshot or count these as already production-ready. | D7: Reconciliation and reuse credit: TBD | E7: Confirm exact demo build and developer review. | F7: User-described demo versus reviewed repository snapshot; inventory mismatch remains open.
A8: SW-01 | B8: Residual production software | C8: Estimate only what remains: persistent named groups and expert-to-project assignments; project linkage and permissions; agreed workflow completion; production data/API, security, QA, deployment and any approved AI dossier workflow. Deduct reuse only where developers confirm it. | D8: Package-level hours and supplier quotes: TBD | E8: Reconcile exact build, acceptance criteria, data access and required configuration first. | F8: Separate from partner consulting and from historical greenfield hours.
A9: PART-01 | B9: Strategy and expert-engagement campaign | C9: Separate partner/consulting package: multiple strategic sessions; prioritize directions and expertise gaps; agree review criteria for existing experts; prepare member survey and campaign materials; run approved campaign; synthesize responses; report on possible links to referrals/membership, content, events, knowledge-base coverage and index capacity; assess application need and specific features. | D9: Session count, deliverables, partner hours and fee: TBD | E9: Client/board approval before selected experts are mobilized, knowledge base is populated, or experts work on indices. Set baselines and observation/attribution method before outcome calculations. | F9: Scope from user direction; no conversion, growth or causal outcome is forecast.
A10: PART-02 | B10: Trust & Influence preparation | C10: Preparation for the co-designed Trust & Influence strategic session was stated as 2–3 working days. This is not the complete model/protocol/training workstream. | D10: 16–24 conditional person-hours; formula: 2–3 working days × 8 hours/day × 1 person. | E10: The 8-hour workday and one-person basis are assumptions; confirm them before treating the hour range as agreed. The session, synthesis, model/protocol, validation and training remain separate TBD items. | F10: User-stated 2–3 working days; hour conversion is conditional on explicit 8 h/day × 1 person assumptions.
A11: PART-03 | B11: Trust & Influence model, protocol and orientation/training | C11: Co-design model and protocol with the client; define evidence classes, governance and correction/challenge process; then orient selected practice leaders and regional representatives. Do not present a sector-wide index as validated without an agreed validation design and evidence. | D11: Hours, participant count, validation and fee: TBD | E11: Agree ownership, group composition, training format and validation method. | F11: Separate from 2–3 preparation days and from the broader strategy/campaign package.
A12: PILOT-01 | B12: AI-assisted dossier preparation and human review | C12: A bounded AI-assisted preparation/triage capability is a candidate for the Base configuration given the possible 300–500-record workload. Measure human work by stage and obtain provider/model/usage pricing; AI does not replace human evidence review or client approval. | D12: Time per record, rates and AI/API unit cost: TBD | E12: Agree lawful sample, data access, output standard, privacy controls, human review and provider before pricing. | F12: User-provided potential workload; not a verified count of experts or participants.
A13: COMM-01 | B13: Possible paid community contributions | C13: Carry only as a note that participant/expert contributions may be paid. Do not assume contributor count, fee, revenue, offset, or reduction in client price. | D13: No calculation; amount and volume not assumed | E13: Separate feasibility, disclosure, consent and governance decisions. | F13: User-approved treatment: note only, no budget assumption.
A14: PAY-01 | B14: Proposed client payment milestones | C14: 30% / 40% / 30% is a discussion proposal, with each payment tied to deliverables and acceptance. The first instalment is at least 30%; final amounts depend on approved scope and price. | D14: Shares stated; contract amounts TBD | E14: Partner/client agreement and milestone acceptance criteria required. | F14: User-approved proposal constraint; not a sector standard or signed term.
A16: B. Measured dossier-workflow inputs — leave blank until measured or quoted
A17: Workflow stage | B17: Human minutes per dossier | C17: Labor rate (contract currency / person-hour) | D17: Status | E17: Source / measurement method | F17: Scope note
A18: Human effort for AI-assisted preparation (source gathering, prompting, editing/formatting) | D18: TBD — measure | E18: Permitted, consent-based pilot time study; record observed minutes by stage. | F18: Human labor only; machine latency is excluded.
A19: Human evidence review / verification | D19: TBD — measure | E19: Permitted, consent-based pilot time study; record observed minutes by stage. | F19: Do not treat AI-generated output as verified evidence.
A20: Correction, appeal and rework | D20: TBD — measure | E20: Measure actual rework across the cohort; use cohort-average minutes per dossier. | F20: No exception rate is assumed.
A21: Client decision / approval effort | D21: TBD — measure | E21: Measure review effort; document whether allocated per dossier or per batch. | F21: Per-dossier allocation is a model simplification to validate.
A22: AI provider/API usage cost per dossier | D22: TBD — quote | E22: Selected model/provider quote or metered pilot usage in the agreed contract currency. | F22: Do not infer from provider list prices without selected model and usage profile.
A25: C. Possible dossier workload scenarios — volume only until measured inputs are supplied
A26: Scenario | B26: Possible dossiers (people) | C26: AI-assisted prep hours | D26: Evidence review hours | E26: Correction / appeal hours | F26: Client approval hours | G26: Total human hours | H26: Human labor subtotal (contract currency) | I26: AI/API subtotal (contract currency) | J26: Combined measured subtotal (contract currency) | K26: Status
A27: Low volume | B27: 300 | C27: =IF(B18="","TBD",$B27*B18/60) | D27: =IF(B19="","TBD",$B27*B19/60) | E27: =IF(B20="","TBD",$B27*B20/60) | F27: =IF(B21="","TBD",$B27*B21/60) | G27: =IF(COUNT($B$18:$B$21)<4,"TBD",SUM(C27:F27)) | H27: =IF(OR(Inputs!$B$16="",COUNT($B$18:$B$21)<4,COUNT($C$18:$C$21)<4,G27="TBD"),"TBD",$B27/60*SUMPRODUCT($B$18:$B$21,$C$18:$C$21)) | I27: =IF(OR(Inputs!$B$16="",$B$22=""),"TBD",$B27*$B$22) | J27: =IF(OR(H27="TBD",I27="TBD"),"TBD",H27+I27) | K27: =IF(OR(G27="TBD",H27="TBD",I27="TBD"),"VOLUME SCENARIO ONLY — effort/rate/API inputs incomplete","SENSITIVITY ONLY — not a quote")
A28: Midpoint | B28: =AVERAGE(B27,B29) | C28: =IF(B18="","TBD",$B28*B18/60) | D28: =IF(B19="","TBD",$B28*B19/60) | E28: =IF(B20="","TBD",$B28*B20/60) | F28: =IF(B21="","TBD",$B28*B21/60) | G28: =IF(COUNT($B$18:$B$21)<4,"TBD",SUM(C28:F28)) | H28: =IF(OR(Inputs!$B$16="",COUNT($B$18:$B$21)<4,COUNT($C$18:$C$21)<4,G28="TBD"),"TBD",$B28/60*SUMPRODUCT($B$18:$B$21,$C$18:$C$21)) | I28: =IF(OR(Inputs!$B$16="",$B$22=""),"TBD",$B28*$B$22) | J28: =IF(OR(H28="TBD",I28="TBD"),"TBD",H28+I28) | K28: =IF(OR(G28="TBD",H28="TBD",I28="TBD"),"VOLUME SCENARIO ONLY — effort/rate/API inputs incomplete","SENSITIVITY ONLY — not a quote")
A29: High volume | B29: 500 | C29: =IF(B18="","TBD",$B29*B18/60) | D29: =IF(B19="","TBD",$B29*B19/60) | E29: =IF(B20="","TBD",$B29*B20/60) | F29: =IF(B21="","TBD",$B29*B21/60) | G29: =IF(COUNT($B$18:$B$21)<4,"TBD",SUM(C29:F29)) | H29: =IF(OR(Inputs!$B$16="",COUNT($B$18:$B$21)<4,COUNT($C$18:$C$21)<4,G29="TBD"),"TBD",$B29/60*SUMPRODUCT($B$18:$B$21,$C$18:$C$21)) | I29: =IF(OR(Inputs!$B$16="",$B$22=""),"TBD",$B29*$B$22) | J29: =IF(OR(H29="TBD",I29="TBD"),"TBD",H29+I29) | K29: =IF(OR(G29="TBD",H29="TBD",I29="TBD"),"VOLUME SCENARIO ONLY — effort/rate/API inputs incomplete","SENSITIVITY ONLY — not a quote")
A31: Formula: stage hours = possible dossier count × measured average human minutes per dossier for that stage ÷ 60. Human labor subtotal = dossier count ÷ 60 × SUM(stage minutes per dossier × stage hourly rate). AI/API subtotal = dossier count × quoted/measured AI cost per dossier. Currency is taken from Inputs!B16.
A32: Interpretation: 300 and 500 are user-provided possible workload bounds; 400 is their arithmetic midpoint, not a forecast. No processing minutes, hourly rates, or AI cost are prefilled, so hours and costs remain TBD until a permitted time study and supplier quote are entered. This calculator excludes software build, partner strategy/Trust & Influence work, hosting, legal/privacy, tax, and ongoing operations. Possible paid community contributions are noted only and are not netted against costs.
A33: Trust & Influence preparation is a separate user-stated input of 2–3 working days. Conditional conversion for one preparer at the assumed 8-hour day is 16–24 person-hours; the arithmetic midpoint is 20 hours, not measured effort or an agreed fee. Facilitation, synthesis, model/protocol drafting, validation and training remain separate TBD items. Do not reuse withdrawn 15/30/60-minute dossier examples.

Sheet Partner_Effort
A1: Partner consulting and delivery effort — line-item scope
A2: Working estimate scaffold, not a quotation. The only prefilled effort is Trust & Influence session preparation: user-stated 2–3 working days. Conditional conversion for one preparer at the assumed 8-hour day: 16–24 person-hours; midpoint 20 hours. This is preparation only; all other hours and rates remain TBD.
A4: A. Partner work packages and review responsibilities
A5: ID | B5: Deliverable / work package | C5: Proposed executor / reviewer | D5: 2-day conditional person-hours | E5: Arithmetic midpoint person-hours | F5: 3-day conditional person-hours | G5: Status / estimate basis | H5: Dependency / acceptance output
A6: TI-01 | B6: Prepare Trust & Influence strategic session | C6: Partner facilitator / preparation lead | D6: =2*Inputs!B40*Inputs!B41 | E6: =AVERAGE(D6,F6) | F6: =3*Inputs!B40*Inputs!B41 | G6: 16–24 conditional person-hours. Source: user-stated 2–3 working days; [ASSUMPTION] 8 h/day and one preparer. 20 hours is the arithmetic midpoint only, not measured effort or an agreed fee. | H6: Confirm workday length and number of preparers. Output: session brief, agenda, evidence questions and pre-read.
A7: TI-02 | B7: Facilitate Trust & Influence strategic session | C7: Partner facilitator with client sponsor; client/board participate | G7: TBD — session duration, format and participant count not set. | H7: Output: documented decisions, unresolved questions, and approved design principles.
A8: TI-03 | B8: Synthesize and document session decisions | C8: Partner facilitator / rapporteur; client validates | G8: TBD — hours and format not set. | H8: Output: decision log and next-step ownership, reviewed by client.
A9: TI-04 | B9: Co-design Trust & Influence index/model | C9: Partners and client jointly; client owns applicability decision | G9: TBD — construct, domains, evidence standards and validation scope not set. | H9: Output: versioned model and explicit limits; not a sector-validated standard absent validation.
A10: TI-05 | B10: Draft the assessment protocol, evidence rules and correction/appeal path | C10: Partners draft; client approves; designated reviewers apply | G10: TBD — evidence types, governance, correction workflow and validation effort not set. | H10: Output: repeatable protocol, audit trail, conflict handling and review criteria.
A11: TI-06 | B11: Select practice leaders and regional representatives for reviewer group | C11: Client/board selects; partners facilitate criteria and process | G11: TBD — number, selection criteria, availability and conflicts not set. | H11: Selection follows model/protocol draft; client/board approves participants.
A12: TI-07 | B12: Prepare training and materials for reviewer group | C12: Partner trainers; client confirms learning objectives | G12: TBD — baseline knowledge and curriculum depth unknown. | H12: Assess whether participants already know the material; size training accordingly.
A13: TI-08 | B13: Deliver reviewer orientation/training | C13: Partner trainers; selected practice leaders/regional representatives attend | G13: TBD — cohort size, duration, practice exercises and follow-up unknown. | H13: Output: attendees oriented to model/protocol; completion is not proof of sector-wide validity.
A14: TI-09 | B14: Apply model/protocol to expert reviews and adjudicate exceptions | C14: Selected trained practice leaders/regional representatives perform substantive review; partners coordinate QA; client/board retain policy decisions | G14: TBD — dossier count, review depth, sampling and escalation rules unknown. | H14: Human review only under approved protocol; separate evidence review from final client/board decisions.
A15: STR-01 | B15: Prepare and facilitate additional client strategy sessions | C15: Partner strategy lead; client sponsor and board as agreed | G15: TBD — number and duration of sessions beyond TI-01 not set. | H15: Output: prioritized strategic questions, decisions and owners.
A16: STR-02 | B16: Prioritize development directions and expertise gaps using the tool | C16: Partner facilitator with client/practice leads | G16: TBD — scope and number of domains not set. | H16: Output: ranked priorities with rationale; priorities are client decisions.
A17: STR-03 | B17: Set criteria and process to review existing network experts | C17: Partners propose; client approves; trained reviewers execute | G17: TBD — source data, criteria, sample and review effort not set. | H17: Output: approved review plan and evidence/consent boundaries.
A18: STR-04 | B18: Prepare community questionnaire and campaign materials | C18: Partner operations/communications; client privacy owner approves | G18: TBD — channel, notice, translations and assets not finalized. | H18: Output: approved survey and outreach pack; no distribution before privacy/channel approval.
... A23: OPS-03 | B23: Developer coordination, scope and acceptance | C23: Partner product owner; developer delivery lead; client accepts | G23: TBD — cadence and responsibility split versus supplier PM not agreed. | H23: Prevent double counting if delivery management is included in supplier quote.
A26: B. Effort roll-up and overhead ratio — calculate after estimates are supplied
A27: Metric | B27: Value / formula | C27: Unit | D27: Method / caveat
A28: Known conditional preparation — Low | B28: =SUM(D6:D6) | C28: person-hours | D28: Includes TI-01 only; one person and 8-hour workday assumptions.
A29: Known conditional preparation — High | B29: =SUM(F6:F6) | C29: person-hours | D29: Includes TI-01 only; one person and 8-hour workday assumptions.
A30: All other partner delivery hours | B30: TBD until line-item estimates are agreed | C30: person-hours | D30: Do not treat blank effort cells as zero.
A31: Developer delivery hours for same agreed scope | B31: TBD pending reconciled residual-software estimate | C31: person-hours | D31: Use the same scope boundary and exclude unrelated greenfield work.
A32: Project-specific partner/developer effort ratio | B32: TBD — partner delivery hours ÷ developer delivery hours | C32: ratio | D32: This ratio is an outcome of scoped estimates, not a norm; state its denominator when reporting.
A33: Partner share of combined delivery hours | B33: TBD — partner delivery hours ÷ (partner + developer hours) | C33: ratio | D33: Different denominator from partner/developer ratio; do not call either one general company overhead.
A34: Partner rate / fee basis | B34: TBD — partner agreement by role or deliverable | C34: contract currency/person-hour or fixed fee | D34: Rates and currency must be agreed and attributed; client-specific delivery effort is not hidden in general overhead.
A35: Supplier all-in quote comparison | B35: TBD — quote for same scope, acceptance, IP and support boundary | C35: contract currency / project | D35: Compare against verified developer direct costs + partner project fees + approved external expenses; difference does not identify overhead or margin separately.
A37: Rates currently shown on Inputs (Clutch provider-directory bands) are market-reference sensitivities for the historical 13-package estimate, not developer salaries, selected supplier rates or partner rates. Paid community contributions remain a note only: no contributor count, fee, gross amount, revenue, offset or client-price reduction is assumed.

Sheet Market_Comparison
A1: Market rate references — not a project quotation
A2: Country/provider-company listings and UK contractor day rates are different comparison classes. No scope hours, project totals, foreign-exchange conversion, or partner/developer quote is inferred here.
A4: Jurisdiction | B4: Comparator class | C4: Low (source) | D4: High (source) | E4: Source unit | F4: Low normalized | G4: High normalized | H4: Normalized unit | I4: Formula / limitation | J4: Source and period
A5: United States | B5: Clutch software-development provider companies | C5: 50 | D5: 99 | E5: USD/provider-hour | F5: =C5 | G5: =D5 | H5: USD/provider-hour | I5: Published band; directory benchmark, not a supplier quote or national floor/ceiling. | J5: Clutch pricing guide; updated 21 Sep 2026
A6: Ukraine | B6: Clutch software-development provider companies | C6: 25 | D6: 49 | E6: USD/provider-hour | F6: =C6 | G6: =D6 | H6: USD/provider-hour | I6: Published band; directory benchmark, not a supplier quote or national floor/ceiling. | J6: Clutch pricing guide; updated 21 Sep 2026
A7: United Kingdom | B7: Clutch country-level provider-company data | E7: USD/provider-hour | H7: Not available | I7: Clutch reports “Unknown”; no country-level provider rate is imputed. | J7: Clutch pricing guide; updated 21 Sep 2026
A8: United Kingdom | B8: Lorien software-engineer contractors (separate class) | C8: 400 | D8: 550 | E8: GBP/contractor-day | F8: =C8/7.5 | G8: =D8/7.5 | H8: GBP/contractor-hour | I8: Formula: GBP/contractor-day ÷ 7.5 hours/day. Contractor benchmark is not comparable to an all-in provider-company rate. | J8: Lorien 2026 UK contractor-rate guide
A9: United Kingdom | B9: IT Jobs Watch Software Engineer contractor vacancies (10th–90th percentile; not provider-company rate) | C9: =Source_Register!B28 | D9: =Source_Register!B30 | E9: GBP/contractor-day | F9: =C9/Source_Register!B24 | G9: =D9/Source_Register!B24 | H9: GBP/contractor-hour | I9: Published daily-rate percentiles ÷ Source_Register!B24 (7.5 hours/day from Lorien). Normalized comparison only; unlike provider-company pricing. | J9: IT Jobs Watch, six months to 2 Oct 2026; 518 daily rates; 10th / median / 90th: £389 / £555 / £750. https://www.itjobswatch.co.uk/contracts/uk/software%20engineer.do
A11: Pricing structures to discuss — selected to fit scope certainty, not asserted as a universal sector standard
A13: Structure | B13: Use when | C13: Proposed application here | D13: Controls / risks | E13: UK guidance | F13: US guidance | G13: Applicability / caveat
A14: Fixed price by accepted deliverable/milestone | B14: Scope, outputs, and acceptance criteria are sufficiently defined. | C14: Use for verified demo-readiness items or residual software packages only after code review and acceptance criteria are agreed. | D14: Change control; explicit exclusions; milestone acceptance must include security, accessibility, QA and handover where in scope. | E14: UK DDT Playbook | F14: US FAR 16.103 | G14: Use only for defined deliverables; no project price implied.
A15: Capped time and materials for discovery/pilot | B15: Effort or duration cannot yet be estimated with reasonable confidence. | C15: Use only for the bounded live dossier workflow measurement or discovery, with a not-to-exceed cap and stop/go approval. | D15: Named roles/rates; timesheets; approved activity; cap; review cadence; client oversight. T&M can weaken cost-efficiency incentives. | E15: UK Contracting for Agile | F15: US FAR Part 16 | G15: Pilot/discovery only with cap, tracking and client oversight.
A16: Hybrid: fixed known outcomes + capped variable work | B16: Some outputs are clear while research, operational throughput, or requirements remain uncertain. | C16: Separate defined build/partner deliverables from capped pilot measurement; re-estimate the residual scope from observed evidence. | D16: No hidden contingency; explicit variable-cost boundary; re-scope at decision gate; no double-counting partner effort. | E16: UK DDT Playbook | F16: US FAR 16.103 | G16: Derived proposal; terms and risk allocation require partner/client agreement.
A17: Outcome-linked / unit pricing after measurement | B17: Outcome/unit can be defined, attributed, measured and accepted without shifting uncontrolled risk. | C17: Consider per-dossier or outcome-linked pricing only after the live pilot establishes eligible units, quality criteria and review effort. | D17: No unverified productivity or conversion assumptions; define exclusions, rework and exception handling. | E17: UK DDT Playbook | F17: Not used | G17: Possible only after pilot makes the unit and acceptance criteria measurable.
A20: Budget variance is calculated only against a documented, agreed numeric whole-project reference in Inputs!B47 and only when scenario total, scope, currency and period match: (scenario whole-project total − agreed reference whole-project total) ÷ agreed reference whole-project total × 100%. Otherwise show TBD. Do not enter a blanket percentage or present effort/cost bounds as product-pricing tiers. Market-source rate bands remain separate comparator evidence, not project estimates.
A22: B. Role-related wage/provider references — distinct pricing classes; no FX conversion
A23: Jurisdiction | B23: Comparator class | C23: Role/service | D23: Low/value | E23: High | F23: Unit | G23: Period/population | H23: Method/type | I23: Source | J23: Limit/relevance
A24: United Kingdom | B24: Employee wage | C24: All full-time employees | D24: 19.67 | F24: GBP/employee-hour | G24: April 2025 | H24: Median | I24: https://www.ons.gov.uk/employmentandlabourmarket/peopleinwork/earningsandworkinghours/bulletins/annualsurveyofhoursandearnings/2025 | J24: Broad wage context only; not role-specific or partner fee.
A25: United Kingdom | B25: Contractor | C25: Software engineer day rate | D25: 400 | E25: 550 | F25: GBP/contractor-day | G25: 2026 guide | H25: Published range | I25: https://www.lorienglobal.com/insights/software-developer-contract-rates-in-the-uk | J25: Separate contractor class; existing normalization uses 7.5 hours/day.
A26: United States | B26: Provider-company | C26: Software development | D26: 50 | E26: 99 | F26: USD/provider-hour | G26: Clutch guide updated 2026-09-21 | H26: Published range | I26: https://clutch.co/developers/pricing | J26: Not individual salary or project quote.
A27: Ukraine | B27: Provider-company | C27: Software development | D27: 25 | E27: 49 | F27: USD/provider-hour | G27: Clutch guide updated 2026-09-21 | H27: Published range | I27: https://clutch.co/developers/pricing | J27: Not individual salary or project quote.
A28: United States | B28: Employee wage | C28: Management analysts | D28: 48.97 | F28: USD/employee-hour | G28: May 2025 | H28: Median | I28: https://www.bls.gov/news.release/ocwage.t01.htm | J28: Role analogue; not consulting fee.
A29: United States | B29: Employee wage | C29: Project management specialists | D29: 49.19 | F29: USD/employee-hour | G29: May 2025 | H29: Median | I29: https://www.bls.gov/news.release/ocwage.t01.htm | J29: Role analogue; not PO contract price.
A30: United States | B30: Employee wage | C30: General and operations managers | D30: 50.85 | F30: USD/employee-hour | G30: May 2025 | H30: Median | I30: https://www.bls.gov/news.release/ocwage.t01.htm | J30: Broad role analogue; not partner rate.
A31: United States | B31: Employee wage | C31: Training/development specialists | D31: 33.31 | F31: USD/employee-hour | G31: May 2025 | H31: Median | I31: https://www.bls.gov/news.release/ocwage.t01.htm | J31: Role analogue; not training quote.
A32: United States | B32: Employee wage | C32: Market research/marketing specialists | D32: 37.87 | F32: USD/employee-hour | G32: May 2025 | H32: Median | I32: https://www.bls.gov/news.release/ocwage.t01.htm | J32: Role analogue; not project quote.
A33: Ukraine | B33: IT-sector survey salary | C33: Senior Project Manager | D33: 3325 | F33: USD/month; reported salary | G33: Dec 2025 | H33: Median; senior IT role | I33: https://dou.ua/lenta/articles/salary-report-managers-winter-2026 | J33: Survey context; not all-sector or hourly.
A34: Ukraine | B34: IT-sector survey salary | C34: Senior Product Manager | D34: 4000 | F34: USD/month; reported salary | G34: Dec 2025 | H34: Median; senior IT role | I34: https://dou.ua/lenta/articles/salary-report-managers-winter-2026 | J34: Survey context; not all-sector or hourly.
A35: United Kingdom | B35: Data gap | C35: Role-specific occupational wage | D35: Not populated | F35: Not available | G35: ONS ASHE Table 14 | H35: No figure inserted | I35: https://www.ons.gov.uk/employmentandlabourmarket/peopleinwork/earningsandworkinghours/datasets/occupation4digitsoc2010ashetable14 | J35: Prior role-table retrieval unavailable; do not substitute broad median.
A38: C. Three-way commercial comparison — identical scope/acceptance boundaries only
A39: Option | B39: Cost basis | C39: Required scope parity | D39: What it supports | E39: What it cannot isolate
A40: 1. Direct supplier cost | B40: Residual developer/vendor cost. | C40: Same requirements, data/access, QA/security, IP, deployment and support. | D40: Technical baseline. | E40: Excludes partner work and verified external spend.
A41: 2. Separate partner work + external spend | B41: Partner hours × agreed rates plus supplier quotes/verified direct costs. | C41: Same scope, roles, deliverables, acceptance and exclusions. | D41: Transparent cost-to-deliver; partner client work stays explicit. | E41: No final price until inputs agreed.
A42: 3. Boutique/all-in proposal | B42: All-in quote for same scope/outcomes/risk. | C42: Same acceptance, IP, data rights, schedule, support and change control. | D42: Commercial alternative. | E42: Difference versus 1+2 is combined overhead/commercial/margin effect; cannot isolate components.
A44: No partner rate is inferred from these benchmarks. Inputs!B33:B39 remain blank for partner completion; currencies/classes are not converted or combined.

Sheet Project_Gantt
A1: ISRM PILOT — SEQUENTIAL DELIVERY GANTT
A2: Relative work-week schedule; tracks are sequential. Durations, handoff lags, hours, rates and fees are not yet evidenced and remain TBD.
A3: Enter approved inputs in yellow cells. Blank/TBD is not zero. Start/finish formulas populate only when required duration and handoff inputs are numeric.
A5: Seq | B5: Delivery track / gate | C5: Scope and deliverables | D5: Entry dependency | E5: Acceptance / decision gate | F5: Partner effort (person-hours) | G5: Developer/vendor effort (person-hours) | H5: Duration (working weeks) | I5: Handoff / approval lag before row (weeks) | J5: Start week (relative) | K5: Finish week (relative) | L5: Fee status | M5: Tranche / decision trigger | N5: KPI / evidence | O5: Assumptions / limits
A6: 1 | B6: Strategy, consulting & reports | C6: Member-needs survey; diagnostic/capacity report; co-design Trust & Influence model/protocol; strategy sessions; expertise priorities/gaps; select and orient reviewers. | D6: Sponsor, survey purpose, participants, privacy and distribution route approved. | E6: Client/board accepts diagnostic, priorities, T&I scope and application requirements. | F6: TBD — known preparation input is 16–24 person-hours for 2–3 workdays × 8 hours × 1 person; this is not total Track 1 effort. | G6: TBD — only discovery if separately commissioned. | H6: TBD | I6: TBD | J6: =1 | K6: =IF(AND(ISNUMBER(J6),ISNUMBER(H6),H6>0),J6+H6-1,"TBD") | L6: TBD — partner rates/fees not agreed. | M6: Gate 1: acceptance of diagnostic and strategy outputs; amount TBD. | N6: Valid completed responses / unique invitees only if denominator is measurable; decisions accepted. | O6: LinkedIn group membership is not survey reach or response denominator.
A7: 2 | B7: Functional integrated application | C7: Residual MVP: persist groups and expert/project links; roles/access, consent/audit, service request and acceptance workflows; verify exact demo reuse. | D7: Track 1 requirements accepted; demo build and data rules inventoried. | E7: UAT scenarios accepted; persistence and access boundaries verified. | F7: TBD — separate partner product/acceptance effort. | G7: TBD — feature estimate and supplier quote required. | H7: TBD | I7: TBD | J7: =IF(AND(ISNUMBER(K6),ISNUMBER(I7)),K6+I7+1,"TBD") | K7: =IF(AND(ISNUMBER(J7),ISNUMBER(H7),H7>0),J7+H7-1,"TBD") | L7: TBD — partner fees + supplier quote + approved expenses. | M7: Gate 2: acceptance of integrated MVP; amount TBD. | N7: Accepted UAT scenarios / agreed UAT scenarios; report critical defects separately. | O7: Reuse credited only after developers verify exact build and boundary.
A8: 3 | B8: Analytics, data & knowledge | C8: Data governance/provenance; research workflow; governed dataset; knowledge base; dashboard and agreed insights. | D8: Track 2 data/workflow accepted; data rights, owners and metric definitions approved. | E8: Lineage, access/refresh rules and outputs accepted with limitations visible. | F8: TBD — data governance, research and analytics effort. | G8: TBD — data model, pipeline, dashboard and KB estimate required. | H8: TBD | I8: TBD | J8: =IF(AND(ISNUMBER(K7),ISNUMBER(I8)),K7+I8+1,"TBD") | K8: =IF(AND(ISNUMBER(J8),ISNUMBER(H8),H8>0),J8+H8-1,"TBD") | L8: TBD — partner fees + supplier quote + approved expenses. | M8: Gate 3: acceptance of data and analytics package; amount TBD. | N8: Source/rights completeness, refresh period and metric definitions recorded; targets set by client. | O8: Do not merge channel, membership and CRM denominators without authority and deduplication.
A9: 4 | B9: Communications, publications & events | C9: Approved activation campaigns; editorial pipeline; expert discussions/events; conference preparation and media outreach. | D9: Tracks 1–3 accepted; channels authorized; opt-in/privacy and funding decisions documented. | E9: Campaign/event results reported by channel; conference spend only after funding approval. | F9: TBD — campaign, editorial and event operations effort. | G9: TBD — workflow/integration estimate if required. | H9: TBD | I9: TBD | J9: =IF(AND(ISNUMBER(K8),ISNUMBER(I9)),K8+I9+1,"TBD") | K9: =IF(AND(ISNUMBER(J9),ISNUMBER(H9),H9>0),J9+H9-1,"TBD") | L9: TBD — partner fees + supplier quote + approved expenses. | M9: Gate 4: pilot/campaign acceptance; separate conference funding approval. | N9: Reach, response, opt-in, participation and attendance measured separately by channel. | O9: ~11,700 LinkedIn memberships is unverified user-reported information, not reach or forecast; 10-media outreach is an objective, not guaranteed placement.
A10: 4A | B10: Pilot evaluation & continuation gate | C10: Evaluate observed evidence; record stop/continue decision and public, client-only, internal or SaaS direction; approve scope/funding for Track 5. | D10: Track 4 evidence and agreed baseline available. | E10: Written client/board go/no-go, access model, funding and product-scope decision. | F10: TBD — synthesis and decision facilitation. | G10: TBD — only if technical evaluation is commissioned. | H10: TBD | I10: TBD | J10: =IF(AND(ISNUMBER(K9),ISNUMBER(I10)),K9+I10+1,"TBD") | K10: =IF(AND(ISNUMBER(J10),ISNUMBER(H10),H10>0),J10+H10-1,"TBD") | L10: TBD — no future development fee assumed before approval. | M10: Gate 4A: written go/no-go and funding/access decision. | N10: Observed baseline-to-follow-up metrics only; no causal/revenue claim without evaluation design. | O10: Community contributions/donations are not confirmed funding or client-price offsets.
A11: 5 | B11: AI, OSINT & chatbot (conditional) | C11: Bounded assistant over approved knowledge; permitted OSINT sources; citations, audit, human review, evaluation and correction path. | D11: Track 4 gate approves continuation; Track 3 knowledge base and source/data rights ready. | E11: Agreed evaluation thresholds pass; review, incident and rollback procedures accepted. | F11: TBD — governance, evaluation and human-review effort. | G11: TBD — provider/model/integration and usage quote required. | H11: TBD | I11: TBD | J11: =IF(AND(ISNUMBER(K10),ISNUMBER(I11)),K10+I11+1,"TBD") | K11: =IF(AND(ISNUMBER(J11),ISNUMBER(H11),H11>0),J11+H11-1,"TBD") | L11: TBD — optional track; no API/provider costs assumed. | M11: Gate 5: accepted bounded AI pilot and separate continuation decision. | N11: Pre-agreed test set and thresholds for source support, errors and human override; values TBD. | O11: AI output is not identity/credential verification; no scraping or automated LinkedIn actions assumed.
